Workbook

Sheet Leeme
A1: Curvas de costo CAPEX colombianizadas — solar, almacenamiento e híbrido
A2: Versión 3 · modelo bottom-up por componente, recalibrado con las cotizaciones de suministro y la tabla de rangos de octubre de 2025
A4: Qué cambió frente a la versión anterior | B4: Tres correcciones de fondo. La curva solar ya no se ajusta a cotizaciones sueltas de alcances distintos: se ancla en la tabla de rangos de octubre de 2025, que cubre los cuatro tramos de escala con un mismo alcance Full EPC y una misma fecha. El suministro de baterías dejó de escalar con la potencia: dos ofertas para el mismo proyecto, una a 0,5C y otra a 0,25C, tienen precio idéntico. Y la energía instalada se separó de la energía nominal, porque el sobredimensionamiento cambia mucho entre servicios.
A5: El suministro de baterías se cotiza por energía, no por potencia | B5: En S-1, las opciones de 0,5C con 10 MW y de 0,25C con 5 MW tienen exactamente el mismo precio: 2.191.375 USD por 25,06 MWh. En la arquitectura de bloque AC el PCS viene embebido y el número de bloques lo fija la energía. Por eso el modelo cobra el suministro por kWh instalado y no por kW, hasta el límite de C-rate del producto. Por encima de ese límite aparece una prima, que se estima con S-3.
A6: Energía instalada frente a energía nominal | B6: Un sistema aislado que cicla profundo todos los días durante veinte años, sin contrato de aumentación, necesita bastante más energía instalada que la garantizada. En R1 son 40 MWh instalados para 25 MWh útiles, un factor de 1,60. En S-1 son 25,06 para 20, un factor de 1,25. El modelo pide el factor explícitamente porque cambia el CAPEX en la misma proporción.
A7: Colombianización | B7: El CAPEX se separa en contenido global —celda, contenedor, PCS, módulo, inversor, estructura, transformación— que se compra al precio mundial, y contenido local —obra civil, montaje, conexión, ingeniería, pólizas, impuestos, margen— que responde a costos colombianos. Las cotizaciones fijan el nivel de ambos bloques y las fuentes internacionales fijan la pendiente de cada uno por separado.
A8: Qué se corrigió del diagnóstico anterior | B8: Al descomponer R2 línea por línea resultó que su obra civil por kWp es prácticamente igual a la del proyecto de 130 MWp: la razón es 0,97. La explicación de obras de inundabilidad era equivocada. La diferencia real está en transformación, con razón 2,81 por usar dos transformadores de potencia en lugar de centros de transformación distribuidos, y en BOP con montaje, con razón 1,98. Y con la tabla de rangos a la vista, R2 no es un dato atípico: cae dentro de la banda de 800 a 900 para su tramo. El atípico es la oferta de 130 MWp, veinte por ciento por debajo de la banda de su tramo.
A9: Estado de la evidencia | B9: Sólido: el desglose de R3 en doce componentes, que suma exactamente el subtotal de la hoja original; la coincidencia de S-1 con el contenedor de R3 en unos 88 USD/kWh; el ajuste de la tabla de rangos con R² de 0,98, sobre el que R2 cae con 0,1 % de error; y la predicción de R1 con 0,1 % una vez confirmados los 40 MWh instalados. Débil: la prima por C-rate, que descansa en un solo punto que además puede traer formación de red; el tramo de 50 a 100 MWp, que la tabla de rangos no cubre; y los segmentos B1 y B2 de almacenamiento, donde el costo de potencia local y el fijo se escogieron por criterio.
A10: Lo que sigue faltando | B10: Una cotización propia de almacenamiento por encima de 4 h, para verificar que el suministro plano por kWh se sostiene a 6 y 8 h. Una cotización solar entre 50 y 100 MWp. Y separar, en S-3, cuánto de la prima es C-rate y cuánto es capacidad de formación de red y regulación primaria de frecuencia.
A11: Codificación de las cotizaciones | B11: Todas las referencias están anonimizadas. R1: híbrido solar más almacenamiento en sitio aislado, con generación diésel de respaldo. R2: planta solar de 8 MWp con línea de interconexión dedicada, la única con desglose completo línea por línea. R3: almacenamiento standalone de 10 MW y 40 MWh, la cotización EPC más granular y más reciente. R4: híbrido de gran escala, 130 MWp más 360 MWh, oferta no vinculante de proveedor de enero de 2025. R5, R6 y R7: benchmark interno de mercado para almacenamiento en baja, media y alta tensión. S-1, S-2 y S-3: cotizaciones de suministro de baterías únicamente, sin obra civil, montaje ni comisionamiento.
A12: Convenciones | B12: Base full costo con margen. USD constantes de 2026. Solar en USD por kWp DC. Almacenamiento en USD por kWh de energía nominal, con la duración siempre declarada. Celdas azules sobre amarillo son entradas; el resto son fórmulas.
A13: Fuentes de las trayectorias | B13: Cole, Ramasamy y Turan (2025), Cost Projections for Utility-Scale Battery Storage: 2025 Update, NREL/TP-6A40-93281, tabla 2 y figura 1. NREL Annual Technology Baseline, escenarios de innovación tecnológica para utility-scale y commercial PV. IRENA, Renewable Power Generation Costs in 2024, para la razón entre la caída del módulo y la de instalación, EPC y costos blandos. La separación de cada trayectoria en hardware y contenido local es construcción propia a partir de esas fuentes, no un dato publicado.

Sheet Suministro_BESS
A1: Calibración del suministro de baterías
A2: Solo baterías, sobre energía instalada. Tres cotizaciones independientes de proveedor
A4: Cotización | B4: Fecha | C4: Incoterm | D4: E instalada (MWh) | E4: P (MW) | F4: C-rate | G4: Valor (USD) | H4: USD/kWh instalado | I4: Ajuste a CIF | J4: USD/kWh CIF equiv.
A5: S-1 — bloque AC, oferta de proveedor | B5: oct-2025 | C5: CIF puerto de destino | D5: 25.06 | E5: 10 | F5: =E5/D5 -> 0.3990423 | G5: 2191375 | H5: =G5/(D5*1000) -> 87.445132 | I5: 0 | J5: =H5*(1+I5) -> 87.445132
A6: S-2 — contenedor, dentro de cotización EPC, antes del recargo del 6 % | B6: jun-2026 | C6: DAP | D6: 40 | E6: 10 | F6: =E6/D6 -> 0.25 | G6: 3526404 | H6: =G6/(D6*1000) -> 88.1601 | I6: 0 | J6: =H6*(1+I6) -> 88.1601
A7: S-3 — bloque AC de alto C-rate, oferta de proveedor | B7: mar-2026 | C7: FOB | D7: 151.06 | E7: 90 | F7: =E7/D7 -> 0.59578975 | G7: 17992344 | H7: =G7/(D7*1000) -> 119.10727 | I7: 0.05 | J7: =H7*(1+I7) -> 125.06263
A9: Las dos opciones de S-1 —0,5C con 10 MW y 0,25C con 5 MW— tienen precio idéntico. El suministro se cotiza por energía y el PCS viene embebido en el bloque AC. S-1 a 0,40C y el contenedor de R3 a 0,25C coinciden en unos 88 USD/kWh con ocho meses de diferencia: los precios de suministro se aplanaron después del primer semestre de 2025.
A11: Prima por C-rate sobre el suministro
A12: C-rate de quiebre | B12: Pendiente de la prima (por unidad de C) | C12: Prima a 0,60C | D12: Prima a 1,00C
A13: 0.5 | B13: 0.22 | C13: =1+MAX(0,0.6-A13)*B13 -> 1.022 | D13: =1+MAX(0,1-A13)*B13 -> 1.11
A15: S-3 cuesta 125,1 USD/kWh en CIF equivalente contra 87,4 de S-1: 43 % más por pasar de 0,50C a 0,60C. Esa pendiente sería de 4,30 por unidad de C, veinte veces la que se deduce de la física del equipo. El PCS pesa 11 % del bloque AC según la figura 1 del NREL, así que duplicar el C-rate de 0,50 a 1,00 solo agrega ese 11 %, o sea 0,22 por unidad de C. La conclusión es que la prima de S-3 casi no es C-rate: es un almacenamiento asociado a una central térmica en otro mercado, con toda probabilidad con requisitos de formación de red y de regulación primaria de frecuencia, y con otra fecha. El modelo usa la pendiente física, 0,22. Poner 4,30 en la celda reproduce el punto observado como límite superior.
A17: Sobredimensionamiento — energía instalada sobre energía nominal
A18: Tipo de servicio | B18: Factor | C18: Origen
A19: Arbitraje y servicios de red, con aumentación contratada | B19: 1.05 | C19: Supuesto
A20: Respaldo y desplazamiento de autoconsumo | B20: 1.25 | C20: S-1: 25,06 MWh instalados para 20 nominales
A21: Sistema aislado, ciclado profundo diario, sin aumentación | B21: 1.6 | C21: R1: 40 MWh instalados para 25 útiles, confirmado

Sheet Parametros_BESS
A1: Modelo de almacenamiento — parámetros por segmento
A2: CAPEX = (cSUP·prima(C)·E_inst + cE_loc·E_nom + cP_loc·P + cF) × (1+indirectos) × (1+EPC mgmt) ÷ (1−margen)
A4: Seg. | B4: Descripción | C4: Rango (MWh) | D4: cSUP (USD/kWh inst.) | E4: cE local (USD/kWh) | F4: cP local (USD/kW) | G4: cF (USD) | H4: Indir. | I4: EPC mgmt | J4: Margen | K4: Ancla | L4: P ancla (MW) | M4: E nom. (MWh) | N4: Factor sobredim. | O4: CAPEX ancla (USD) | P4: Modelo (USD) | Q4: Error
A5: B1 | B5: Baja tensión — gabinete comercial e industrial | C5: 0,1 – 1 | D5: 320.1 | E5: 5 | F5: 20 | G5: 15000 | H5: 0.054 | I5: 0.015 | J5: 0.2 | K5: R5 | L5: 0.15 | M5: 0.3 | N5: 1 | O5: 154500 | P5: =(D5*(1+MAX(0,L5/M5-Suministro_BESS!$A$13)*Suministro_BESS!$B$13)*M5*N5*1000+E5*M5*1000+F5*L5*1000+G5)*(1+H5)*(1+I5)/(1-J5) -> 154493.94 | Q5: =P5/O5-1 -> -3.9245146e-05
A6: B2 | B6: Media tensión — skid | C6: 1 – 20 | D6: 141.8 | E6: 5 | F6: 43.5 | G6: 200000 | H6: 0.054 | I6: 0.015 | J6: 0.2 | K6: R6 | L6: 5 | M6: 20 | N6: 1 | O6: 4485000 | P6: =(D6*(1+MAX(0,L6/M6-Suministro_BESS!$A$13)*Suministro_BESS!$B$13)*M6*N6*1000+E6*M6*1000+F6*L6*1000+G6)*(1+H6)*(1+I6)/(1-J6) -> 4484509.8 | Q6: =P6/O6-1 -> -0.00010929905
A7: B3 | B7: Media tensión — utility | C7: 20 – 100 | D7: 93.4 | E7: 5.35 | F7: 86.6 | G7: 526263 | H7: 0.054 | I7: 0.015 | J7: 0.2 | K7: R3 | L7: 10 | M7: 40 | N7: 1 | O7: 7146475 | P7: =(D7*(1+MAX(0,L7/M7-Suministro_BESS!$A$13)*Suministro_BESS!$B$13)*M7*N7*1000+E7*M7*1000+F7*L7*1000+G7)*(1+H7)*(1+I7)/(1-J7) -> 7144008 | Q7: =P7/O7-1 -> -0.00034520865
A8: B4 | B8: Alta tensión — utility grande | C8: > 100 | D8: 93.4 | E8: 5.35 | F8: 203.4 | G8: 900000 | H8: 0.054 | I8: 0.015 | J8: 0.2 | K8: R7 | L8: 20 | M8: 40 | N8: 1 | O8: 11926580 | P8: =(D8*(1+MAX(0,L8/M8-Suministro_BESS!$A$13)*Suministro_BESS!$B$13)*M8*N8*1000+E8*M8*1000+F8*L8*1000+G8)*(1+H8)*(1+I8)/(1-J8) -> 11925707 | Q8: =P8/O8-1 -> -7.3199945e-05
A10: cSUP se calibra como residuo dentro de cada segmento. En B3 y B4 coincide con el suministro medido en la hoja anterior, 93,4 USD/kWh, lo cual es una comprobación real. En B1 y B2 el costo de potencia local y el costo fijo se escogieron por criterio, así que su cSUP absorbe esa elección y no debe leerse como precio de suministro observado.
A12: Validación cruzada
A13: Punto | B13: Seg. | C13: P (MW) | D13: E nom. (MWh) | E13: Factor sobredim. | F13: E inst. (MWh) | G13: CAPEX real | H13: Modelo | I13: Error
A14: R4 — híbrido de gran escala | B14: B4 | C14: 90 | D14: 360 | E14: 1 | F14: =D14*E14 -> 360 | G14: 70179605 | H14: =(INDEX($D$5:$D$8,MATCH($B14,$A$5:$A$8,0))*(1+MAX(0,C14/D14-Suministro_BESS!$A$13)*Suministro_BESS!$B$13)*F14*1000+INDEX($E$5:$E$8,MATCH($B14,$A$5:$A$8,0))*D14*1000+INDEX($F$5:$F$8,MATCH($B14,$A$5:$A$8,0))*C14*1000+INDEX($G$5:$G$8,MATCH($B14,$A$5:$A$8,0)))*(1+INDEX($H$5:$H$8,MATCH($B14,$A$5:$A$8,0)))*(1+INDEX($I$5:$I$8,MATCH($B14,$A$5:$A$8,0)))/(1-INDEX($J$5:$J$8,MATCH($B14,$A$5:$A$8,0))) -> 73223145 | I14: =H14/G14-1 -> 0.043367877
A15: R1 — híbrido aislado | B15: B3 | C15: 6.25 | D15: 25 | E15: 1.6 | F15: =D15*E15 -> 40 | G15: 6610100 | H15: =(INDEX($D$5:$D$8,MATCH($B15,$A$5:$A$8,0))*(1+MAX(0,C15/D15-Suministro_BESS!$A$13)*Suministro_BESS!$B$13)*F15*1000+INDEX($E$5:$E$8,MATCH($B15,$A$5:$A$8,0))*D15*1000+INDEX($F$5:$F$8,MATCH($B15,$A$5:$A$8,0))*C15*1000+INDEX($G$5:$G$8,MATCH($B15,$A$5:$A$8,0)))*(1+INDEX($H$5:$H$8,MATCH($B15,$A$5:$A$8,0)))*(1+INDEX($I$5:$I$8,MATCH($B15,$A$5:$A$8,0)))/(1-INDEX($J$5:$J$8,MATCH($B15,$A$5:$A$8,0))) -> 6602416.7 | I15: =H15/G15-1 -> -0.0011623633
A17: R1 entra con los 40 MWh instalados confirmados. R4 queda por encima del modelo porque su oferta es de enero de 2025 con precios unitarios de proveedor, no un precio EPC en firme.

Sheet Parametros_PV
A1: Modelo solar — composición por componente y curva de escala
A2: CAPEX/kWp = (HW·(S/8)^bHW + LOC·(S/8)^bLOC + conexión) × factor de indirectos, IVA y AIU
A4: Composición a 8 MWp — desglose línea por línea de la cotización R2, en USD/kWp DC sin IVA ni AIU
A5: Componente | B5: Contenido | C5: USD/kWp | D5: Razón frente a 130 MWp
A6: Módulos | B6: Global | C6: 154.3 | D6: 1.27
A7: Estructura, hincas, correas y omegas | B7: Global | C7: 67.1 | D7: 1.31
A8: Inversores string | B8: Global | C8: 21.9 | D8: 1.15
A9: Transformación MT | B9: Global | C9: 61.8 | D9: 2.81
A10: BOP eléctrico: cables DC y AC, SPT, monitoreo, CCTV, fibra | B10: Global | C10: 41.8 | D10: —
A11: Montaje electromecánico | B11: Local | C11: 87.1 | D11: —
A12: Obra civil y eléctrica | B12: Local | C12: 92.1 | D12: 0.97
A13: Ingeniería y estudios | B13: Local | C13: 13.3 | D13: 0.79
A14: Comisionamiento y puesta en marcha | B14: Local | C14: 16.3 | D14: —
A15: Repuestos, pólizas, cerramiento y otros | B15: Local | C15: 34.7 | D15: —
A16: Hardware global (HW) | C16: =SUMIF($B$6:$B$15,"Global",$C$6:$C$15) -> 346.9
A17: Contenido local (LOC) | C17: =SUMIF($B$6:$B$15,"Local",$C$6:$C$15) -> 243.5
A18: Línea de interconexión, subestación y bahía CPM (CNX) | C18: 48.8
A19: Total a 8 MWp | C19: =C16+C17+C18 -> 639.2
A20: Factor de indirectos, IVA no descontable y AIU | C20: 1.2719
A21: Precio a 8 MWp | C21: =C19*C20 -> 812.99848
A23: La obra civil por kWp es prácticamente igual en las dos cotizaciones: razón de 0,97. La diferencia entre el proyecto de 8 MWp y el de 130 MWp está en transformación, con razón 2,81 por usar dos transformadores de potencia en lugar de centros de transformación distribuidos, y en BOP con montaje, con razón 1,98.
A25: Anclas de escala — rangos de mercado, octubre de 2025, alcance Full EPC con 5 km de línea MT
A26: Tramo | B26: MWp de referencia | C26: Inferior (USD/MWp) | D26: Superior (USD/MWp) | E26: Punto medio (USD/kWp) | F26: Modelo (USD/kWp) | G26: Error
A27: 1 – 10 MW | B27: 5 | C27: 800000 | D27: 900000 | E27: =(C27+D27)/2000 -> 850 | F27: =(Parametros_PV!$C$16*(B27/8)^$C$33+Parametros_PV!$C$17*(B27/8)^$C$34+Parametros_PV!$C$18)*Parametros_PV!$C$20 -> 841.05064 | G27: =F27/E27-1 -> -0.010528653
A28: 10 – 20 MW | B28: 15 | C28: 750000 | D28: 800000 | E28: =(C28+D28)/2000 -> 775 | F28: =(Parametros_PV!$C$16*(B28/8)^$C$33+Parametros_PV!$C$17*(B28/8)^$C$34+Parametros_PV!$C$18)*Parametros_PV!$C$20 -> 777.10863 | G28: =F28/E28-1 -> 0.0027208182
A29: 20 – 50 MW | B29: 32 | C29: 700000 | D29: 750000 | E29: =(C29+D29)/2000 -> 725 | F29: =(Parametros_PV!$C$16*(B29/8)^$C$33+Parametros_PV!$C$17*(B29/8)^$C$34+Parametros_PV!$C$18)*Parametros_PV!$C$20 -> 736.20214 | G29: =F29/E29-1 -> 0.015451224
A30: > 100 MW | B30: 130 | C30: 650000 | D30: 700000 | E30: =(C30+D30)/2000 -> 675 | F30: =(Parametros_PV!$C$16*(B30/8)^$C$33+Parametros_PV!$C$17*(B30/8)^$C$34+Parametros_PV!$C$18)*Parametros_PV!$C$20 -> 666.79983 | G30: =F30/E30-1 -> -0.012148404
A33: Exponente de escala del hardware (bHW) | C33: -0.0906
A34: Exponente de escala del contenido local (bLOC) | C34: -0.06
A35: Validación — oferta R4 a 130 MWp, con su línea de 34,5 kV | C35: 531
A36: Diferencia frente al modelo | C36: =C35/F30-1 -> -0.20365906
A38: La oferta de 130 MWp queda cerca de veinte por ciento por debajo de la banda de su tramo. Es una oferta no vinculante de proveedor de enero de 2025, con indirectos del 4 % y margen embebido en los unitarios, no un precio EPC en firme. Entra como validación, no como ancla.

Sheet Trayectorias
A1: Trayectorias de costo por componente
A2: Índices reales en USD constantes, base 2026 = 1,00
A4: Componente | B4: Fuente | C4: Bajo 2026-2035 | D4: Medio 2026-2035 | E4: Alto 2026-2035 | F4: Bajo 2035-2050 | G4: Medio 2035-2050 | H4: Alto 2035-2050
A5: Suministro de baterías | B5: NREL/TP-6A40-93281, tabla 2, índice del sistema de 4 h | C5: -0.0745 | D5: -0.029 | E5: -0.0084 | F5: -0.0662 | G5: -0.021 | H5: -0.0068
A6: Hardware solar — utility | B6: NREL ATB, escenarios de innovación, utility-scale PV | C6: -0.1234 | D6: -0.0788 | E6: -0.0394 | F6: -0.0206 | G6: -0.0287 | H6: -0.0302
A7: Hardware solar — comercial | B7: NREL ATB, escenarios de innovación, commercial PV | C7: -0.0958 | D7: -0.0531 | E7: -0.0121 | F7: -0.0215 | G7: -0.03 | H7: -0.0316
A8: Contenido local | B8: NREL ATB e IRENA 2024, instalación, EPC y costos blandos | C8: -0.0317 | D8: -0.0199 | E8: -0.0098 | F8: -0.0051 | G8: -0.0071 | H8: -0.0075
A10: La versión anterior aplicaba las tasas de utility a todos los tramos solares. El ATB publica una trayectoria distinta para commercial PV, bastante más plana, y es la que corresponde a los proyectos por debajo de 10 MWp.
A11: Los precios de suministro de baterías se aplanaron entre octubre de 2025 y junio de 2026, según S-1 y el contenedor de R3. Eso afecta la reconstrucción hacia atrás, no la proyección hacia adelante, que arranca en 2026 con el índice del NREL.
A13: Índices anuales
A14: Año | B14: Batería Bajo | C14: Batería Medio | D14: Batería Alto | E14: Solar util. Bajo | F14: Solar util. Medio | G14: Solar util. Alto | H14: Solar com. Bajo | I14: Solar com. Medio | J14: Solar com. Alto | K14: Local Bajo | L14: Local Medio | M14: Local Alto
A15: 2026 | B15: =IF($A15<=2035,(1+$C$5)^($A15-2026),(1+$C$5)^9*(1+$F$5)^($A15-2035)) -> 1 | C15: =IF($A15<=2035,(1+$D$5)^($A15-2026),(1+$D$5)^9*(1+$G$5)^($A15-2035)) -> 1 | D15: =IF($A15<=2035,(1+$E$5)^($A15-2026),(1+$E$5)^9*(1+$H$5)^($A15-2035)) -> 1 | E15: =IF($A15<=2035,(1+$C$6)^($A15-2026),(1+$C$6)^9*(1+$F$6)^($A15-2035)) -> 1 | F15: =IF($A15<=2035,(1+$D$6)^($A15-2026),(1+$D$6)^9*(1+$G$6)^($A15-2035)) -> 1 | G15: =IF($A15<=2035,(1+$E$6)^($A15-2026),(1+$E$6)^9*(1+$H$6)^($A15-2035)) -> 1 | H15: =IF($A15<=2035,(1+$C$7)^($A15-2026),(1+$C$7)^9*(1+$F$7)^($A15-2035)) -> 1 | I15: =IF($A15<=2035,(1+$D$7)^($A15-2026),(1+$D$7)^9*(1+$G$7)^($A15-2035)) -> 1 | J15: =IF($A15<=2035,(1+$E$7)^($A15-2026),(1+$E$7)^9*(1+$H$7)^($A15-2035)) -> 1 | K15: =IF($A15<=2035,(1+$C$8)^($A15-2026),(1+$C$8)^9*(1+$F$8)^($A15-2035)) -> 1 | L15: =IF($A15<=2035,(1+$D$8)^($A15-2026),(1+$D$8)^9*(1+$G$8)^($A15-2035)) -> 1 | M15: =IF($A15<=2035,(1+$E$8)^($A15-2026),(1+$E$8)^9*(1+$H$8)^($A15-2035)) -> 1
A16: 2027 | B16: =IF($A16<=2035,(1+$C$5)^($A16-2026),(1+$C$5)^9*(1+$F$5)^($A16-2035)) -> 0.9255 | C16: =IF($A16<=2035,(1+$D$5)^($A16-2026),(1+$D$5)^9*(1+$G$5)^($A16-2035)) -> 0.971 | D16: =IF($A16<=2035,(1+$E$5)^($A16-2026),(1+$E$5)^9*(1+$H$5)^($A16-2035)) -> 0.9916 | E16: =IF($A16<=2035,(1+$C$6)^($A16-2026),(1+$C$6)^9*(1+$F$6)^($A16-2035)) -> 0.8766 | F16: =IF($A16<=2035,(1+$D$6)^($A16-2026),(1+$D$6)^9*(1+$G$6)^($A16-2035)) -> 0.9212 | G16: =IF($A16<=2035,(1+$E$6)^($A16-2026),(1+$E$6)^9*(1+$H$6)^($A16-2035)) -> 0.9606 | H16: =IF($A16<=2035,(1+$C$7)^($A16-2026),(1+$C$7)^9*(1+$F$7)^($A16-2035)) -> 0.9042 | I16: =IF($A16<=2035,(1+$D$7)^($A16-2026),(1+$D$7)^9*(1+$G$7)^($A16-2035)) -> 0.9469 | J16: =IF($A16<=2035,(1+$E$7)^($A16-2026),(1+$E$7)^9*(1+$H$7)^($A16-2035)) -> 0.9879 | K16: =IF($A16<=2035,(1+$C$8)^($A16-2026),(1+$C$8)^9*(1+$F$8)^($A16-2035)) -> 0.9683 | L16: =IF($A16<=2035,(1+$D$8)^($A16-2026),(1+$D$8)^9*(1+$G$8)^($A16-2035)) -> 0.9801 | M16: =IF($A16<=2035,(1+$E$8)^($A16-2026),(1+$E$8)^9*(1+$H$8)^($A16-2035)) -> 0.9902
A17: 2028 | B17: =IF($A17<=2035,(1+$C$5)^($A17-2026),(1+$C$5)^9*(1+$F$5)^($A17-2035)) -> 0.85655025 | C17: =IF($A17<=2035,(1+$D$5)^($A17-2026),(1+$D$5)^9*(1+$G$5)^($A17-2035)) -> 0.942841 | D17: =IF($A17<=2035,(1+$E$5)^($A17-2026),(1+$E$5)^9*(1+$H$5)^($A17-2035)) -> 0.98327056 | E17: =IF($A17<=2035,(1+$C$6)^($A17-2026),(1+$C$6)^9*(1+$F$6)^($A17-2035)) -> 0.76842756 | F17: =IF($A17<=2035,(1+$D$6)^($A17-2026),(1+$D$6)^9*(1+$G$6)^($A17-2035)) -> 0.84860944 | G17: =IF($A17<=2035,(1+$E$6)^($A17-2026),(1+$E$6)^9*(1+$H$6)^($A17-2035)) -> 0.92275236 | H17: =IF($A17<=2035,(1+$C$7)^($A17-2026),(1+$C$7)^9*(1+$F$7)^($A17-2035)) -> 0.81757764 | I17: =IF($A17<=2035,(1+$D$7)^($A17-2026),(1+$D$7)^9*(1+$G$7)^($A17-2035)) -> 0.89661961 | J17: =IF($A17<=2035,(1+$E$7)^($A17-2026),(1+$E$7)^9*(1+$H$7)^($A17-2035)) -> 0.97594641 | K17: =IF($A17<=2035,(1+$C$8)^($A17-2026),(1+$C$8)^9*(1+$F$8)^($A17-2035)) -> 0.93760489 | L17: =IF($A17<=2035,(1+$D$8)^($A17-2026),(1+$D$8)^9*(1+$G$8)^($A17-2035)) -> 0.96059601 | M17: =IF($A17<=2035,(1+$E$8)^($A17-2026),(1+$E$8)^9*(1+$H$8)^($A17-2035)) -> 0.98049604
A18: 2029 | B18: =IF($A18<=2035,(1+$C$5)^($A18-2026),(1+$C$5)^9*(1+$F$5)^($A18-2035)) -> 0.79273726 | C18: =IF($A18<=2035,(1+$D$5)^($A18-2026),(1+$D$5)^9*(1+$G$5)^($A18-2035)) -> 0.91549861 | D18: =IF($A18<=2035,(1+$E$5)^($A18-2026),(1+$E$5)^9*(1+$H$5)^($A18-2035)) -> 0.97501109 | E18: =IF($A18<=2035,(1+$C$6)^($A18-2026),(1+$C$6)^9*(1+$F$6)^($A18-2035)) -> 0.6736036 | F18: =IF($A18<=2035,(1+$D$6)^($A18-2026),(1+$D$6)^9*(1+$G$6)^($A18-2035)) -> 0.78173902 | G18: =IF($A18<=2035,(1+$E$6)^($A18-2026),(1+$E$6)^9*(1+$H$6)^($A18-2035)) -> 0.88639592 | H18: =IF($A18<=2035,(1+$C$7)^($A18-2026),(1+$C$7)^9*(1+$F$7)^($A18-2035)) -> 0.7392537 | I18: =IF($A18<=2035,(1+$D$7)^($A18-2026),(1+$D$7)^9*(1+$G$7)^($A18-2035)) -> 0.84900911 | J18: =IF($A18<=2035,(1+$E$7)^($A18-2026),(1+$E$7)^9*(1+$H$7)^($A18-2035)) -> 0.96413746 | K18: =IF($A18<=2035,(1+$C$8)^($A18-2026),(1+$C$8)^9*(1+$F$8)^($A18-2035)) -> 0.90788281 | L18: =IF($A18<=2035,(1+$D$8)^($A18-2026),(1+$D$8)^9*(1+$G$8)^($A18-2035)) -> 0.94148015 | M18: =IF($A18<=2035,(1+$E$8)^($A18-2026),(1+$E$8)^9*(1+$H$8)^($A18-2035)) -> 0.97088718
A19: 2030 | B19: =IF($A19<=2035,(1+$C$5)^($A19-2026),(1+$C$5)^9*(1+$F$5)^($A19-2035)) -> 0.73367833 | C19: =IF($A19<=2035,(1+$D$5)^($A19-2026),(1+$D$5)^9*(1+$G$5)^($A19-2035)) -> 0.88894915 | D19: =IF($A19<=2035,(1+$E$5)^($A19-2026),(1+$E$5)^9*(1+$H$5)^($A19-2035)) -> 0.96682099 | E19: =IF($A19<=2035,(1+$C$6)^($A19-2026),(1+$C$6)^9*(1+$F$6)^($A19-2035)) -> 0.59048091 | F19: =IF($A19<=2035,(1+$D$6)^($A19-2026),(1+$D$6)^9*(1+$G$6)^($A19-2035)) -> 0.72013798 | G19: =IF($A19<=2035,(1+$E$6)^($A19-2026),(1+$E$6)^9*(1+$H$6)^($A19-2035)) -> 0.85147192 | H19: =IF($A19<=2035,(1+$C$7)^($A19-2026),(1+$C$7)^9*(1+$F$7)^($A19-2035)) -> 0.6684332 | I19: =IF($A19<=2035,(1+$D$7)^($A19-2026),(1+$D$7)^9*(1+$G$7)^($A19-2035)) -> 0.80392673 | J19: =IF($A19<=2035,(1+$E$7)^($A19-2026),(1+$E$7)^9*(1+$H$7)^($A19-2035)) -> 0.9524714 | K19: =IF($A19<=2035,(1+$C$8)^($A19-2026),(1+$C$8)^9*(1+$F$8)^($A19-2035)) -> 0.87910293 | L19: =IF($A19<=2035,(1+$D$8)^($A19-2026),(1+$D$8)^9*(1+$G$8)^($A19-2035)) -> 0.92274469 | M19: =IF($A19<=2035,(1+$E$8)^($A19-2026),(1+$E$8)^9*(1+$H$8)^($A19-2035)) -> 0.96137248
A20: 2031 | B20: =IF($A20<=2035,(1+$C$5)^($A20-2026),(1+$C$5)^9*(1+$F$5)^($A20-2035)) -> 0.6790193 | C20: =IF($A20<=2035,(1+$D$5)^($A20-2026),(1+$D$5)^9*(1+$G$5)^($A20-2035)) -> 0.86316963 | D20: =IF($A20<=2035,(1+$E$5)^($A20-2026),(1+$E$5)^9*(1+$H$5)^($A20-2035)) -> 0.9586997 | E20: =IF($A20<=2035,(1+$C$6)^($A20-2026),(1+$C$6)^9*(1+$F$6)^($A20-2035)) -> 0.51761557 | F20: =IF($A20<=2035,(1+$D$6)^($A20-2026),(1+$D$6)^9*(1+$G$6)^($A20-2035)) -> 0.66339111 | G20: =IF($A20<=2035,(1+$E$6)^($A20-2026),(1+$E$6)^9*(1+$H$6)^($A20-2035)) -> 0.81792392 | H20: =IF($A20<=2035,(1+$C$7)^($A20-2026),(1+$C$7)^9*(1+$F$7)^($A20-2035)) -> 0.6043973 | I20: =IF($A20<=2035,(1+$D$7)^($A20-2026),(1+$D$7)^9*(1+$G$7)^($A20-2035)) -> 0.76123822 | J20: =IF($A20<=2035,(1+$E$7)^($A20-2026),(1+$E$7)^9*(1+$H$7)^($A20-2035)) -> 0.94094649 | K20: =IF($A20<=2035,(1+$C$8)^($A20-2026),(1+$C$8)^9*(1+$F$8)^($A20-2035)) -> 0.85123537 | L20: =IF($A20<=2035,(1+$D$8)^($A20-2026),(1+$D$8)^9*(1+$G$8)^($A20-2035)) -> 0.90438208 | M20: =IF($A20<=2035,(1+$E$8)^($A20-2026),(1+$E$8)^9*(1+$H$8)^($A20-2035)) -> 0.95195103
A21: 2032 | B21: =IF($A21<=2035,(1+$C$5)^($A21-2026),(1+$C$5)^9*(1+$F$5)^($A21-2035)) -> 0.62843236 | C21: =IF($A21<=2035,(1+$D$5)^($A21-2026),(1+$D$5)^9*(1+$G$5)^($A21-2035)) -> 0.83813771 | D21: =IF($A21<=2035,(1+$E$5)^($A21-2026),(1+$E$5)^9*(1+$H$5)^($A21-2035)) -> 0.95064662 | E21: =IF($A21<=2035,(1+$C$6)^($A21-2026),(1+$C$6)^9*(1+$F$6)^($A21-2035)) -> 0.45374181 | F21: =IF($A21<=2035,(1+$D$6)^($A21-2026),(1+$D$6)^9*(1+$G$6)^($A21-2035)) -> 0.61111589 | G21: =IF($A21<=2035,(1+$E$6)^($A21-2026),(1+$E$6)^9*(1+$H$6)^($A21-2035)) -> 0.78569772 | H21: =IF($A21<=2035,(1+$C$7)^($A21-2026),(1+$C$7)^9*(1+$F$7)^($A21-2035)) -> 0.54649604 | I21: =IF($A21<=2035,(1+$D$7)^($A21-2026),(1+$D$7)^9*(1+$G$7)^($A21-2035)) -> 0.72081647 | J21: =IF($A21<=2035,(1+$E$7)^($A21-2026),(1+$E$7)^9*(1+$H$7)^($A21-2035)) -> 0.92956104 | K21: =IF($A21<=2035,(1+$C$8)^($A21-2026),(1+$C$8)^9*(1+$F$8)^($A21-2035)) -> 0.82425121 | L21: =IF($A21<=2035,(1+$D$8)^($A21-2026),(1+$D$8)^9*(1+$G$8)^($A21-2035)) -> 0.88638487 | M21: =IF($A21<=2035,(1+$E$8)^($A21-2026),(1+$E$8)^9*(1+$H$8)^($A21-2035)) -> 0.94262191
A22: 2033 | B22: =IF($A22<=2035,(1+$C$5)^($A22-2026),(1+$C$5)^9*(1+$F$5)^($A22-2035)) -> 0.58161415 | C22: =IF($A22<=2035,(1+$D$5)^($A22-2026),(1+$D$5)^9*(1+$G$5)^($A22-2035)) -> 0.81383171 | D22: =IF($A22<=2035,(1+$E$5)^($A22-2026),(1+$E$5)^9*(1+$H$5)^($A22-2035)) -> 0.94266119 | E22: =IF($A22<=2035,(1+$C$6)^($A22-2026),(1+$C$6)^9*(1+$F$6)^($A22-2035)) -> 0.39775007 | F22: =IF($A22<=2035,(1+$D$6)^($A22-2026),(1+$D$6)^9*(1+$G$6)^($A22-2035)) -> 0.56295996 | G22: =IF($A22<=2035,(1+$E$6)^($A22-2026),(1+$E$6)^9*(1+$H$6)^($A22-2035)) -> 0.75474123 | H22: =IF($A22<=2035,(1+$C$7)^($A22-2026),(1+$C$7)^9*(1+$F$7)^($A22-2035)) -> 0.49414172 | I22: =IF($A22<=2035,(1+$D$7)^($A22-2026),(1+$D$7)^9*(1+$G$7)^($A22-2035)) -> 0.68254111 | J22: =IF($A22<=2035,(1+$E$7)^($A22-2026),(1+$E$7)^9*(1+$H$7)^($A22-2035)) -> 0.91831335 | K22: =IF($A22<=2035,(1+$C$8)^($A22-2026),(1+$C$8)^9*(1+$F$8)^($A22-2035)) -> 0.79812244 | L22: =IF($A22<=2035,(1+$D$8)^($A22-2026),(1+$D$8)^9*(1+$G$8)^($A22-2035)) -> 0.86874581 | M22: =IF($A22<=2035,(1+$E$8)^($A22-2026),(1+$E$8)^9*(1+$H$8)^($A22-2035)) -> 0.93338422
A23: 2034 | B23: =IF($A23<=2035,(1+$C$5)^($A23-2026),(1+$C$5)^9*(1+$F$5)^($A23-2035)) -> 0.53828389 | C23: =IF($A23<=2035,(1+$D$5)^($A23-2026),(1+$D$5)^9*(1+$G$5)^($A23-2035)) -> 0.79023059 | D23: =IF($A23<=2035,(1+$E$5)^($A23-2026),(1+$E$5)^9*(1+$H$5)^($A23-2035)) -> 0.93474283 | E23: =IF($A23<=2035,(1+$C$6)^($A23-2026),(1+$C$6)^9*(1+$F$6)^($A23-2035)) -> 0.34866771 | F23: =IF($A23<=2035,(1+$D$6)^($A23-2026),(1+$D$6)^9*(1+$G$6)^($A23-2035)) -> 0.51859871 | G23: =IF($A23<=2035,(1+$E$6)^($A23-2026),(1+$E$6)^9*(1+$H$6)^($A23-2035)) -> 0.72500443 | H23: =IF($A23<=2035,(1+$C$7)^($A23-2026),(1+$C$7)^9*(1+$F$7)^($A23-2035)) -> 0.44680294 | I23: =IF($A23<=2035,(1+$D$7)^($A23-2026),(1+$D$7)^9*(1+$G$7)^($A23-2035)) -> 0.64629818 | J23: =IF($A23<=2035,(1+$E$7)^($A23-2026),(1+$E$7)^9*(1+$H$7)^($A23-2035)) -> 0.90720176 | K23: =IF($A23<=2035,(1+$C$8)^($A23-2026),(1+$C$8)^9*(1+$F$8)^($A23-2035)) -> 0.77282196 | L23: =IF($A23<=2035,(1+$D$8)^($A23-2026),(1+$D$8)^9*(1+$G$8)^($A23-2035)) -> 0.85145777 | M23: =IF($A23<=2035,(1+$E$8)^($A23-2026),(1+$E$8)^9*(1+$H$8)^($A23-2035)) -> 0.92423705
A24: 2035 | B24: =IF($A24<=2035,(1+$C$5)^($A24-2026),(1+$C$5)^9*(1+$F$5)^($A24-2035)) -> 0.49818174 | C24: =IF($A24<=2035,(1+$D$5)^($A24-2026),(1+$D$5)^9*(1+$G$5)^($A24-2035)) -> 0.76731391 | D24: =IF($A24<=2035,(1+$E$5)^($A24-2026),(1+$E$5)^9*(1+$H$5)^($A24-2035)) -> 0.92689099 | E24: =IF($A24<=2035,(1+$C$6)^($A24-2026),(1+$C$6)^9*(1+$F$6)^($A24-2035)) -> 0.30564212 | F24: =IF($A24<=2035,(1+$D$6)^($A24-2026),(1+$D$6)^9*(1+$G$6)^($A24-2035)) -> 0.47773313 | G24: =IF($A24<=2035,(1+$E$6)^($A24-2026),(1+$E$6)^9*(1+$H$6)^($A24-2035)) -> 0.69643925 | H24: =IF($A24<=2035,(1+$C$7)^($A24-2026),(1+$C$7)^9*(1+$F$7)^($A24-2035)) -> 0.40399922 | I24: =IF($A24<=2035,(1+$D$7)^($A24-2026),(1+$D$7)^9*(1+$G$7)^($A24-2035)) -> 0.61197975 | J24: =IF($A24<=2035,(1+$E$7)^($A24-2026),(1+$E$7)^9*(1+$H$7)^($A24-2035)) -> 0.89622462 | K24: =IF($A24<=2035,(1+$C$8)^($A24-2026),(1+$C$8)^9*(1+$F$8)^($A24-2035)) -> 0.7483235 | L24: =IF($A24<=2035,(1+$D$8)^($A24-2026),(1+$D$8)^9*(1+$G$8)^($A24-2035)) -> 0.83451376 | M24: =IF($A24<=2035,(1+$E$8)^($A24-2026),(1+$E$8)^9*(1+$H$8)^($A24-2035)) -> 0.91517953
A25: 2036 | B25: =IF($A25<=2035,(1+$C$5)^($A25-2026),(1+$C$5)^9*(1+$F$5)^($A25-2035)) -> 0.46520211 | C25: =IF($A25<=2035,(1+$D$5)^($A25-2026),(1+$D$5)^9*(1+$G$5)^($A25-2035)) -> 0.75120031 | D25: =IF($A25<=2035,(1+$E$5)^($A25-2026),(1+$E$5)^9*(1+$H$5)^($A25-2035)) -> 0.92058814 | E25: =IF($A25<=2035,(1+$C$6)^($A25-2026),(1+$C$6)^9*(1+$F$6)^($A25-2035)) -> 0.29934589 | F25: =IF($A25<=2035,(1+$D$6)^($A25-2026),(1+$D$6)^9*(1+$G$6)^($A25-2035)) -> 0.46402219 | G25: =IF($A25<=2035,(1+$E$6)^($A25-2026),(1+$E$6)^9*(1+$H$6)^($A25-2035)) -> 0.67540679 | H25: =IF($A25<=2035,(1+$C$7)^($A25-2026),(1+$C$7)^9*(1+$F$7)^($A25-2035)) -> 0.39531323 | I25: =IF($A25<=2035,(1+$D$7)^($A25-2026),(1+$D$7)^9*(1+$G$7)^($A25-2035)) -> 0.59362035 | J25: =IF($A25<=2035,(1+$E$7)^($A25-2026),(1+$E$7)^9*(1+$H$7)^($A25-2035)) -> 0.86790392 | K25: =IF($A25<=2035,(1+$C$8)^($A25-2026),(1+$C$8)^9*(1+$F$8)^($A25-2035)) -> 0.74450706 | L25: =IF($A25<=2035,(1+$D$8)^($A25-2026),(1+$D$8)^9*(1+$G$8)^($A25-2035)) -> 0.82858871 | M25: =IF($A25<=2035,(1+$E$8)^($A25-2026),(1+$E$8)^9*(1+$H$8)^($A25-2035)) -> 0.90831568
A26: 2037 | B26: =IF($A26<=2035,(1+$C$5)^($A26-2026),(1+$C$5)^9*(1+$F$5)^($A26-2035)) -> 0.43440573 | C26: =IF($A26<=2035,(1+$D$5)^($A26-2026),(1+$D$5)^9*(1+$G$5)^($A26-2035)) -> 0.73542511 | D26: =IF($A26<=2035,(1+$E$5)^($A26-2026),(1+$E$5)^9*(1+$H$5)^($A26-2035)) -> 0.91432814 | E26: =IF($A26<=2035,(1+$C$6)^($A26-2026),(1+$C$6)^9*(1+$F$6)^($A26-2035)) -> 0.29317936 | F26: =IF($A26<=2035,(1+$D$6)^($A26-2026),(1+$D$6)^9*(1+$G$6)^($A26-2035)) -> 0.45070476 | G26: =IF($A26<=2035,(1+$E$6)^($A26-2026),(1+$E$6)^9*(1+$H$6)^($A26-2035)) -> 0.6550095 | H26: =IF($A26<=2035,(1+$C$7)^($A26-2026),(1+$C$7)^9*(1+$F$7)^($A26-2035)) -> 0.386814 | I26: =IF($A26<=2035,(1+$D$7)^($A26-2026),(1+$D$7)^9*(1+$G$7)^($A26-2035)) -> 0.57581174 | J26: =IF($A26<=2035,(1+$E$7)^($A26-2026),(1+$E$7)^9*(1+$H$7)^($A26-2035)) -> 0.84047816 | K26: =IF($A26<=2035,(1+$C$8)^($A26-2026),(1+$C$8)^9*(1+$F$8)^($A26-2035)) -> 0.74071007 | L26: =IF($A26<=2035,(1+$D$8)^($A26-2026),(1+$D$8)^9*(1+$G$8)^($A26-2035)) -> 0.82270573 | M26: =IF($A26<=2035,(1+$E$8)^($A26-2026),(1+$E$8)^9*(1+$H$8)^($A26-2035)) -> 0.90150332
... A39: 2050 | B39: =IF($A39<=2035,(1+$C$5)^($A39-2026),(1+$C$5)^9*(1+$F$5)^($A39-2035)) -> 0.17831827 | C39: =IF($A39<=2035,(1+$D$5)^($A39-2026),(1+$D$5)^9*(1+$G$5)^($A39-2035)) -> 0.55810183 | D39: =IF($A39<=2035,(1+$E$5)^($A39-2026),(1+$E$5)^9*(1+$H$5)^($A39-2035)) -> 0.83671841 | E39: =IF($A39<=2035,(1+$C$6)^($A39-2026),(1+$C$6)^9*(1+$F$6)^($A39-2035)) -> 0.22367358 | F39: =IF($A39<=2035,(1+$D$6)^($A39-2026),(1+$D$6)^9*(1+$G$6)^($A39-2035)) -> 0.30866415 | G39: =IF($A39<=2035,(1+$E$6)^($A39-2026),(1+$E$6)^9*(1+$H$6)^($A39-2035)) -> 0.43965897 | H39: =IF($A39<=2035,(1+$C$7)^($A39-2026),(1+$C$7)^9*(1+$F$7)^($A39-2035)) -> 0.29160366 | I39: =IF($A39<=2035,(1+$D$7)^($A39-2026),(1+$D$7)^9*(1+$G$7)^($A39-2035)) -> 0.3875369 | J39: =IF($A39<=2035,(1+$E$7)^($A39-2026),(1+$E$7)^9*(1+$H$7)^($A39-2035)) -> 0.55365418 | K39: =IF($A39<=2035,(1+$C$8)^($A39-2026),(1+$C$8)^9*(1+$F$8)^($A39-2035)) -> 0.69307598 | L39: =IF($A39<=2035,(1+$D$8)^($A39-2026),(1+$D$8)^9*(1+$G$8)^($A39-2035)) -> 0.74992212 | M39: =IF($A39<=2035,(1+$E$8)^($A39-2026),(1+$E$8)^9*(1+$H$8)^($A39-2035)) -> 0.81745533

Sheet Curva_BESS
A1: Curva de almacenamiento — duración 1 a 8 h
A2: USD por kWh de energía nominal, constantes de 2026, full costo con margen
A4: Segmento | C4: B3
A5: Escenario | C5: Medio
A6: Energía nominal del proyecto (MWh) | C6: 40
A7: Factor de sobredimensionamiento | C7: 1
A8: cSUP (USD/kWh instalado) | C8: =INDEX(Parametros_BESS!$D$5:$D$8,MATCH($C$4,Parametros_BESS!$A$5:$A$8,0)) -> 93.4
A9: cE local (USD/kWh) | C9: =INDEX(Parametros_BESS!$E$5:$E$8,MATCH($C$4,Parametros_BESS!$A$5:$A$8,0)) -> 5.35
A10: cP local (USD/kW) | C10: =INDEX(Parametros_BESS!$F$5:$F$8,MATCH($C$4,Parametros_BESS!$A$5:$A$8,0)) -> 86.6
A11: cF (USD) | C11: =INDEX(Parametros_BESS!$G$5:$G$8,MATCH($C$4,Parametros_BESS!$A$5:$A$8,0)) -> 526263
A12: Indirectos | C12: =INDEX(Parametros_BESS!$H$5:$H$8,MATCH($C$4,Parametros_BESS!$A$5:$A$8,0)) -> 0.054
A13: EPC management | C13: =INDEX(Parametros_BESS!$I$5:$I$8,MATCH($C$4,Parametros_BESS!$A$5:$A$8,0)) -> 0.015
A14: Margen | C14: =INDEX(Parametros_BESS!$J$5:$J$8,MATCH($C$4,Parametros_BESS!$A$5:$A$8,0)) -> 0.2
A15: Columna de escenario | C15: =MATCH($C$5,{"Bajo","Medio","Alto"},0) -> 2
A17: USD por kWh de energía nominal
A18: Año | B18: 1 h | C18: 2 h | D18: 3 h | E18: 4 h | F18: 5 h | G18: 6 h | H18: 7 h | I18: 8 h
A19: 2026 | B19: =($C$8*(1+MAX(0,1/1-Suministro_BESS!$A$13)*Suministro_BESS!$B$13)*$C$7*INDEX(Trayectorias!$B$15:$D$39,MATCH($A19,Trayectorias!$A$15:$A$39,0),$C$15)+$C$9*INDEX(Trayectorias!$K$15:$M$39,MATCH($A19,Trayectorias!$A$15:$A$39,0),$C$15)+$C$10*INDEX(Trayectorias!$K$15:$M$39,MATCH($A19,Trayectorias!$A$15:$A$39,0),$C$15)/1+$C$11*INDEX(Trayectorias!$K$15:$M$39,MATCH($A19,Trayectorias!$A$15:$A$39,0),$C$15)/($C$6*1000))*(1+$C$12)*(1+$C$13)/(1-$C$14) -> 279.19443 | C19: =($C$8*(1+MAX(0,1/2-Suministro_BESS!$A$13)*Suministro_BESS!$B$13)*$C$7*INDEX(Trayectorias!$B$15:$D$39,MATCH($A19,Trayectorias!$A$15:$A$39,0),$C$15)+$C$9*INDEX(Trayectorias!$K$15:$M$39,MATCH($A19,Trayectorias!$A$15:$A$39,0),$C$15)+$C$10*INDEX(Trayectorias!$K$15:$M$39,MATCH($A19,Trayectorias!$A$15:$A$39,0),$C$15)/2+$C$11*INDEX(Trayectorias!$K$15:$M$39,MATCH($A19,Trayectorias!$A$15:$A$39,0),$C$15)/($C$6*1000))*(1+$C$12)*(1+$C$13)/(1-$C$14) -> 207.55193 | D19: =($C$8*(1+MAX(0,1/3-Suministro_BESS!$A$13)*Suministro_BESS!$B$13)*$C$7*INDEX(Trayectorias!$B$15:$D$39,MATCH($A19,Trayectorias!$A$15:$A$39,0),$C$15)+$C$9*INDEX(Trayectorias!$K$15:$M$39,MATCH($A19,Trayectorias!$A$15:$A$39,0),$C$15)+$C$10*INDEX(Trayectorias!$K$15:$M$39,MATCH($A19,Trayectorias!$A$15:$A$39,0),$C$15)/3+$C$11*INDEX(Trayectorias!$K$15:$M$39,MATCH($A19,Trayectorias!$A$15:$A$39,0),$C$15)/($C$6*1000))*(1+$C$12)*(1+$C$13)/(1-$C$14) -> 188.25078 | E19: =($C$8*(1+MAX(0,1/4-Suministro_BESS!$A$13)*Suministro_BESS!$B$13)*$C$7*INDEX(Trayectorias!$B$15:$D$39,MATCH($A19,Trayectorias!$A$15:$A$39,0),$C$15)+$C$9*INDEX(Trayectorias!$K$15:$M$39,MATCH($A19,Trayectorias!$A$15:$A$39,0),$C$15)+$C$10*INDEX(Trayectorias!$K$15:$M$39,MATCH($A19,Trayectorias!$A$15:$A$39,0),$C$15)/4+$C$11*INDEX(Trayectorias!$K$15:$M$39,MATCH($A19,Trayectorias!$A$15:$A$39,0),$C$15)/($C$6*1000))*(1+$C$12)*(1+$C$13)/(1-$C$14) -> 178.6002 | F19: =($C$8*(1+MAX(0,1/5-Suministro_BESS!$A$13)*Suministro_BESS!$B$13)*$C$7*INDEX(Trayectorias!$B$15:$D$39,MATCH($A19,Trayectorias!$A$15:$A$39,0),$C$15)+$C$9*INDEX(Trayectorias!$K$15:$M$39,MATCH($A19,Trayectorias!$A$15:$A$39,0),$C$15)+$C$10*INDEX(Trayectorias!$K$15:$M$39,MATCH($A19,Trayectorias!$A$15:$A$39,0),$C$15)/5+$C$11*INDEX(Trayectorias!$K$15:$M$39,MATCH($A19,Trayectorias!$A$15:$A$39,0),$C$15)/($C$6*1000))*(1+$C$12)*(1+$C$13)/(1-$C$14) -> 172.80985 | G19: =($C$8*(1+MAX(0,1/6-Suministro_BESS!$A$13)*Suministro_BESS!$B$13)*$C$7*INDEX(Trayectorias!$B$15:$D$39,MATCH($A19,Trayectorias!$A$15:$A$39,0),$C$15)+$C$9*INDEX(Trayectorias!$K$15:$M$39,MATCH($A19,Trayectorias!$A$15:$A$39,0),$C$15)+$C$10*INDEX(Trayectorias!$K$15:$M$39,MATCH($A19,Trayectorias!$A$15:$A$39,0),$C$15)/6+$C$11*INDEX(Trayectorias!$K$15:$M$39,MATCH($A19,Trayectorias!$A$15:$A$39,0),$C$15)/($C$6*1000))*(1+$C$12)*(1+$C$13)/(1-$C$14) -> 168.94962 | H19: =($C$8*(1+MAX(0,1/7-Suministro_BESS!$A$13)*Suministro_BESS!$B$13)*$C$7*INDEX(Trayectorias!$B$15:$D$39,MATCH($A19,Trayectorias!$A$15:$A$39,0),$C$15)+$C$9*INDEX(Trayectorias!$K$15:$M$39,MATCH($A19,Trayectorias!$A$15:$A$39,0),$C$15)+$C$10*INDEX(Trayectorias!$K$15:$M$39,MATCH($A19,Trayectorias!$A$15:$A$39,0),$C$15)/7+$C$11*INDEX(Trayectorias!$K$15:$M$39,MATCH($A19,Trayectorias!$A$15:$A$39,0),$C$15)/($C$6*1000))*(1+$C$12)*(1+$C$13)/(1-$C$14) -> 166.19231 | I19: =($C$8*(1+MAX(0,1/8-Suministro_BESS!$A$13)*Suministro_BESS!$B$13)*$C$7*INDEX(Trayectorias!$B$15:$D$39,MATCH($A19,Trayectorias!$A$15:$A$39,0),$C$15)+$C$9*INDEX(Trayectorias!$K$15:$M$39,MATCH($A19,Trayectorias!$A$15:$A$39,0),$C$15)+$C$10*INDEX(Trayectorias!$K$15:$M$39,MATCH($A19,Trayectorias!$A$15:$A$39,0),$C$15)/8+$C$11*INDEX(Trayectorias!$K$15:$M$39,MATCH($A19,Trayectorias!$A$15:$A$39,0),$C$15)/($C$6*1000))*(1+$C$12)*(1+$C$13)/(1-$C$14) -> 164.12433
A20: 2027 | B20: =($C$8*(1+MAX(0,1/1-Suministro_BESS!$A$13)*Suministro_BESS!$B$13)*$C$7*INDEX(Trayectorias!$B$15:$D$39,MATCH($A20,Trayectorias!$A$15:$A$39,0),$C$15)+$C$9*INDEX(Trayectorias!$K$15:$M$39,MATCH($A20,Trayectorias!$A$15:$A$39,0),$C$15)+$C$10*INDEX(Trayectorias!$K$15:$M$39,MATCH($A20,Trayectorias!$A$15:$A$39,0),$C$15)/1+$C$11*INDEX(Trayectorias!$K$15:$M$39,MATCH($A20,Trayectorias!$A$15:$A$39,0),$C$15)/($C$6*1000))*(1+$C$12)*(1+$C$13)/(1-$C$14) -> 272.37685 | C20: =($C$8*(1+MAX(0,1/2-Suministro_BESS!$A$13)*Suministro_BESS!$B$13)*$C$7*INDEX(Trayectorias!$B$15:$D$39,MATCH($A20,Trayectorias!$A$15:$A$39,0),$C$15)+$C$9*INDEX(Trayectorias!$K$15:$M$39,MATCH($A20,Trayectorias!$A$15:$A$39,0),$C$15)+$C$10*INDEX(Trayectorias!$K$15:$M$39,MATCH($A20,Trayectorias!$A$15:$A$39,0),$C$15)/2+$C$11*INDEX(Trayectorias!$K$15:$M$39,MATCH($A20,Trayectorias!$A$15:$A$39,0),$C$15)/($C$6*1000))*(1+$C$12)*(1+$C$13)/(1-$C$14) -> 202.28506 | D20: =($C$8*(1+MAX(0,1/3-Suministro_BESS!$A$13)*Suministro_BESS!$B$13)*$C$7*INDEX(Trayectorias!$B$15:$D$39,MATCH($A20,Trayectorias!$A$15:$A$39,0),$C$15)+$C$9*INDEX(Trayectorias!$K$15:$M$39,MATCH($A20,Trayectorias!$A$15:$A$39,0),$C$15)+$C$10*INDEX(Trayectorias!$K$15:$M$39,MATCH($A20,Trayectorias!$A$15:$A$39,0),$C$15)/3+$C$11*INDEX(Trayectorias!$K$15:$M$39,MATCH($A20,Trayectorias!$A$15:$A$39,0),$C$15)/($C$6*1000))*(1+$C$12)*(1+$C$13)/(1-$C$14) -> 183.36799 | E20: =($C$8*(1+MAX(0,1/4-Suministro_BESS!$A$13)*Suministro_BESS!$B$13)*$C$7*INDEX(Trayectorias!$B$15:$D$39,MATCH($A20,Trayectorias!$A$15:$A$39,0),$C$15)+$C$9*INDEX(Trayectorias!$K$15:$M$39,MATCH($A20,Trayectorias!$A$15:$A$39,0),$C$15)+$C$10*INDEX(Trayectorias!$K$15:$M$39,MATCH($A20,Trayectorias!$A$15:$A$39,0),$C$15)/4+$C$11*INDEX(Trayectorias!$K$15:$M$39,MATCH($A20,Trayectorias!$A$15:$A$39,0),$C$15)/($C$6*1000))*(1+$C$12)*(1+$C$13)/(1-$C$14) -> 173.90946 | F20: =($C$8*(1+MAX(0,1/5-Suministro_BESS!$A$13)*Suministro_BESS!$B$13)*$C$7*INDEX(Trayectorias!$B$15:$D$39,MATCH($A20,Trayectorias!$A$15:$A$39,0),$C$15)+$C$9*INDEX(Trayectorias!$K$15:$M$39,MATCH($A20,Trayectorias!$A$15:$A$39,0),$C$15)+$C$10*INDEX(Trayectorias!$K$15:$M$39,MATCH($A20,Trayectorias!$A$15:$A$39,0),$C$15)/5+$C$11*INDEX(Trayectorias!$K$15:$M$39,MATCH($A20,Trayectorias!$A$15:$A$39,0),$C$15)/($C$6*1000))*(1+$C$12)*(1+$C$13)/(1-$C$14) -> 168.23434 | G20: =($C$8*(1+MAX(0,1/6-Suministro_BESS!$A$13)*Suministro_BESS!$B$13)*$C$7*INDEX(Trayectorias!$B$15:$D$39,MATCH($A20,Trayectorias!$A$15:$A$39,0),$C$15)+$C$9*INDEX(Trayectorias!$K$15:$M$39,MATCH($A20,Trayectorias!$A$15:$A$39,0),$C$15)+$C$10*INDEX(Trayectorias!$K$15:$M$39,MATCH($A20,Trayectorias!$A$15:$A$39,0),$C$15)/6+$C$11*INDEX(Trayectorias!$K$15:$M$39,MATCH($A20,Trayectorias!$A$15:$A$39,0),$C$15)/($C$6*1000))*(1+$C$12)*(1+$C$13)/(1-$C$14) -> 164.45093 | H20: =($C$8*(1+MAX(0,1/7-Suministro_BESS!$A$13)*Suministro_BESS!$B$13)*$C$7*INDEX(Trayectorias!$B$15:$D$39,MATCH($A20,Trayectorias!$A$15:$A$39,0),$C$15)+$C$9*INDEX(Trayectorias!$K$15:$M$39,MATCH($A20,Trayectorias!$A$15:$A$39,0),$C$15)+$C$10*INDEX(Trayectorias!$K$15:$M$39,MATCH($A20,Trayectorias!$A$15:$A$39,0),$C$15)/7+$C$11*INDEX(Trayectorias!$K$15:$M$39,MATCH($A20,Trayectorias!$A$15:$A$39,0),$C$15)/($C$6*1000))*(1+$C$12)*(1+$C$13)/(1-$C$14) -> 161.74849 | I20: =($C$8*(1+MAX(0,1/8-Suministro_BESS!$A$13)*Suministro_BESS!$B$13)*$C$7*INDEX(Trayectorias!$B$15:$D$39,MATCH($A20,Trayectorias!$A$15:$A$39,0),$C$15)+$C$9*INDEX(Trayectorias!$K$15:$M$39,MATCH($A20,Trayectorias!$A$15:$A$39,0),$C$15)+$C$10*INDEX(Trayectorias!$K$15:$M$39,MATCH($A20,Trayectorias!$A$15:$A$39,0),$C$15)/8+$C$11*INDEX(Trayectorias!$K$15:$M$39,MATCH($A20,Trayectorias!$A$15:$A$39,0),$C$15)/($C$6*1000))*(1+$C$12)*(1+$C$13)/(1-$C$14) -> 159.72167
A21: 2028 | B21: =($C$8*(1+MAX(0,1/1-Suministro_BESS!$A$13)*Suministro_BESS!$B$13)*$C$7*INDEX(Trayectorias!$B$15:$D$39,MATCH($A21,Trayectorias!$A$15:$A$39,0),$C$15)+$C$9*INDEX(Trayectorias!$K$15:$M$39,MATCH($A21,Trayectorias!$A$15:$A$39,0),$C$15)+$C$10*INDEX(Trayectorias!$K$15:$M$39,MATCH($A21,Trayectorias!$A$15:$A$39,0),$C$15)/1+$C$11*INDEX(Trayectorias!$K$15:$M$39,MATCH($A21,Trayectorias!$A$15:$A$39,0),$C$15)/($C$6*1000))*(1+$C$12)*(1+$C$13)/(1-$C$14) -> 265.73152 | C21: =($C$8*(1+MAX(0,1/2-Suministro_BESS!$A$13)*Suministro_BESS!$B$13)*$C$7*INDEX(Trayectorias!$B$15:$D$39,MATCH($A21,Trayectorias!$A$15:$A$39,0),$C$15)+$C$9*INDEX(Trayectorias!$K$15:$M$39,MATCH($A21,Trayectorias!$A$15:$A$39,0),$C$15)+$C$10*INDEX(Trayectorias!$K$15:$M$39,MATCH($A21,Trayectorias!$A$15:$A$39,0),$C$15)/2+$C$11*INDEX(Trayectorias!$K$15:$M$39,MATCH($A21,Trayectorias!$A$15:$A$39,0),$C$15)/($C$6*1000))*(1+$C$12)*(1+$C$13)/(1-$C$14) -> 197.15595 | D21: =($C$8*(1+MAX(0,1/3-Suministro_BESS!$A$13)*Suministro_BESS!$B$13)*$C$7*INDEX(Trayectorias!$B$15:$D$39,MATCH($A21,Trayectorias!$A$15:$A$39,0),$C$15)+$C$9*INDEX(Trayectorias!$K$15:$M$39,MATCH($A21,Trayectorias!$A$15:$A$39,0),$C$15)+$C$10*INDEX(Trayectorias!$K$15:$M$39,MATCH($A21,Trayectorias!$A$15:$A$39,0),$C$15)/3+$C$11*INDEX(Trayectorias!$K$15:$M$39,MATCH($A21,Trayectorias!$A$15:$A$39,0),$C$15)/($C$6*1000))*(1+$C$12)*(1+$C$13)/(1-$C$14) -> 178.61534 | E21: =($C$8*(1+MAX(0,1/4-Suministro_BESS!$A$13)*Suministro_BESS!$B$13)*$C$7*INDEX(Trayectorias!$B$15:$D$39,MATCH($A21,Trayectorias!$A$15:$A$39,0),$C$15)+$C$9*INDEX(Trayectorias!$K$15:$M$39,MATCH($A21,Trayectorias!$A$15:$A$39,0),$C$15)+$C$10*INDEX(Trayectorias!$K$15:$M$39,MATCH($A21,Trayectorias!$A$15:$A$39,0),$C$15)/4+$C$11*INDEX(Trayectorias!$K$15:$M$39,MATCH($A21,Trayectorias!$A$15:$A$39,0),$C$15)/($C$6*1000))*(1+$C$12)*(1+$C$13)/(1-$C$14) -> 169.34503 | F21: =($C$8*(1+MAX(0,1/5-Suministro_BESS!$A$13)*Suministro_BESS!$B$13)*$C$7*INDEX(Trayectorias!$B$15:$D$39,MATCH($A21,Trayectorias!$A$15:$A$39,0),$C$15)+$C$9*INDEX(Trayectorias!$K$15:$M$39,MATCH($A21,Trayectorias!$A$15:$A$39,0),$C$15)+$C$10*INDEX(Trayectorias!$K$15:$M$39,MATCH($A21,Trayectorias!$A$15:$A$39,0),$C$15)/5+$C$11*INDEX(Trayectorias!$K$15:$M$39,MATCH($A21,Trayectorias!$A$15:$A$39,0),$C$15)/($C$6*1000))*(1+$C$12)*(1+$C$13)/(1-$C$14) -> 163.78285 | G21: =($C$8*(1+MAX(0,1/6-Suministro_BESS!$A$13)*Suministro_BESS!$B$13)*$C$7*INDEX(Trayectorias!$B$15:$D$39,MATCH($A21,Trayectorias!$A$15:$A$39,0),$C$15)+$C$9*INDEX(Trayectorias!$K$15:$M$39,MATCH($A21,Trayectorias!$A$15:$A$39,0),$C$15)+$C$10*INDEX(Trayectorias!$K$15:$M$39,MATCH($A21,Trayectorias!$A$15:$A$39,0),$C$15)/6+$C$11*INDEX(Trayectorias!$K$15:$M$39,MATCH($A21,Trayectorias!$A$15:$A$39,0),$C$15)/($C$6*1000))*(1+$C$12)*(1+$C$13)/(1-$C$14) -> 160.07473 | H21: =($C$8*(1+MAX(0,1/7-Suministro_BESS!$A$13)*Suministro_BESS!$B$13)*$C$7*INDEX(Trayectorias!$B$15:$D$39,MATCH($A21,Trayectorias!$A$15:$A$39,0),$C$15)+$C$9*INDEX(Trayectorias!$K$15:$M$39,MATCH($A21,Trayectorias!$A$15:$A$39,0),$C$15)+$C$10*INDEX(Trayectorias!$K$15:$M$39,MATCH($A21,Trayectorias!$A$15:$A$39,0),$C$15)/7+$C$11*INDEX(Trayectorias!$K$15:$M$39,MATCH($A21,Trayectorias!$A$15:$A$39,0),$C$15)/($C$6*1000))*(1+$C$12)*(1+$C$13)/(1-$C$14) -> 157.42607 | I21: =($C$8*(1+MAX(0,1/8-Suministro_BESS!$A$13)*Suministro_BESS!$B$13)*$C$7*INDEX(Trayectorias!$B$15:$D$39,MATCH($A21,Trayectorias!$A$15:$A$39,0),$C$15)+$C$9*INDEX(Trayectorias!$K$15:$M$39,MATCH($A21,Trayectorias!$A$15:$A$39,0),$C$15)+$C$10*INDEX(Trayectorias!$K$15:$M$39,MATCH($A21,Trayectorias!$A$15:$A$39,0),$C$15)/8+$C$11*INDEX(Trayectorias!$K$15:$M$39,MATCH($A21,Trayectorias!$A$15:$A$39,0),$C$15)/($C$6*1000))*(1+$C$12)*(1+$C$13)/(1-$C$14) -> 155.43957
A22: 2029 | B22: =($C$8*(1+MAX(0,1/1-Suministro_BESS!$A$13)*Suministro_BESS!$B$13)*$C$7*INDEX(Trayectorias!$B$15:$D$39,MATCH($A22,Trayectorias!$A$15:$A$39,0),$C$15)+$C$9*INDEX(Trayectorias!$K$15:$M$39,MATCH($A22,Trayectorias!$A$15:$A$39,0),$C$15)+$C$10*INDEX(Trayectorias!$K$15:$M$39,MATCH($A22,Trayectorias!$A$15:$A$39,0),$C$15)/1+$C$11*INDEX(Trayectorias!$K$15:$M$39,MATCH($A22,Trayectorias!$A$15:$A$39,0),$C$15)/($C$6*1000))*(1+$C$12)*(1+$C$13)/(1-$C$14) -> 259.25395 | C22: =($C$8*(1+MAX(0,1/2-Suministro_BESS!$A$13)*Suministro_BESS!$B$13)*$C$7*INDEX(Trayectorias!$B$15:$D$39,MATCH($A22,Trayectorias!$A$15:$A$39,0),$C$15)+$C$9*INDEX(Trayectorias!$K$15:$M$39,MATCH($A22,Trayectorias!$A$15:$A$39,0),$C$15)+$C$10*INDEX(Trayectorias!$K$15:$M$39,MATCH($A22,Trayectorias!$A$15:$A$39,0),$C$15)/2+$C$11*INDEX(Trayectorias!$K$15:$M$39,MATCH($A22,Trayectorias!$A$15:$A$39,0),$C$15)/($C$6*1000))*(1+$C$12)*(1+$C$13)/(1-$C$14) -> 192.16092 | D22: =($C$8*(1+MAX(0,1/3-Suministro_BESS!$A$13)*Suministro_BESS!$B$13)*$C$7*INDEX(Trayectorias!$B$15:$D$39,MATCH($A22,Trayectorias!$A$15:$A$39,0),$C$15)+$C$9*INDEX(Trayectorias!$K$15:$M$39,MATCH($A22,Trayectorias!$A$15:$A$39,0),$C$15)+$C$10*INDEX(Trayectorias!$K$15:$M$39,MATCH($A22,Trayectorias!$A$15:$A$39,0),$C$15)/3+$C$11*INDEX(Trayectorias!$K$15:$M$39,MATCH($A22,Trayectorias!$A$15:$A$39,0),$C$15)/($C$6*1000))*(1+$C$12)*(1+$C$13)/(1-$C$14) -> 173.98927 | E22: =($C$8*(1+MAX(0,1/4-Suministro_BESS!$A$13)*Suministro_BESS!$B$13)*$C$7*INDEX(Trayectorias!$B$15:$D$39,MATCH($A22,Trayectorias!$A$15:$A$39,0),$C$15)+$C$9*INDEX(Trayectorias!$K$15:$M$39,MATCH($A22,Trayectorias!$A$15:$A$39,0),$C$15)+$C$10*INDEX(Trayectorias!$K$15:$M$39,MATCH($A22,Trayectorias!$A$15:$A$39,0),$C$15)/4+$C$11*INDEX(Trayectorias!$K$15:$M$39,MATCH($A22,Trayectorias!$A$15:$A$39,0),$C$15)/($C$6*1000))*(1+$C$12)*(1+$C$13)/(1-$C$14) -> 164.90344 | F22: =($C$8*(1+MAX(0,1/5-Suministro_BESS!$A$13)*Suministro_BESS!$B$13)*$C$7*INDEX(Trayectorias!$B$15:$D$39,MATCH($A22,Trayectorias!$A$15:$A$39,0),$C$15)+$C$9*INDEX(Trayectorias!$K$15:$M$39,MATCH($A22,Trayectorias!$A$15:$A$39,0),$C$15)+$C$10*INDEX(Trayectorias!$K$15:$M$39,MATCH($A22,Trayectorias!$A$15:$A$39,0),$C$15)/5+$C$11*INDEX(Trayectorias!$K$15:$M$39,MATCH($A22,Trayectorias!$A$15:$A$39,0),$C$15)/($C$6*1000))*(1+$C$12)*(1+$C$13)/(1-$C$14) -> 159.45194 | G22: =($C$8*(1+MAX(0,1/6-Suministro_BESS!$A$13)*Suministro_BESS!$B$13)*$C$7*INDEX(Trayectorias!$B$15:$D$39,MATCH($A22,Trayectorias!$A$15:$A$39,0),$C$15)+$C$9*INDEX(Trayectorias!$K$15:$M$39,MATCH($A22,Trayectorias!$A$15:$A$39,0),$C$15)+$C$10*INDEX(Trayectorias!$K$15:$M$39,MATCH($A22,Trayectorias!$A$15:$A$39,0),$C$15)/6+$C$11*INDEX(Trayectorias!$K$15:$M$39,MATCH($A22,Trayectorias!$A$15:$A$39,0),$C$15)/($C$6*1000))*(1+$C$12)*(1+$C$13)/(1-$C$14) -> 155.81761 | H22: =($C$8*(1+MAX(0,1/7-Suministro_BESS!$A$13)*Suministro_BESS!$B$13)*$C$7*INDEX(Trayectorias!$B$15:$D$39,MATCH($A22,Trayectorias!$A$15:$A$39,0),$C$15)+$C$9*INDEX(Trayectorias!$K$15:$M$39,MATCH($A22,Trayectorias!$A$15:$A$39,0),$C$15)+$C$10*INDEX(Trayectorias!$K$15:$M$39,MATCH($A22,Trayectorias!$A$15:$A$39,0),$C$15)/7+$C$11*INDEX(Trayectorias!$K$15:$M$39,MATCH($A22,Trayectorias!$A$15:$A$39,0),$C$15)/($C$6*1000))*(1+$C$12)*(1+$C$13)/(1-$C$14) -> 153.22166 | I22: =($C$8*(1+MAX(0,1/8-Suministro_BESS!$A$13)*Suministro_BESS!$B$13)*$C$7*INDEX(Trayectorias!$B$15:$D$39,MATCH($A22,Trayectorias!$A$15:$A$39,0),$C$15)+$C$9*INDEX(Trayectorias!$K$15:$M$39,MATCH($A22,Trayectorias!$A$15:$A$39,0),$C$15)+$C$10*INDEX(Trayectorias!$K$15:$M$39,MATCH($A22,Trayectorias!$A$15:$A$39,0),$C$15)/8+$C$11*INDEX(Trayectorias!$K$15:$M$39,MATCH($A22,Trayectorias!$A$15:$A$39,0),$C$15)/($C$6*1000))*(1+$C$12)*(1+$C$13)/(1-$C$14) -> 151.2747
A23: 2030 | B23: =($C$8*(1+MAX(0,1/1-Suministro_BESS!$A$13)*Suministro_BESS!$B$13)*$C$7*INDEX(Trayectorias!$B$15:$D$39,MATCH($A23,Trayectorias!$A$15:$A$39,0),$C$15)+$C$9*INDEX(Trayectorias!$K$15:$M$39,MATCH($A23,Trayectorias!$A$15:$A$39,0),$C$15)+$C$10*INDEX(Trayectorias!$K$15:$M$39,MATCH($A23,Trayectorias!$A$15:$A$39,0),$C$15)/1+$C$11*INDEX(Trayectorias!$K$15:$M$39,MATCH($A23,Trayectorias!$A$15:$A$39,0),$C$15)/($C$6*1000))*(1+$C$12)*(1+$C$13)/(1-$C$14) -> 252.93979 | C23: =($C$8*(1+MAX(0,1/2-Suministro_BESS!$A$13)*Suministro_BESS!$B$13)*$C$7*INDEX(Trayectorias!$B$15:$D$39,MATCH($A23,Trayectorias!$A$15:$A$39,0),$C$15)+$C$9*INDEX(Trayectorias!$K$15:$M$39,MATCH($A23,Trayectorias!$A$15:$A$39,0),$C$15)+$C$10*INDEX(Trayectorias!$K$15:$M$39,MATCH($A23,Trayectorias!$A$15:$A$39,0),$C$15)/2+$C$11*INDEX(Trayectorias!$K$15:$M$39,MATCH($A23,Trayectorias!$A$15:$A$39,0),$C$15)/($C$6*1000))*(1+$C$12)*(1+$C$13)/(1-$C$14) -> 187.29637 | D23: =($C$8*(1+MAX(0,1/3-Suministro_BESS!$A$13)*Suministro_BESS!$B$13)*$C$7*INDEX(Trayectorias!$B$15:$D$39,MATCH($A23,Trayectorias!$A$15:$A$39,0),$C$15)+$C$9*INDEX(Trayectorias!$K$15:$M$39,MATCH($A23,Trayectorias!$A$15:$A$39,0),$C$15)+$C$10*INDEX(Trayectorias!$K$15:$M$39,MATCH($A23,Trayectorias!$A$15:$A$39,0),$C$15)/3+$C$11*INDEX(Trayectorias!$K$15:$M$39,MATCH($A23,Trayectorias!$A$15:$A$39,0),$C$15)/($C$6*1000))*(1+$C$12)*(1+$C$13)/(1-$C$14) -> 169.48633 | E23: =($C$8*(1+MAX(0,1/4-Suministro_BESS!$A$13)*Suministro_BESS!$B$13)*$C$7*INDEX(Trayectorias!$B$15:$D$39,MATCH($A23,Trayectorias!$A$15:$A$39,0),$C$15)+$C$9*INDEX(Trayectorias!$K$15:$M$39,MATCH($A23,Trayectorias!$A$15:$A$39,0),$C$15)+$C$10*INDEX(Trayectorias!$K$15:$M$39,MATCH($A23,Trayectorias!$A$15:$A$39,0),$C$15)/4+$C$11*INDEX(Trayectorias!$K$15:$M$39,MATCH($A23,Trayectorias!$A$15:$A$39,0),$C$15)/($C$6*1000))*(1+$C$12)*(1+$C$13)/(1-$C$14) -> 160.58131 | F23: =($C$8*(1+MAX(0,1/5-Suministro_BESS!$A$13)*Suministro_BESS!$B$13)*$C$7*INDEX(Trayectorias!$B$15:$D$39,MATCH($A23,Trayectorias!$A$15:$A$39,0),$C$15)+$C$9*INDEX(Trayectorias!$K$15:$M$39,MATCH($A23,Trayectorias!$A$15:$A$39,0),$C$15)+$C$10*INDEX(Trayectorias!$K$15:$M$39,MATCH($A23,Trayectorias!$A$15:$A$39,0),$C$15)/5+$C$11*INDEX(Trayectorias!$K$15:$M$39,MATCH($A23,Trayectorias!$A$15:$A$39,0),$C$15)/($C$6*1000))*(1+$C$12)*(1+$C$13)/(1-$C$14) -> 155.2383 | G23: =($C$8*(1+MAX(0,1/6-Suministro_BESS!$A$13)*Suministro_BESS!$B$13)*$C$7*INDEX(Trayectorias!$B$15:$D$39,MATCH($A23,Trayectorias!$A$15:$A$39,0),$C$15)+$C$9*INDEX(Trayectorias!$K$15:$M$39,MATCH($A23,Trayectorias!$A$15:$A$39,0),$C$15)+$C$10*INDEX(Trayectorias!$K$15:$M$39,MATCH($A23,Trayectorias!$A$15:$A$39,0),$C$15)/6+$C$11*INDEX(Trayectorias!$K$15:$M$39,MATCH($A23,Trayectorias!$A$15:$A$39,0),$C$15)/($C$6*1000))*(1+$C$12)*(1+$C$13)/(1-$C$14) -> 151.67629 | H23: =($C$8*(1+MAX(0,1/7-Suministro_BESS!$A$13)*Suministro_BESS!$B$13)*$C$7*INDEX(Trayectorias!$B$15:$D$39,MATCH($A23,Trayectorias!$A$15:$A$39,0),$C$15)+$C$9*INDEX(Trayectorias!$K$15:$M$39,MATCH($A23,Trayectorias!$A$15:$A$39,0),$C$15)+$C$10*INDEX(Trayectorias!$K$15:$M$39,MATCH($A23,Trayectorias!$A$15:$A$39,0),$C$15)/7+$C$11*INDEX(Trayectorias!$K$15:$M$39,MATCH($A23,Trayectorias!$A$15:$A$39,0),$C$15)/($C$6*1000))*(1+$C$12)*(1+$C$13)/(1-$C$14) -> 149.132 | I23: =($C$8*(1+MAX(0,1/8-Suministro_BESS!$A$13)*Suministro_BESS!$B$13)*$C$7*INDEX(Trayectorias!$B$15:$D$39,MATCH($A23,Trayectorias!$A$15:$A$39,0),$C$15)+$C$9*INDEX(Trayectorias!$K$15:$M$39,MATCH($A23,Trayectorias!$A$15:$A$39,0),$C$15)+$C$10*INDEX(Trayectorias!$K$15:$M$39,MATCH($A23,Trayectorias!$A$15:$A$39,0),$C$15)/8+$C$11*INDEX(Trayectorias!$K$15:$M$39,MATCH($A23,Trayectorias!$A$15:$A$39,0),$C$15)/($C$6*1000))*(1+$C$12)*(1+$C$13)/(1-$C$14) -> 147.22378
A24: 2031 | B24: =($C$8*(1+MAX(0,1/1-Suministro_BESS!$A$13)*Suministro_BESS!$B$13)*$C$7*INDEX(Trayectorias!$B$15:$D$39,MATCH($A24,Trayectorias!$A$15:$A$39,0),$C$15)+$C$9*INDEX(Trayectorias!$K$15:$M$39,MATCH($A24,Trayectorias!$A$15:$A$39,0),$C$15)+$C$10*INDEX(Trayectorias!$K$15:$M$39,MATCH($A24,Trayectorias!$A$15:$A$39,0),$C$15)/1+$C$11*INDEX(Trayectorias!$K$15:$M$39,MATCH($A24,Trayectorias!$A$15:$A$39,0),$C$15)/($C$6*1000))*(1+$C$12)*(1+$C$13)/(1-$C$14) -> 246.78477 | C24: =($C$8*(1+MAX(0,1/2-Suministro_BESS!$A$13)*Suministro_BESS!$B$13)*$C$7*INDEX(Trayectorias!$B$15:$D$39,MATCH($A24,Trayectorias!$A$15:$A$39,0),$C$15)+$C$9*INDEX(Trayectorias!$K$15:$M$39,MATCH($A24,Trayectorias!$A$15:$A$39,0),$C$15)+$C$10*INDEX(Trayectorias!$K$15:$M$39,MATCH($A24,Trayectorias!$A$15:$A$39,0),$C$15)/2+$C$11*INDEX(Trayectorias!$K$15:$M$39,MATCH($A24,Trayectorias!$A$15:$A$39,0),$C$15)/($C$6*1000))*(1+$C$12)*(1+$C$13)/(1-$C$14) -> 182.5588 | D24: =($C$8*(1+MAX(0,1/3-Suministro_BESS!$A$13)*Suministro_BESS!$B$13)*$C$7*INDEX(Trayectorias!$B$15:$D$39,MATCH($A24,Trayectorias!$A$15:$A$39,0),$C$15)+$C$9*INDEX(Trayectorias!$K$15:$M$39,MATCH($A24,Trayectorias!$A$15:$A$39,0),$C$15)+$C$10*INDEX(Trayectorias!$K$15:$M$39,MATCH($A24,Trayectorias!$A$15:$A$39,0),$C$15)/3+$C$11*INDEX(Trayectorias!$K$15:$M$39,MATCH($A24,Trayectorias!$A$15:$A$39,0),$C$15)/($C$6*1000))*(1+$C$12)*(1+$C$13)/(1-$C$14) -> 165.10318 | E24: =($C$8*(1+MAX(0,1/4-Suministro_BESS!$A$13)*Suministro_BESS!$B$13)*$C$7*INDEX(Trayectorias!$B$15:$D$39,MATCH($A24,Trayectorias!$A$15:$A$39,0),$C$15)+$C$9*INDEX(Trayectorias!$K$15:$M$39,MATCH($A24,Trayectorias!$A$15:$A$39,0),$C$15)+$C$10*INDEX(Trayectorias!$K$15:$M$39,MATCH($A24,Trayectorias!$A$15:$A$39,0),$C$15)/4+$C$11*INDEX(Trayectorias!$K$15:$M$39,MATCH($A24,Trayectorias!$A$15:$A$39,0),$C$15)/($C$6*1000))*(1+$C$12)*(1+$C$13)/(1-$C$14) -> 156.37537 | F24: =($C$8*(1+MAX(0,1/5-Suministro_BESS!$A$13)*Suministro_BESS!$B$13)*$C$7*INDEX(Trayectorias!$B$15:$D$39,MATCH($A24,Trayectorias!$A$15:$A$39,0),$C$15)+$C$9*INDEX(Trayectorias!$K$15:$M$39,MATCH($A24,Trayectorias!$A$15:$A$39,0),$C$15)+$C$10*INDEX(Trayectorias!$K$15:$M$39,MATCH($A24,Trayectorias!$A$15:$A$39,0),$C$15)/5+$C$11*INDEX(Trayectorias!$K$15:$M$39,MATCH($A24,Trayectorias!$A$15:$A$39,0),$C$15)/($C$6*1000))*(1+$C$12)*(1+$C$13)/(1-$C$14) -> 151.13869 | G24: =($C$8*(1+MAX(0,1/6-Suministro_BESS!$A$13)*Suministro_BESS!$B$13)*$C$7*INDEX(Trayectorias!$B$15:$D$39,MATCH($A24,Trayectorias!$A$15:$A$39,0),$C$15)+$C$9*INDEX(Trayectorias!$K$15:$M$39,MATCH($A24,Trayectorias!$A$15:$A$39,0),$C$15)+$C$10*INDEX(Trayectorias!$K$15:$M$39,MATCH($A24,Trayectorias!$A$15:$A$39,0),$C$15)/6+$C$11*INDEX(Trayectorias!$K$15:$M$39,MATCH($A24,Trayectorias!$A$15:$A$39,0),$C$15)/($C$6*1000))*(1+$C$12)*(1+$C$13)/(1-$C$14) -> 147.64756 | H24: =($C$8*(1+MAX(0,1/7-Suministro_BESS!$A$13)*Suministro_BESS!$B$13)*$C$7*INDEX(Trayectorias!$B$15:$D$39,MATCH($A24,Trayectorias!$A$15:$A$39,0),$C$15)+$C$9*INDEX(Trayectorias!$K$15:$M$39,MATCH($A24,Trayectorias!$A$15:$A$39,0),$C$15)+$C$10*INDEX(Trayectorias!$K$15:$M$39,MATCH($A24,Trayectorias!$A$15:$A$39,0),$C$15)/7+$C$11*INDEX(Trayectorias!$K$15:$M$39,MATCH($A24,Trayectorias!$A$15:$A$39,0),$C$15)/($C$6*1000))*(1+$C$12)*(1+$C$13)/(1-$C$14) -> 145.1539 | I24: =($C$8*(1+MAX(0,1/8-Suministro_BESS!$A$13)*Suministro_BESS!$B$13)*$C$7*INDEX(Trayectorias!$B$15:$D$39,MATCH($A24,Trayectorias!$A$15:$A$39,0),$C$15)+$C$9*INDEX(Trayectorias!$K$15:$M$39,MATCH($A24,Trayectorias!$A$15:$A$39,0),$C$15)+$C$10*INDEX(Trayectorias!$K$15:$M$39,MATCH($A24,Trayectorias!$A$15:$A$39,0),$C$15)/8+$C$11*INDEX(Trayectorias!$K$15:$M$39,MATCH($A24,Trayectorias!$A$15:$A$39,0),$C$15)/($C$6*1000))*(1+$C$12)*(1+$C$13)/(1-$C$14) -> 143.28366
A25: 2032 | B25: =($C$8*(1+MAX(0,1/1-Suministro_BESS!$A$13)*Suministro_BESS!$B$13)*$C$7*INDEX(Trayectorias!$B$15:$D$39,MATCH($A25,Trayectorias!$A$15:$A$39,0),$C$15)+$C$9*INDEX(Trayectorias!$K$15:$M$39,MATCH($A25,Trayectorias!$A$15:$A$39,0),$C$15)+$C$10*INDEX(Trayectorias!$K$15:$M$39,MATCH($A25,Trayectorias!$A$15:$A$39,0),$C$15)/1+$C$11*INDEX(Trayectorias!$K$15:$M$39,MATCH($A25,Trayectorias!$A$15:$A$39,0),$C$15)/($C$6*1000))*(1+$C$12)*(1+$C$13)/(1-$C$14) -> 240.78477 | C25: =($C$8*(1+MAX(0,1/2-Suministro_BESS!$A$13)*Suministro_BESS!$B$13)*$C$7*INDEX(Trayectorias!$B$15:$D$39,MATCH($A25,Trayectorias!$A$15:$A$39,0),$C$15)+$C$9*INDEX(Trayectorias!$K$15:$M$39,MATCH($A25,Trayectorias!$A$15:$A$39,0),$C$15)+$C$10*INDEX(Trayectorias!$K$15:$M$39,MATCH($A25,Trayectorias!$A$15:$A$39,0),$C$15)/2+$C$11*INDEX(Trayectorias!$K$15:$M$39,MATCH($A25,Trayectorias!$A$15:$A$39,0),$C$15)/($C$6*1000))*(1+$C$12)*(1+$C$13)/(1-$C$14) -> 177.94481 | D25: =($C$8*(1+MAX(0,1/3-Suministro_BESS!$A$13)*Suministro_BESS!$B$13)*$C$7*INDEX(Trayectorias!$B$15:$D$39,MATCH($A25,Trayectorias!$A$15:$A$39,0),$C$15)+$C$9*INDEX(Trayectorias!$K$15:$M$39,MATCH($A25,Trayectorias!$A$15:$A$39,0),$C$15)+$C$10*INDEX(Trayectorias!$K$15:$M$39,MATCH($A25,Trayectorias!$A$15:$A$39,0),$C$15)/3+$C$11*INDEX(Trayectorias!$K$15:$M$39,MATCH($A25,Trayectorias!$A$15:$A$39,0),$C$15)/($C$6*1000))*(1+$C$12)*(1+$C$13)/(1-$C$14) -> 160.83655 | E25: =($C$8*(1+MAX(0,1/4-Suministro_BESS!$A$13)*Suministro_BESS!$B$13)*$C$7*INDEX(Trayectorias!$B$15:$D$39,MATCH($A25,Trayectorias!$A$15:$A$39,0),$C$15)+$C$9*INDEX(Trayectorias!$K$15:$M$39,MATCH($A25,Trayectorias!$A$15:$A$39,0),$C$15)+$C$10*INDEX(Trayectorias!$K$15:$M$39,MATCH($A25,Trayectorias!$A$15:$A$39,0),$C$15)/4+$C$11*INDEX(Trayectorias!$K$15:$M$39,MATCH($A25,Trayectorias!$A$15:$A$39,0),$C$15)/($C$6*1000))*(1+$C$12)*(1+$C$13)/(1-$C$14) -> 152.28243 | F25: =($C$8*(1+MAX(0,1/5-Suministro_BESS!$A$13)*Suministro_BESS!$B$13)*$C$7*INDEX(Trayectorias!$B$15:$D$39,MATCH($A25,Trayectorias!$A$15:$A$39,0),$C$15)+$C$9*INDEX(Trayectorias!$K$15:$M$39,MATCH($A25,Trayectorias!$A$15:$A$39,0),$C$15)+$C$10*INDEX(Trayectorias!$K$15:$M$39,MATCH($A25,Trayectorias!$A$15:$A$39,0),$C$15)/5+$C$11*INDEX(Trayectorias!$K$15:$M$39,MATCH($A25,Trayectorias!$A$15:$A$39,0),$C$15)/($C$6*1000))*(1+$C$12)*(1+$C$13)/(1-$C$14) -> 147.14995 | G25: =($C$8*(1+MAX(0,1/6-Suministro_BESS!$A$13)*Suministro_BESS!$B$13)*$C$7*INDEX(Trayectorias!$B$15:$D$39,MATCH($A25,Trayectorias!$A$15:$A$39,0),$C$15)+$C$9*INDEX(Trayectorias!$K$15:$M$39,MATCH($A25,Trayectorias!$A$15:$A$39,0),$C$15)+$C$10*INDEX(Trayectorias!$K$15:$M$39,MATCH($A25,Trayectorias!$A$15:$A$39,0),$C$15)/6+$C$11*INDEX(Trayectorias!$K$15:$M$39,MATCH($A25,Trayectorias!$A$15:$A$39,0),$C$15)/($C$6*1000))*(1+$C$12)*(1+$C$13)/(1-$C$14) -> 143.7283 | H25: =($C$8*(1+MAX(0,1/7-Suministro_BESS!$A$13)*Suministro_BESS!$B$13)*$C$7*INDEX(Trayectorias!$B$15:$D$39,MATCH($A25,Trayectorias!$A$15:$A$39,0),$C$15)+$C$9*INDEX(Trayectorias!$K$15:$M$39,MATCH($A25,Trayectorias!$A$15:$A$39,0),$C$15)+$C$10*INDEX(Trayectorias!$K$15:$M$39,MATCH($A25,Trayectorias!$A$15:$A$39,0),$C$15)/7+$C$11*INDEX(Trayectorias!$K$15:$M$39,MATCH($A25,Trayectorias!$A$15:$A$39,0),$C$15)/($C$6*1000))*(1+$C$12)*(1+$C$13)/(1-$C$14) -> 141.28427 | I25: =($C$8*(1+MAX(0,1/8-Suministro_BESS!$A$13)*Suministro_BESS!$B$13)*$C$7*INDEX(Trayectorias!$B$15:$D$39,MATCH($A25,Trayectorias!$A$15:$A$39,0),$C$15)+$C$9*INDEX(Trayectorias!$K$15:$M$39,MATCH($A25,Trayectorias!$A$15:$A$39,0),$C$15)+$C$10*INDEX(Trayectorias!$K$15:$M$39,MATCH($A25,Trayectorias!$A$15:$A$39,0),$C$15)/8+$C$11*INDEX(Trayectorias!$K$15:$M$39,MATCH($A25,Trayectorias!$A$15:$A$39,0),$C$15)/($C$6*1000))*(1+$C$12)*(1+$C$13)/(1-$C$14) -> 139.45124
A26: 2033 | B26: =($C$8*(1+MAX(0,1/1-Suministro_BESS!$A$13)*Suministro_BESS!$B$13)*$C$7*INDEX(Trayectorias!$B$15:$D$39,MATCH($A26,Trayectorias!$A$15:$A$39,0),$C$15)+$C$9*INDEX(Trayectorias!$K$15:$M$39,MATCH($A26,Trayectorias!$A$15:$A$39,0),$C$15)+$C$10*INDEX(Trayectorias!$K$15:$M$39,MATCH($A26,Trayectorias!$A$15:$A$39,0),$C$15)/1+$C$11*INDEX(Trayectorias!$K$15:$M$39,MATCH($A26,Trayectorias!$A$15:$A$39,0),$C$15)/($C$6*1000))*(1+$C$12)*(1+$C$13)/(1-$C$14) -> 234.93574 | C26: =($C$8*(1+MAX(0,1/2-Suministro_BESS!$A$13)*Suministro_BESS!$B$13)*$C$7*INDEX(Trayectorias!$B$15:$D$39,MATCH($A26,Trayectorias!$A$15:$A$39,0),$C$15)+$C$9*INDEX(Trayectorias!$K$15:$M$39,MATCH($A26,Trayectorias!$A$15:$A$39,0),$C$15)+$C$10*INDEX(Trayectorias!$K$15:$M$39,MATCH($A26,Trayectorias!$A$15:$A$39,0),$C$15)/2+$C$11*INDEX(Trayectorias!$K$15:$M$39,MATCH($A26,Trayectorias!$A$15:$A$39,0),$C$15)/($C$6*1000))*(1+$C$12)*(1+$C$13)/(1-$C$14) -> 173.45108 | D26: =($C$8*(1+MAX(0,1/3-Suministro_BESS!$A$13)*Suministro_BESS!$B$13)*$C$7*INDEX(Trayectorias!$B$15:$D$39,MATCH($A26,Trayectorias!$A$15:$A$39,0),$C$15)+$C$9*INDEX(Trayectorias!$K$15:$M$39,MATCH($A26,Trayectorias!$A$15:$A$39,0),$C$15)+$C$10*INDEX(Trayectorias!$K$15:$M$39,MATCH($A26,Trayectorias!$A$15:$A$39,0),$C$15)/3+$C$11*INDEX(Trayectorias!$K$15:$M$39,MATCH($A26,Trayectorias!$A$15:$A$39,0),$C$15)/($C$6*1000))*(1+$C$12)*(1+$C$13)/(1-$C$14) -> 156.68329 | E26: =($C$8*(1+MAX(0,1/4-Suministro_BESS!$A$13)*Suministro_BESS!$B$13)*$C$7*INDEX(Trayectorias!$B$15:$D$39,MATCH($A26,Trayectorias!$A$15:$A$39,0),$C$15)+$C$9*INDEX(Trayectorias!$K$15:$M$39,MATCH($A26,Trayectorias!$A$15:$A$39,0),$C$15)+$C$10*INDEX(Trayectorias!$K$15:$M$39,MATCH($A26,Trayectorias!$A$15:$A$39,0),$C$15)/4+$C$11*INDEX(Trayectorias!$K$15:$M$39,MATCH($A26,Trayectorias!$A$15:$A$39,0),$C$15)/($C$6*1000))*(1+$C$12)*(1+$C$13)/(1-$C$14) -> 148.29939 | F26: =($C$8*(1+MAX(0,1/5-Suministro_BESS!$A$13)*Suministro_BESS!$B$13)*$C$7*INDEX(Trayectorias!$B$15:$D$39,MATCH($A26,Trayectorias!$A$15:$A$39,0),$C$15)+$C$9*INDEX(Trayectorias!$K$15:$M$39,MATCH($A26,Trayectorias!$A$15:$A$39,0),$C$15)+$C$10*INDEX(Trayectorias!$K$15:$M$39,MATCH($A26,Trayectorias!$A$15:$A$39,0),$C$15)/5+$C$11*INDEX(Trayectorias!$K$15:$M$39,MATCH($A26,Trayectorias!$A$15:$A$39,0),$C$15)/($C$6*1000))*(1+$C$12)*(1+$C$13)/(1-$C$14) -> 143.26905 | G26: =($C$8*(1+MAX(0,1/6-Suministro_BESS!$A$13)*Suministro_BESS!$B$13)*$C$7*INDEX(Trayectorias!$B$15:$D$39,MATCH($A26,Trayectorias!$A$15:$A$39,0),$C$15)+$C$9*INDEX(Trayectorias!$K$15:$M$39,MATCH($A26,Trayectorias!$A$15:$A$39,0),$C$15)+$C$10*INDEX(Trayectorias!$K$15:$M$39,MATCH($A26,Trayectorias!$A$15:$A$39,0),$C$15)/6+$C$11*INDEX(Trayectorias!$K$15:$M$39,MATCH($A26,Trayectorias!$A$15:$A$39,0),$C$15)/($C$6*1000))*(1+$C$12)*(1+$C$13)/(1-$C$14) -> 139.91549 | H26: =($C$8*(1+MAX(0,1/7-Suministro_BESS!$A$13)*Suministro_BESS!$B$13)*$C$7*INDEX(Trayectorias!$B$15:$D$39,MATCH($A26,Trayectorias!$A$15:$A$39,0),$C$15)+$C$9*INDEX(Trayectorias!$K$15:$M$39,MATCH($A26,Trayectorias!$A$15:$A$39,0),$C$15)+$C$10*INDEX(Trayectorias!$K$15:$M$39,MATCH($A26,Trayectorias!$A$15:$A$39,0),$C$15)/7+$C$11*INDEX(Trayectorias!$K$15:$M$39,MATCH($A26,Trayectorias!$A$15:$A$39,0),$C$15)/($C$6*1000))*(1+$C$12)*(1+$C$13)/(1-$C$14) -> 137.52009 | I26: =($C$8*(1+MAX(0,1/8-Suministro_BESS!$A$13)*Suministro_BESS!$B$13)*$C$7*INDEX(Trayectorias!$B$15:$D$39,MATCH($A26,Trayectorias!$A$15:$A$39,0),$C$15)+$C$9*INDEX(Trayectorias!$K$15:$M$39,MATCH($A26,Trayectorias!$A$15:$A$39,0),$C$15)+$C$10*INDEX(Trayectorias!$K$15:$M$39,MATCH($A26,Trayectorias!$A$15:$A$39,0),$C$15)/8+$C$11*INDEX(Trayectorias!$K$15:$M$39,MATCH($A26,Trayectorias!$A$15:$A$39,0),$C$15)/($C$6*1000))*(1+$C$12)*(1+$C$13)/(1-$C$14) -> 135.72354
A27: 2034 | B27: =($C$8*(1+MAX(0,1/1-Suministro_BESS!$A$13)*Suministro_BESS!$B$13)*$C$7*INDEX(Trayectorias!$B$15:$D$39,MATCH($A27,Trayectorias!$A$15:$A$39,0),$C$15)+$C$9*INDEX(Trayectorias!$K$15:$M$39,MATCH($A27,Trayectorias!$A$15:$A$39,0),$C$15)+$C$10*INDEX(Trayectorias!$K$15:$M$39,MATCH($A27,Trayectorias!$A$15:$A$39,0),$C$15)/1+$C$11*INDEX(Trayectorias!$K$15:$M$39,MATCH($A27,Trayectorias!$A$15:$A$39,0),$C$15)/($C$6*1000))*(1+$C$12)*(1+$C$13)/(1-$C$14) -> 229.23377 | C27: =($C$8*(1+MAX(0,1/2-Suministro_BESS!$A$13)*Suministro_BESS!$B$13)*$C$7*INDEX(Trayectorias!$B$15:$D$39,MATCH($A27,Trayectorias!$A$15:$A$39,0),$C$15)+$C$9*INDEX(Trayectorias!$K$15:$M$39,MATCH($A27,Trayectorias!$A$15:$A$39,0),$C$15)+$C$10*INDEX(Trayectorias!$K$15:$M$39,MATCH($A27,Trayectorias!$A$15:$A$39,0),$C$15)/2+$C$11*INDEX(Trayectorias!$K$15:$M$39,MATCH($A27,Trayectorias!$A$15:$A$39,0),$C$15)/($C$6*1000))*(1+$C$12)*(1+$C$13)/(1-$C$14) -> 169.07441 | D27: =($C$8*(1+MAX(0,1/3-Suministro_BESS!$A$13)*Suministro_BESS!$B$13)*$C$7*INDEX(Trayectorias!$B$15:$D$39,MATCH($A27,Trayectorias!$A$15:$A$39,0),$C$15)+$C$9*INDEX(Trayectorias!$K$15:$M$39,MATCH($A27,Trayectorias!$A$15:$A$39,0),$C$15)+$C$10*INDEX(Trayectorias!$K$15:$M$39,MATCH($A27,Trayectorias!$A$15:$A$39,0),$C$15)/3+$C$11*INDEX(Trayectorias!$K$15:$M$39,MATCH($A27,Trayectorias!$A$15:$A$39,0),$C$15)/($C$6*1000))*(1+$C$12)*(1+$C$13)/(1-$C$14) -> 152.64029 | E27: =($C$8*(1+MAX(0,1/4-Suministro_BESS!$A$13)*Suministro_BESS!$B$13)*$C$7*INDEX(Trayectorias!$B$15:$D$39,MATCH($A27,Trayectorias!$A$15:$A$39,0),$C$15)+$C$9*INDEX(Trayectorias!$K$15:$M$39,MATCH($A27,Trayectorias!$A$15:$A$39,0),$C$15)+$C$10*INDEX(Trayectorias!$K$15:$M$39,MATCH($A27,Trayectorias!$A$15:$A$39,0),$C$15)/4+$C$11*INDEX(Trayectorias!$K$15:$M$39,MATCH($A27,Trayectorias!$A$15:$A$39,0),$C$15)/($C$6*1000))*(1+$C$12)*(1+$C$13)/(1-$C$14) -> 144.42323 | F27: =($C$8*(1+MAX(0,1/5-Suministro_BESS!$A$13)*Suministro_BESS!$B$13)*$C$7*INDEX(Trayectorias!$B$15:$D$39,MATCH($A27,Trayectorias!$A$15:$A$39,0),$C$15)+$C$9*INDEX(Trayectorias!$K$15:$M$39,MATCH($A27,Trayectorias!$A$15:$A$39,0),$C$15)+$C$10*INDEX(Trayectorias!$K$15:$M$39,MATCH($A27,Trayectorias!$A$15:$A$39,0),$C$15)/5+$C$11*INDEX(Trayectorias!$K$15:$M$39,MATCH($A27,Trayectorias!$A$15:$A$39,0),$C$15)/($C$6*1000))*(1+$C$12)*(1+$C$13)/(1-$C$14) -> 139.493 | G27: =($C$8*(1+MAX(0,1/6-Suministro_BESS!$A$13)*Suministro_BESS!$B$13)*$C$7*INDEX(Trayectorias!$B$15:$D$39,MATCH($A27,Trayectorias!$A$15:$A$39,0),$C$15)+$C$9*INDEX(Trayectorias!$K$15:$M$39,MATCH($A27,Trayectorias!$A$15:$A$39,0),$C$15)+$C$10*INDEX(Trayectorias!$K$15:$M$39,MATCH($A27,Trayectorias!$A$15:$A$39,0),$C$15)/6+$C$11*INDEX(Trayectorias!$K$15:$M$39,MATCH($A27,Trayectorias!$A$15:$A$39,0),$C$15)/($C$6*1000))*(1+$C$12)*(1+$C$13)/(1-$C$14) -> 136.20617 | H27: =($C$8*(1+MAX(0,1/7-Suministro_BESS!$A$13)*Suministro_BESS!$B$13)*$C$7*INDEX(Trayectorias!$B$15:$D$39,MATCH($A27,Trayectorias!$A$15:$A$39,0),$C$15)+$C$9*INDEX(Trayectorias!$K$15:$M$39,MATCH($A27,Trayectorias!$A$15:$A$39,0),$C$15)+$C$10*INDEX(Trayectorias!$K$15:$M$39,MATCH($A27,Trayectorias!$A$15:$A$39,0),$C$15)/7+$C$11*INDEX(Trayectorias!$K$15:$M$39,MATCH($A27,Trayectorias!$A$15:$A$39,0),$C$15)/($C$6*1000))*(1+$C$12)*(1+$C$13)/(1-$C$14) -> 133.85844 | I27: =($C$8*(1+MAX(0,1/8-Suministro_BESS!$A$13)*Suministro_BESS!$B$13)*$C$7*INDEX(Trayectorias!$B$15:$D$39,MATCH($A27,Trayectorias!$A$15:$A$39,0),$C$15)+$C$9*INDEX(Trayectorias!$K$15:$M$39,MATCH($A27,Trayectorias!$A$15:$A$39,0),$C$15)+$C$10*INDEX(Trayectorias!$K$15:$M$39,MATCH($A27,Trayectorias!$A$15:$A$39,0),$C$15)/8+$C$11*INDEX(Trayectorias!$K$15:$M$39,MATCH($A27,Trayectorias!$A$15:$A$39,0),$C$15)/($C$6*1000))*(1+$C$12)*(1+$C$13)/(1-$C$14) -> 132.09764
A28: 2035 | B28: =($C$8*(1+MAX(0,1/1-Suministro_BESS!$A$13)*Suministro_BESS!$B$13)*$C$7*INDEX(Trayectorias!$B$15:$D$39,MATCH($A28,Trayectorias!$A$15:$A$39,0),$C$15)+$C$9*INDEX(Trayectorias!$K$15:$M$39,MATCH($A28,Trayectorias!$A$15:$A$39,0),$C$15)+$C$10*INDEX(Trayectorias!$K$15:$M$39,MATCH($A28,Trayectorias!$A$15:$A$39,0),$C$15)/1+$C$11*INDEX(Trayectorias!$K$15:$M$39,MATCH($A28,Trayectorias!$A$15:$A$39,0),$C$15)/($C$6*1000))*(1+$C$12)*(1+$C$13)/(1-$C$14) -> 223.67505 | C28: =($C$8*(1+MAX(0,1/2-Suministro_BESS!$A$13)*Suministro_BESS!$B$13)*$C$7*INDEX(Trayectorias!$B$15:$D$39,MATCH($A28,Trayectorias!$A$15:$A$39,0),$C$15)+$C$9*INDEX(Trayectorias!$K$15:$M$39,MATCH($A28,Trayectorias!$A$15:$A$39,0),$C$15)+$C$10*INDEX(Trayectorias!$K$15:$M$39,MATCH($A28,Trayectorias!$A$15:$A$39,0),$C$15)/2+$C$11*INDEX(Trayectorias!$K$15:$M$39,MATCH($A28,Trayectorias!$A$15:$A$39,0),$C$15)/($C$6*1000))*(1+$C$12)*(1+$C$13)/(1-$C$14) -> 164.81166 | D28: =($C$8*(1+MAX(0,1/3-Suministro_BESS!$A$13)*Suministro_BESS!$B$13)*$C$7*INDEX(Trayectorias!$B$15:$D$39,MATCH($A28,Trayectorias!$A$15:$A$39,0),$C$15)+$C$9*INDEX(Trayectorias!$K$15:$M$39,MATCH($A28,Trayectorias!$A$15:$A$39,0),$C$15)+$C$10*INDEX(Trayectorias!$K$15:$M$39,MATCH($A28,Trayectorias!$A$15:$A$39,0),$C$15)/3+$C$11*INDEX(Trayectorias!$K$15:$M$39,MATCH($A28,Trayectorias!$A$15:$A$39,0),$C$15)/($C$6*1000))*(1+$C$12)*(1+$C$13)/(1-$C$14) -> 148.70458 | E28: =($C$8*(1+MAX(0,1/4-Suministro_BESS!$A$13)*Suministro_BESS!$B$13)*$C$7*INDEX(Trayectorias!$B$15:$D$39,MATCH($A28,Trayectorias!$A$15:$A$39,0),$C$15)+$C$9*INDEX(Trayectorias!$K$15:$M$39,MATCH($A28,Trayectorias!$A$15:$A$39,0),$C$15)+$C$10*INDEX(Trayectorias!$K$15:$M$39,MATCH($A28,Trayectorias!$A$15:$A$39,0),$C$15)/4+$C$11*INDEX(Trayectorias!$K$15:$M$39,MATCH($A28,Trayectorias!$A$15:$A$39,0),$C$15)/($C$6*1000))*(1+$C$12)*(1+$C$13)/(1-$C$14) -> 140.65104 | F28: =($C$8*(1+MAX(0,1/5-Suministro_BESS!$A$13)*Suministro_BESS!$B$13)*$C$7*INDEX(Trayectorias!$B$15:$D$39,MATCH($A28,Trayectorias!$A$15:$A$39,0),$C$15)+$C$9*INDEX(Trayectorias!$K$15:$M$39,MATCH($A28,Trayectorias!$A$15:$A$39,0),$C$15)+$C$10*INDEX(Trayectorias!$K$15:$M$39,MATCH($A28,Trayectorias!$A$15:$A$39,0),$C$15)/5+$C$11*INDEX(Trayectorias!$K$15:$M$39,MATCH($A28,Trayectorias!$A$15:$A$39,0),$C$15)/($C$6*1000))*(1+$C$12)*(1+$C$13)/(1-$C$14) -> 135.81892 | G28: =($C$8*(1+MAX(0,1/6-Suministro_BESS!$A$13)*Suministro_BESS!$B$13)*$C$7*INDEX(Trayectorias!$B$15:$D$39,MATCH($A28,Trayectorias!$A$15:$A$39,0),$C$15)+$C$9*INDEX(Trayectorias!$K$15:$M$39,MATCH($A28,Trayectorias!$A$15:$A$39,0),$C$15)+$C$10*INDEX(Trayectorias!$K$15:$M$39,MATCH($A28,Trayectorias!$A$15:$A$39,0),$C$15)/6+$C$11*INDEX(Trayectorias!$K$15:$M$39,MATCH($A28,Trayectorias!$A$15:$A$39,0),$C$15)/($C$6*1000))*(1+$C$12)*(1+$C$13)/(1-$C$14) -> 132.5975 | H28: =($C$8*(1+MAX(0,1/7-Suministro_BESS!$A$13)*Suministro_BESS!$B$13)*$C$7*INDEX(Trayectorias!$B$15:$D$39,MATCH($A28,Trayectorias!$A$15:$A$39,0),$C$15)+$C$9*INDEX(Trayectorias!$K$15:$M$39,MATCH($A28,Trayectorias!$A$15:$A$39,0),$C$15)+$C$10*INDEX(Trayectorias!$K$15:$M$39,MATCH($A28,Trayectorias!$A$15:$A$39,0),$C$15)/7+$C$11*INDEX(Trayectorias!$K$15:$M$39,MATCH($A28,Trayectorias!$A$15:$A$39,0),$C$15)/($C$6*1000))*(1+$C$12)*(1+$C$13)/(1-$C$14) -> 130.29649 | I28: =($C$8*(1+MAX(0,1/8-Suministro_BESS!$A$13)*Suministro_BESS!$B$13)*$C$7*INDEX(Trayectorias!$B$15:$D$39,MATCH($A28,Trayectorias!$A$15:$A$39,0),$C$15)+$C$9*INDEX(Trayectorias!$K$15:$M$39,MATCH($A28,Trayectorias!$A$15:$A$39,0),$C$15)+$C$10*INDEX(Trayectorias!$K$15:$M$39,MATCH($A28,Trayectorias!$A$15:$A$39,0),$C$15)/8+$C$11*INDEX(Trayectorias!$K$15:$M$39,MATCH($A28,Trayectorias!$A$15:$A$39,0),$C$15)/($C$6*1000))*(1+$C$12)*(1+$C$13)/(1-$C$14) -> 128.57073
A29: 2036 | B29: =($C$8*(1+MAX(0,1/1-Suministro_BESS!$A$13)*Suministro_BESS!$B$13)*$C$7*INDEX(Trayectorias!$B$15:$D$39,MATCH($A29,Trayectorias!$A$15:$A$39,0),$C$15)+$C$9*INDEX(Trayectorias!$K$15:$M$39,MATCH($A29,Trayectorias!$A$15:$A$39,0),$C$15)+$C$10*INDEX(Trayectorias!$K$15:$M$39,MATCH($A29,Trayectorias!$A$15:$A$39,0),$C$15)/1+$C$11*INDEX(Trayectorias!$K$15:$M$39,MATCH($A29,Trayectorias!$A$15:$A$39,0),$C$15)/($C$6*1000))*(1+$C$12)*(1+$C$13)/(1-$C$14) -> 220.60828 | C29: =($C$8*(1+MAX(0,1/2-Suministro_BESS!$A$13)*Suministro_BESS!$B$13)*$C$7*INDEX(Trayectorias!$B$15:$D$39,MATCH($A29,Trayectorias!$A$15:$A$39,0),$C$15)+$C$9*INDEX(Trayectorias!$K$15:$M$39,MATCH($A29,Trayectorias!$A$15:$A$39,0),$C$15)+$C$10*INDEX(Trayectorias!$K$15:$M$39,MATCH($A29,Trayectorias!$A$15:$A$39,0),$C$15)/2+$C$11*INDEX(Trayectorias!$K$15:$M$39,MATCH($A29,Trayectorias!$A$15:$A$39,0),$C$15)/($C$6*1000))*(1+$C$12)*(1+$C$13)/(1-$C$14) -> 162.30935 | D29: =($C$8*(1+MAX(0,1/3-Suministro_BESS!$A$13)*Suministro_BESS!$B$13)*$C$7*INDEX(Trayectorias!$B$15:$D$39,MATCH($A29,Trayectorias!$A$15:$A$39,0),$C$15)+$C$9*INDEX(Trayectorias!$K$15:$M$39,MATCH($A29,Trayectorias!$A$15:$A$39,0),$C$15)+$C$10*INDEX(Trayectorias!$K$15:$M$39,MATCH($A29,Trayectorias!$A$15:$A$39,0),$C$15)/3+$C$11*INDEX(Trayectorias!$K$15:$M$39,MATCH($A29,Trayectorias!$A$15:$A$39,0),$C$15)/($C$6*1000))*(1+$C$12)*(1+$C$13)/(1-$C$14) -> 146.31663 | E29: =($C$8*(1+MAX(0,1/4-Suministro_BESS!$A$13)*Suministro_BESS!$B$13)*$C$7*INDEX(Trayectorias!$B$15:$D$39,MATCH($A29,Trayectorias!$A$15:$A$39,0),$C$15)+$C$9*INDEX(Trayectorias!$K$15:$M$39,MATCH($A29,Trayectorias!$A$15:$A$39,0),$C$15)+$C$10*INDEX(Trayectorias!$K$15:$M$39,MATCH($A29,Trayectorias!$A$15:$A$39,0),$C$15)/4+$C$11*INDEX(Trayectorias!$K$15:$M$39,MATCH($A29,Trayectorias!$A$15:$A$39,0),$C$15)/($C$6*1000))*(1+$C$12)*(1+$C$13)/(1-$C$14) -> 138.32027 | F29: =($C$8*(1+MAX(0,1/5-Suministro_BESS!$A$13)*Suministro_BESS!$B$13)*$C$7*INDEX(Trayectorias!$B$15:$D$39,MATCH($A29,Trayectorias!$A$15:$A$39,0),$C$15)+$C$9*INDEX(Trayectorias!$K$15:$M$39,MATCH($A29,Trayectorias!$A$15:$A$39,0),$C$15)+$C$10*INDEX(Trayectorias!$K$15:$M$39,MATCH($A29,Trayectorias!$A$15:$A$39,0),$C$15)/5+$C$11*INDEX(Trayectorias!$K$15:$M$39,MATCH($A29,Trayectorias!$A$15:$A$39,0),$C$15)/($C$6*1000))*(1+$C$12)*(1+$C$13)/(1-$C$14) -> 133.52246 | G29: =($C$8*(1+MAX(0,1/6-Suministro_BESS!$A$13)*Suministro_BESS!$B$13)*$C$7*INDEX(Trayectorias!$B$15:$D$39,MATCH($A29,Trayectorias!$A$15:$A$39,0),$C$15)+$C$9*INDEX(Trayectorias!$K$15:$M$39,MATCH($A29,Trayectorias!$A$15:$A$39,0),$C$15)+$C$10*INDEX(Trayectorias!$K$15:$M$39,MATCH($A29,Trayectorias!$A$15:$A$39,0),$C$15)/6+$C$11*INDEX(Trayectorias!$K$15:$M$39,MATCH($A29,Trayectorias!$A$15:$A$39,0),$C$15)/($C$6*1000))*(1+$C$12)*(1+$C$13)/(1-$C$14) -> 130.32391 | H29: =($C$8*(1+MAX(0,1/7-Suministro_BESS!$A$13)*Suministro_BESS!$B$13)*$C$7*INDEX(Trayectorias!$B$15:$D$39,MATCH($A29,Trayectorias!$A$15:$A$39,0),$C$15)+$C$9*INDEX(Trayectorias!$K$15:$M$39,MATCH($A29,Trayectorias!$A$15:$A$39,0),$C$15)+$C$10*INDEX(Trayectorias!$K$15:$M$39,MATCH($A29,Trayectorias!$A$15:$A$39,0),$C$15)/7+$C$11*INDEX(Trayectorias!$K$15:$M$39,MATCH($A29,Trayectorias!$A$15:$A$39,0),$C$15)/($C$6*1000))*(1+$C$12)*(1+$C$13)/(1-$C$14) -> 128.03924 | I29: =($C$8*(1+MAX(0,1/8-Suministro_BESS!$A$13)*Suministro_BESS!$B$13)*$C$7*INDEX(Trayectorias!$B$15:$D$39,MATCH($A29,Trayectorias!$A$15:$A$39,0),$C$15)+$C$9*INDEX(Trayectorias!$K$15:$M$39,MATCH($A29,Trayectorias!$A$15:$A$39,0),$C$15)+$C$10*INDEX(Trayectorias!$K$15:$M$39,MATCH($A29,Trayectorias!$A$15:$A$39,0),$C$15)/8+$C$11*INDEX(Trayectorias!$K$15:$M$39,MATCH($A29,Trayectorias!$A$15:$A$39,0),$C$15)/($C$6*1000))*(1+$C$12)*(1+$C$13)/(1-$C$14) -> 126.32573
A30: 2037 | B30: =($C$8*(1+MAX(0,1/1-Suministro_BESS!$A$13)*Suministro_BESS!$B$13)*$C$7*INDEX(Trayectorias!$B$15:$D$39,MATCH($A30,Trayectorias!$A$15:$A$39,0),$C$15)+$C$9*INDEX(Trayectorias!$K$15:$M$39,MATCH($A30,Trayectorias!$A$15:$A$39,0),$C$15)+$C$10*INDEX(Trayectorias!$K$15:$M$39,MATCH($A30,Trayectorias!$A$15:$A$39,0),$C$15)/1+$C$11*INDEX(Trayectorias!$K$15:$M$39,MATCH($A30,Trayectorias!$A$15:$A$39,0),$C$15)/($C$6*1000))*(1+$C$12)*(1+$C$13)/(1-$C$14) -> 217.59433 | C30: =($C$8*(1+MAX(0,1/2-Suministro_BESS!$A$13)*Suministro_BESS!$B$13)*$C$7*INDEX(Trayectorias!$B$15:$D$39,MATCH($A30,Trayectorias!$A$15:$A$39,0),$C$15)+$C$9*INDEX(Trayectorias!$K$15:$M$39,MATCH($A30,Trayectorias!$A$15:$A$39,0),$C$15)+$C$10*INDEX(Trayectorias!$K$15:$M$39,MATCH($A30,Trayectorias!$A$15:$A$39,0),$C$15)/2+$C$11*INDEX(Trayectorias!$K$15:$M$39,MATCH($A30,Trayectorias!$A$15:$A$39,0),$C$15)/($C$6*1000))*(1+$C$12)*(1+$C$13)/(1-$C$14) -> 159.85279 | D30: =($C$8*(1+MAX(0,1/3-Suministro_BESS!$A$13)*Suministro_BESS!$B$13)*$C$7*INDEX(Trayectorias!$B$15:$D$39,MATCH($A30,Trayectorias!$A$15:$A$39,0),$C$15)+$C$9*INDEX(Trayectorias!$K$15:$M$39,MATCH($A30,Trayectorias!$A$15:$A$39,0),$C$15)+$C$10*INDEX(Trayectorias!$K$15:$M$39,MATCH($A30,Trayectorias!$A$15:$A$39,0),$C$15)/3+$C$11*INDEX(Trayectorias!$K$15:$M$39,MATCH($A30,Trayectorias!$A$15:$A$39,0),$C$15)/($C$6*1000))*(1+$C$12)*(1+$C$13)/(1-$C$14) -> 143.97362 | E30: =($C$8*(1+MAX(0,1/4-Suministro_BESS!$A$13)*Suministro_BESS!$B$13)*$C$7*INDEX(Trayectorias!$B$15:$D$39,MATCH($A30,Trayectorias!$A$15:$A$39,0),$C$15)+$C$9*INDEX(Trayectorias!$K$15:$M$39,MATCH($A30,Trayectorias!$A$15:$A$39,0),$C$15)+$C$10*INDEX(Trayectorias!$K$15:$M$39,MATCH($A30,Trayectorias!$A$15:$A$39,0),$C$15)/4+$C$11*INDEX(Trayectorias!$K$15:$M$39,MATCH($A30,Trayectorias!$A$15:$A$39,0),$C$15)/($C$6*1000))*(1+$C$12)*(1+$C$13)/(1-$C$14) -> 136.03403 | F30: =($C$8*(1+MAX(0,1/5-Suministro_BESS!$A$13)*Suministro_BESS!$B$13)*$C$7*INDEX(Trayectorias!$B$15:$D$39,MATCH($A30,Trayectorias!$A$15:$A$39,0),$C$15)+$C$9*INDEX(Trayectorias!$K$15:$M$39,MATCH($A30,Trayectorias!$A$15:$A$39,0),$C$15)+$C$10*INDEX(Trayectorias!$K$15:$M$39,MATCH($A30,Trayectorias!$A$15:$A$39,0),$C$15)/5+$C$11*INDEX(Trayectorias!$K$15:$M$39,MATCH($A30,Trayectorias!$A$15:$A$39,0),$C$15)/($C$6*1000))*(1+$C$12)*(1+$C$13)/(1-$C$14) -> 131.27028 | G30: =($C$8*(1+MAX(0,1/6-Suministro_BESS!$A$13)*Suministro_BESS!$B$13)*$C$7*INDEX(Trayectorias!$B$15:$D$39,MATCH($A30,Trayectorias!$A$15:$A$39,0),$C$15)+$C$9*INDEX(Trayectorias!$K$15:$M$39,MATCH($A30,Trayectorias!$A$15:$A$39,0),$C$15)+$C$10*INDEX(Trayectorias!$K$15:$M$39,MATCH($A30,Trayectorias!$A$15:$A$39,0),$C$15)/6+$C$11*INDEX(Trayectorias!$K$15:$M$39,MATCH($A30,Trayectorias!$A$15:$A$39,0),$C$15)/($C$6*1000))*(1+$C$12)*(1+$C$13)/(1-$C$14) -> 128.09444 | H30: =($C$8*(1+MAX(0,1/7-Suministro_BESS!$A$13)*Suministro_BESS!$B$13)*$C$7*INDEX(Trayectorias!$B$15:$D$39,MATCH($A30,Trayectorias!$A$15:$A$39,0),$C$15)+$C$9*INDEX(Trayectorias!$K$15:$M$39,MATCH($A30,Trayectorias!$A$15:$A$39,0),$C$15)+$C$10*INDEX(Trayectorias!$K$15:$M$39,MATCH($A30,Trayectorias!$A$15:$A$39,0),$C$15)/7+$C$11*INDEX(Trayectorias!$K$15:$M$39,MATCH($A30,Trayectorias!$A$15:$A$39,0),$C$15)/($C$6*1000))*(1+$C$12)*(1+$C$13)/(1-$C$14) -> 125.82599 | I30: =($C$8*(1+MAX(0,1/8-Suministro_BESS!$A$13)*Suministro_BESS!$B$13)*$C$7*INDEX(Trayectorias!$B$15:$D$39,MATCH($A30,Trayectorias!$A$15:$A$39,0),$C$15)+$C$9*INDEX(Trayectorias!$K$15:$M$39,MATCH($A30,Trayectorias!$A$15:$A$39,0),$C$15)+$C$10*INDEX(Trayectorias!$K$15:$M$39,MATCH($A30,Trayectorias!$A$15:$A$39,0),$C$15)/8+$C$11*INDEX(Trayectorias!$K$15:$M$39,MATCH($A30,Trayectorias!$A$15:$A$39,0),$C$15)/($C$6*1000))*(1+$C$12)*(1+$C$13)/(1-$C$14) -> 124.12465
... A43: 2050 | B43: =($C$8*(1+MAX(0,1/1-Suministro_BESS!$A$13)*Suministro_BESS!$B$13)*$C$7*INDEX(Trayectorias!$B$15:$D$39,MATCH($A43,Trayectorias!$A$15:$A$39,0),$C$15)+$C$9*INDEX(Trayectorias!$K$15:$M$39,MATCH($A43,Trayectorias!$A$15:$A$39,0),$C$15)+$C$10*INDEX(Trayectorias!$K$15:$M$39,MATCH($A43,Trayectorias!$A$15:$A$39,0),$C$15)/1+$C$11*INDEX(Trayectorias!$K$15:$M$39,MATCH($A43,Trayectorias!$A$15:$A$39,0),$C$15)/($C$6*1000))*(1+$C$12)*(1+$C$13)/(1-$C$14) -> 182.78024 | C43: =($C$8*(1+MAX(0,1/2-Suministro_BESS!$A$13)*Suministro_BESS!$B$13)*$C$7*INDEX(Trayectorias!$B$15:$D$39,MATCH($A43,Trayectorias!$A$15:$A$39,0),$C$15)+$C$9*INDEX(Trayectorias!$K$15:$M$39,MATCH($A43,Trayectorias!$A$15:$A$39,0),$C$15)+$C$10*INDEX(Trayectorias!$K$15:$M$39,MATCH($A43,Trayectorias!$A$15:$A$39,0),$C$15)/2+$C$11*INDEX(Trayectorias!$K$15:$M$39,MATCH($A43,Trayectorias!$A$15:$A$39,0),$C$15)/($C$6*1000))*(1+$C$12)*(1+$C$13)/(1-$C$14) -> 131.68937 | D43: =($C$8*(1+MAX(0,1/3-Suministro_BESS!$A$13)*Suministro_BESS!$B$13)*$C$7*INDEX(Trayectorias!$B$15:$D$39,MATCH($A43,Trayectorias!$A$15:$A$39,0),$C$15)+$C$9*INDEX(Trayectorias!$K$15:$M$39,MATCH($A43,Trayectorias!$A$15:$A$39,0),$C$15)+$C$10*INDEX(Trayectorias!$K$15:$M$39,MATCH($A43,Trayectorias!$A$15:$A$39,0),$C$15)/3+$C$11*INDEX(Trayectorias!$K$15:$M$39,MATCH($A43,Trayectorias!$A$15:$A$39,0),$C$15)/($C$6*1000))*(1+$C$12)*(1+$C$13)/(1-$C$14) -> 117.21501 | E43: =($C$8*(1+MAX(0,1/4-Suministro_BESS!$A$13)*Suministro_BESS!$B$13)*$C$7*INDEX(Trayectorias!$B$15:$D$39,MATCH($A43,Trayectorias!$A$15:$A$39,0),$C$15)+$C$9*INDEX(Trayectorias!$K$15:$M$39,MATCH($A43,Trayectorias!$A$15:$A$39,0),$C$15)+$C$10*INDEX(Trayectorias!$K$15:$M$39,MATCH($A43,Trayectorias!$A$15:$A$39,0),$C$15)/4+$C$11*INDEX(Trayectorias!$K$15:$M$39,MATCH($A43,Trayectorias!$A$15:$A$39,0),$C$15)/($C$6*1000))*(1+$C$12)*(1+$C$13)/(1-$C$14) -> 109.97782 | F43: =($C$8*(1+MAX(0,1/5-Suministro_BESS!$A$13)*Suministro_BESS!$B$13)*$C$7*INDEX(Trayectorias!$B$15:$D$39,MATCH($A43,Trayectorias!$A$15:$A$39,0),$C$15)+$C$9*INDEX(Trayectorias!$K$15:$M$39,MATCH($A43,Trayectorias!$A$15:$A$39,0),$C$15)+$C$10*INDEX(Trayectorias!$K$15:$M$39,MATCH($A43,Trayectorias!$A$15:$A$39,0),$C$15)/5+$C$11*INDEX(Trayectorias!$K$15:$M$39,MATCH($A43,Trayectorias!$A$15:$A$39,0),$C$15)/($C$6*1000))*(1+$C$12)*(1+$C$13)/(1-$C$14) -> 105.63552 | G43: =($C$8*(1+MAX(0,1/6-Suministro_BESS!$A$13)*Suministro_BESS!$B$13)*$C$7*INDEX(Trayectorias!$B$15:$D$39,MATCH($A43,Trayectorias!$A$15:$A$39,0),$C$15)+$C$9*INDEX(Trayectorias!$K$15:$M$39,MATCH($A43,Trayectorias!$A$15:$A$39,0),$C$15)+$C$10*INDEX(Trayectorias!$K$15:$M$39,MATCH($A43,Trayectorias!$A$15:$A$39,0),$C$15)/6+$C$11*INDEX(Trayectorias!$K$15:$M$39,MATCH($A43,Trayectorias!$A$15:$A$39,0),$C$15)/($C$6*1000))*(1+$C$12)*(1+$C$13)/(1-$C$14) -> 102.74064 | H43: =($C$8*(1+MAX(0,1/7-Suministro_BESS!$A$13)*Suministro_BESS!$B$13)*$C$7*INDEX(Trayectorias!$B$15:$D$39,MATCH($A43,Trayectorias!$A$15:$A$39,0),$C$15)+$C$9*INDEX(Trayectorias!$K$15:$M$39,MATCH($A43,Trayectorias!$A$15:$A$39,0),$C$15)+$C$10*INDEX(Trayectorias!$K$15:$M$39,MATCH($A43,Trayectorias!$A$15:$A$39,0),$C$15)/7+$C$11*INDEX(Trayectorias!$K$15:$M$39,MATCH($A43,Trayectorias!$A$15:$A$39,0),$C$15)/($C$6*1000))*(1+$C$12)*(1+$C$13)/(1-$C$14) -> 100.67288 | I43: =($C$8*(1+MAX(0,1/8-Suministro_BESS!$A$13)*Suministro_BESS!$B$13)*$C$7*INDEX(Trayectorias!$B$15:$D$39,MATCH($A43,Trayectorias!$A$15:$A$39,0),$C$15)+$C$9*INDEX(Trayectorias!$K$15:$M$39,MATCH($A43,Trayectorias!$A$15:$A$39,0),$C$15)+$C$10*INDEX(Trayectorias!$K$15:$M$39,MATCH($A43,Trayectorias!$A$15:$A$39,0),$C$15)/8+$C$11*INDEX(Trayectorias!$K$15:$M$39,MATCH($A43,Trayectorias!$A$15:$A$39,0),$C$15)/($C$6*1000))*(1+$C$12)*(1+$C$13)/(1-$C$14) -> 99.122052
A45: USD por kW de potencia nominal
A46: Año | B46: 1 h | C46: 2 h | D46: 3 h | E46: 4 h | F46: 5 h | G46: 6 h | H46: 7 h | I46: 8 h
A47: 2026 | B47: =B19*1 -> 279.19443 | C47: =C19*2 -> 415.10387 | D47: =D19*3 -> 564.75233 | E47: =E19*4 -> 714.4008 | F47: =F19*5 -> 864.04926 | G47: =G19*6 -> 1013.6977 | H47: =H19*7 -> 1163.3462 | I47: =I19*8 -> 1312.9947
A48: 2027 | B48: =B20*1 -> 272.37685 | C48: =C20*2 -> 404.57011 | D48: =D20*3 -> 550.10398 | E48: =E20*4 -> 695.63785 | F48: =F20*5 -> 841.17172 | G48: =G20*6 -> 986.70559 | H48: =H20*7 -> 1132.2395 | I48: =I20*8 -> 1277.7733
A49: 2028 | B49: =B21*1 -> 265.73152 | C49: =C21*2 -> 394.3119 | D49: =D21*3 -> 535.84602 | E49: =E21*4 -> 677.38013 | F49: =F21*5 -> 818.91424 | G49: =G21*6 -> 960.44836 | H49: =H21*7 -> 1101.9825 | I49: =I21*8 -> 1243.5166
A50: 2029 | B50: =B22*1 -> 259.25395 | C50: =C22*2 -> 384.32184 | D50: =D22*3 -> 521.9678 | E50: =E22*4 -> 659.61376 | F50: =F22*5 -> 797.25972 | G50: =G22*6 -> 934.90568 | H50: =H22*7 -> 1072.5516 | I50: =I22*8 -> 1210.1976
A51: 2030 | B51: =B23*1 -> 252.93979 | C51: =C23*2 -> 374.59274 | D51: =D23*3 -> 508.459 | E51: =E23*4 -> 642.32525 | F51: =F23*5 -> 776.1915 | G51: =G23*6 -> 910.05776 | H51: =H23*7 -> 1043.924 | I51: =I23*8 -> 1177.7903
A52: 2031 | B52: =B24*1 -> 246.78477 | C52: =C24*2 -> 365.1176 | D52: =D24*3 -> 495.30954 | E52: =E24*4 -> 625.50148 | F52: =F24*5 -> 755.69343 | G52: =G24*6 -> 885.88537 | H52: =H24*7 -> 1016.0773 | I52: =I24*8 -> 1146.2693
A53: 2032 | B53: =B25*1 -> 240.78477 | C53: =C25*2 -> 355.88961 | D53: =D25*3 -> 482.50966 | E53: =E25*4 -> 609.12971 | F53: =F25*5 -> 735.74976 | G53: =G25*6 -> 862.36982 | H53: =H25*7 -> 988.98987 | I53: =I25*8 -> 1115.6099
A54: 2033 | B54: =B26*1 -> 234.93574 | C54: =C26*2 -> 346.90217 | D54: =D26*3 -> 470.04986 | E54: =E26*4 -> 593.19755 | F54: =F26*5 -> 716.34524 | G54: =G26*6 -> 839.49293 | H54: =H26*7 -> 962.64062 | I54: =I26*8 -> 1085.7883
A55: 2034 | B55: =B27*1 -> 229.23377 | C55: =C27*2 -> 338.14882 | D55: =D27*3 -> 457.92088 | E55: =E27*4 -> 577.69294 | F55: =F27*5 -> 697.46499 | G55: =G27*6 -> 817.23705 | H55: =H27*7 -> 937.0091 | I55: =I27*8 -> 1056.7812
A56: 2035 | B56: =B28*1 -> 223.67505 | C56: =C28*2 -> 329.62332 | D56: =D28*3 -> 446.11374 | E56: =E28*4 -> 562.60416 | F56: =F28*5 -> 679.09458 | G56: =G28*6 -> 795.58501 | H56: =H28*7 -> 912.07543 | I56: =I28*8 -> 1028.5658
A57: 2036 | B57: =B29*1 -> 220.60828 | C57: =C29*2 -> 324.61871 | D57: =D29*3 -> 438.9499 | E57: =E29*4 -> 553.2811 | F57: =F29*5 -> 667.61229 | G57: =G29*6 -> 781.94348 | H57: =H29*7 -> 896.27468 | I57: =I29*8 -> 1010.6059
A58: 2037 | B58: =B30*1 -> 217.59433 | C58: =C30*2 -> 319.70557 | D58: =D30*3 -> 431.92085 | E58: =E30*4 -> 544.13612 | F58: =F30*5 -> 656.35139 | G58: =G30*6 -> 768.56667 | H58: =H30*7 -> 880.78194 | I58: =I30*8 -> 992.99721
... A71: 2050 | B71: =B43*1 -> 182.78024 | C71: =C43*2 -> 263.37874 | D71: =D43*3 -> 351.64502 | E71: =E43*4 -> 439.9113 | F71: =F43*5 -> 528.17758 | G71: =G43*6 -> 616.44386 | H71: =H43*7 -> 704.71014 | I71: =I43*8 -> 792.97642
A73: Por debajo de 2 h el C-rate supera el límite del bloque AC estándar y entra la prima de suministro, que es el parámetro más incierto del modelo. Por encima de 4 h la curva se aplana: como el suministro se cobra por energía y el PCS viene embebido, lo único que se reparte sobre más energía es la conexión, la transformación y los fijos.

Sheet Curva_PV
A1: Curva solar por escala
A2: USD por kWp DC, constantes de 2026, full costo con margen, alcance Full EPC con 5 km de línea MT
A4: Escenario | C4: Medio
A5: Columna de escenario | C5: =MATCH($C$4,{"Bajo","Medio","Alto"},0) -> 2
A6: Escala de corte para la trayectoria comercial (MWp) | C6: 10
A8: CAPEX en USD por kWp DC
A9: Año | B9: 1 MWp | C9: 5 MWp | D9: 10 MWp | E9: 20 MWp | F9: 50 MWp | G9: 100 MWp | H9: 200 MWp
A10: 2026 | B10: =(Parametros_PV!$C$16*(1/8)^Parametros_PV!$C$33*IF(1<$C$6,INDEX(Trayectorias!$H$15:$J$39,MATCH($A10,Trayectorias!$A$15:$A$39,0),$C$5),INDEX(Trayectorias!$E$15:$G$39,MATCH($A10,Trayectorias!$A$15:$A$39,0),$C$5))+Parametros_PV!$C$17*(1/8)^Parametros_PV!$C$34*INDEX(Trayectorias!$K$15:$M$39,MATCH($A10,Trayectorias!$A$15:$A$39,0),$C$5)+Parametros_PV!$C$18*INDEX(Trayectorias!$K$15:$M$39,MATCH($A10,Trayectorias!$A$15:$A$39,0),$C$5))*Parametros_PV!$C$20 -> 945.62481 | C10: =(Parametros_PV!$C$16*(5/8)^Parametros_PV!$C$33*IF(5<$C$6,INDEX(Trayectorias!$H$15:$J$39,MATCH($A10,Trayectorias!$A$15:$A$39,0),$C$5),INDEX(Trayectorias!$E$15:$G$39,MATCH($A10,Trayectorias!$A$15:$A$39,0),$C$5))+Parametros_PV!$C$17*(5/8)^Parametros_PV!$C$34*INDEX(Trayectorias!$K$15:$M$39,MATCH($A10,Trayectorias!$A$15:$A$39,0),$C$5)+Parametros_PV!$C$18*INDEX(Trayectorias!$K$15:$M$39,MATCH($A10,Trayectorias!$A$15:$A$39,0),$C$5))*Parametros_PV!$C$20 -> 841.05064 | D10: =(Parametros_PV!$C$16*(10/8)^Parametros_PV!$C$33*IF(10<$C$6,INDEX(Trayectorias!$H$15:$J$39,MATCH($A10,Trayectorias!$A$15:$A$39,0),$C$5),INDEX(Trayectorias!$E$15:$G$39,MATCH($A10,Trayectorias!$A$15:$A$39,0),$C$5))+Parametros_PV!$C$17*(10/8)^Parametros_PV!$C$34*INDEX(Trayectorias!$K$15:$M$39,MATCH($A10,Trayectorias!$A$15:$A$39,0),$C$5)+Parametros_PV!$C$18*INDEX(Trayectorias!$K$15:$M$39,MATCH($A10,Trayectorias!$A$15:$A$39,0),$C$5))*Parametros_PV!$C$20 -> 800.04902 | E10: =(Parametros_PV!$C$16*(20/8)^Parametros_PV!$C$33*IF(20<$C$6,INDEX(Trayectorias!$H$15:$J$39,MATCH($A10,Trayectorias!$A$15:$A$39,0),$C$5),INDEX(Trayectorias!$E$15:$G$39,MATCH($A10,Trayectorias!$A$15:$A$39,0),$C$5))+Parametros_PV!$C$17*(20/8)^Parametros_PV!$C$34*INDEX(Trayectorias!$K$15:$M$39,MATCH($A10,Trayectorias!$A$15:$A$39,0),$C$5)+Parametros_PV!$C$18*INDEX(Trayectorias!$K$15:$M$39,MATCH($A10,Trayectorias!$A$15:$A$39,0),$C$5))*Parametros_PV!$C$20 -> 761.28183 | F10: =(Parametros_PV!$C$16*(50/8)^Parametros_PV!$C$33*IF(50<$C$6,INDEX(Trayectorias!$H$15:$J$39,MATCH($A10,Trayectorias!$A$15:$A$39,0),$C$5),INDEX(Trayectorias!$E$15:$G$39,MATCH($A10,Trayectorias!$A$15:$A$39,0),$C$5))+Parametros_PV!$C$17*(50/8)^Parametros_PV!$C$34*INDEX(Trayectorias!$K$15:$M$39,MATCH($A10,Trayectorias!$A$15:$A$39,0),$C$5)+Parametros_PV!$C$18*INDEX(Trayectorias!$K$15:$M$39,MATCH($A10,Trayectorias!$A$15:$A$39,0),$C$5))*Parametros_PV!$C$20 -> 713.25153 | G10: =(Parametros_PV!$C$16*(100/8)^Parametros_PV!$C$33*IF(100<$C$6,INDEX(Trayectorias!$H$15:$J$39,MATCH($A10,Trayectorias!$A$15:$A$39,0),$C$5),INDEX(Trayectorias!$E$15:$G$39,MATCH($A10,Trayectorias!$A$15:$A$39,0),$C$5))+Parametros_PV!$C$17*(100/8)^Parametros_PV!$C$34*INDEX(Trayectorias!$K$15:$M$39,MATCH($A10,Trayectorias!$A$15:$A$39,0),$C$5)+Parametros_PV!$C$18*INDEX(Trayectorias!$K$15:$M$39,MATCH($A10,Trayectorias!$A$15:$A$39,0),$C$5))*Parametros_PV!$C$20 -> 679.20121 | H10: =(Parametros_PV!$C$16*(200/8)^Parametros_PV!$C$33*IF(200<$C$6,INDEX(Trayectorias!$H$15:$J$39,MATCH($A10,Trayectorias!$A$15:$A$39,0),$C$5),INDEX(Trayectorias!$E$15:$G$39,MATCH($A10,Trayectorias!$A$15:$A$39,0),$C$5))+Parametros_PV!$C$17*(200/8)^Parametros_PV!$C$34*INDEX(Trayectorias!$K$15:$M$39,MATCH($A10,Trayectorias!$A$15:$A$39,0),$C$5)+Parametros_PV!$C$18*INDEX(Trayectorias!$K$15:$M$39,MATCH($A10,Trayectorias!$A$15:$A$39,0),$C$5))*Parametros_PV!$C$20 -> 646.99592
A11: 2027 | B11: =(Parametros_PV!$C$16*(1/8)^Parametros_PV!$C$33*IF(1<$C$6,INDEX(Trayectorias!$H$15:$J$39,MATCH($A11,Trayectorias!$A$15:$A$39,0),$C$5),INDEX(Trayectorias!$E$15:$G$39,MATCH($A11,Trayectorias!$A$15:$A$39,0),$C$5))+Parametros_PV!$C$17*(1/8)^Parametros_PV!$C$34*INDEX(Trayectorias!$K$15:$M$39,MATCH($A11,Trayectorias!$A$15:$A$39,0),$C$5)+Parametros_PV!$C$18*INDEX(Trayectorias!$K$15:$M$39,MATCH($A11,Trayectorias!$A$15:$A$39,0),$C$5))*Parametros_PV!$C$20 -> 909.12146 | C11: =(Parametros_PV!$C$16*(5/8)^Parametros_PV!$C$33*IF(5<$C$6,INDEX(Trayectorias!$H$15:$J$39,MATCH($A11,Trayectorias!$A$15:$A$39,0),$C$5),INDEX(Trayectorias!$E$15:$G$39,MATCH($A11,Trayectorias!$A$15:$A$39,0),$C$5))+Parametros_PV!$C$17*(5/8)^Parametros_PV!$C$34*INDEX(Trayectorias!$K$15:$M$39,MATCH($A11,Trayectorias!$A$15:$A$39,0),$C$5)+Parametros_PV!$C$18*INDEX(Trayectorias!$K$15:$M$39,MATCH($A11,Trayectorias!$A$15:$A$39,0),$C$5))*Parametros_PV!$C$20 -> 809.02792 | D11: =(Parametros_PV!$C$16*(10/8)^Parametros_PV!$C$33*IF(10<$C$6,INDEX(Trayectorias!$H$15:$J$39,MATCH($A11,Trayectorias!$A$15:$A$39,0),$C$5),INDEX(Trayectorias!$E$15:$G$39,MATCH($A11,Trayectorias!$A$15:$A$39,0),$C$5))+Parametros_PV!$C$17*(10/8)^Parametros_PV!$C$34*INDEX(Trayectorias!$K$15:$M$39,MATCH($A11,Trayectorias!$A$15:$A$39,0),$C$5)+Parametros_PV!$C$18*INDEX(Trayectorias!$K$15:$M$39,MATCH($A11,Trayectorias!$A$15:$A$39,0),$C$5))*Parametros_PV!$C$20 -> 758.66018 | E11: =(Parametros_PV!$C$16*(20/8)^Parametros_PV!$C$33*IF(20<$C$6,INDEX(Trayectorias!$H$15:$J$39,MATCH($A11,Trayectorias!$A$15:$A$39,0),$C$5),INDEX(Trayectorias!$E$15:$G$39,MATCH($A11,Trayectorias!$A$15:$A$39,0),$C$5))+Parametros_PV!$C$17*(20/8)^Parametros_PV!$C$34*INDEX(Trayectorias!$K$15:$M$39,MATCH($A11,Trayectorias!$A$15:$A$39,0),$C$5)+Parametros_PV!$C$18*INDEX(Trayectorias!$K$15:$M$39,MATCH($A11,Trayectorias!$A$15:$A$39,0),$C$5))*Parametros_PV!$C$20 -> 722.21463 | F11: =(Parametros_PV!$C$16*(50/8)^Parametros_PV!$C$33*IF(50<$C$6,INDEX(Trayectorias!$H$15:$J$39,MATCH($A11,Trayectorias!$A$15:$A$39,0),$C$5),INDEX(Trayectorias!$E$15:$G$39,MATCH($A11,Trayectorias!$A$15:$A$39,0),$C$5))+Parametros_PV!$C$17*(50/8)^Parametros_PV!$C$34*INDEX(Trayectorias!$K$15:$M$39,MATCH($A11,Trayectorias!$A$15:$A$39,0),$C$5)+Parametros_PV!$C$18*INDEX(Trayectorias!$K$15:$M$39,MATCH($A11,Trayectorias!$A$15:$A$39,0),$C$5))*Parametros_PV!$C$20 -> 677.04551 | G11: =(Parametros_PV!$C$16*(100/8)^Parametros_PV!$C$33*IF(100<$C$6,INDEX(Trayectorias!$H$15:$J$39,MATCH($A11,Trayectorias!$A$15:$A$39,0),$C$5),INDEX(Trayectorias!$E$15:$G$39,MATCH($A11,Trayectorias!$A$15:$A$39,0),$C$5))+Parametros_PV!$C$17*(100/8)^Parametros_PV!$C$34*INDEX(Trayectorias!$K$15:$M$39,MATCH($A11,Trayectorias!$A$15:$A$39,0),$C$5)+Parametros_PV!$C$18*INDEX(Trayectorias!$K$15:$M$39,MATCH($A11,Trayectorias!$A$15:$A$39,0),$C$5))*Parametros_PV!$C$20 -> 645.01263 | H11: =(Parametros_PV!$C$16*(200/8)^Parametros_PV!$C$33*IF(200<$C$6,INDEX(Trayectorias!$H$15:$J$39,MATCH($A11,Trayectorias!$A$15:$A$39,0),$C$5),INDEX(Trayectorias!$E$15:$G$39,MATCH($A11,Trayectorias!$A$15:$A$39,0),$C$5))+Parametros_PV!$C$17*(200/8)^Parametros_PV!$C$34*INDEX(Trayectorias!$K$15:$M$39,MATCH($A11,Trayectorias!$A$15:$A$39,0),$C$5)+Parametros_PV!$C$18*INDEX(Trayectorias!$K$15:$M$39,MATCH($A11,Trayectorias!$A$15:$A$39,0),$C$5))*Parametros_PV!$C$20 -> 614.70652
A12: 2028 | B12: =(Parametros_PV!$C$16*(1/8)^Parametros_PV!$C$33*IF(1<$C$6,INDEX(Trayectorias!$H$15:$J$39,MATCH($A12,Trayectorias!$A$15:$A$39,0),$C$5),INDEX(Trayectorias!$E$15:$G$39,MATCH($A12,Trayectorias!$A$15:$A$39,0),$C$5))+Parametros_PV!$C$17*(1/8)^Parametros_PV!$C$34*INDEX(Trayectorias!$K$15:$M$39,MATCH($A12,Trayectorias!$A$15:$A$39,0),$C$5)+Parametros_PV!$C$18*INDEX(Trayectorias!$K$15:$M$39,MATCH($A12,Trayectorias!$A$15:$A$39,0),$C$5))*Parametros_PV!$C$20 -> 874.28362 | C12: =(Parametros_PV!$C$16*(5/8)^Parametros_PV!$C$33*IF(5<$C$6,INDEX(Trayectorias!$H$15:$J$39,MATCH($A12,Trayectorias!$A$15:$A$39,0),$C$5),INDEX(Trayectorias!$E$15:$G$39,MATCH($A12,Trayectorias!$A$15:$A$39,0),$C$5))+Parametros_PV!$C$17*(5/8)^Parametros_PV!$C$34*INDEX(Trayectorias!$K$15:$M$39,MATCH($A12,Trayectorias!$A$15:$A$39,0),$C$5)+Parametros_PV!$C$18*INDEX(Trayectorias!$K$15:$M$39,MATCH($A12,Trayectorias!$A$15:$A$39,0),$C$5))*Parametros_PV!$C$20 -> 778.45413 | D12: =(Parametros_PV!$C$16*(10/8)^Parametros_PV!$C$33*IF(10<$C$6,INDEX(Trayectorias!$H$15:$J$39,MATCH($A12,Trayectorias!$A$15:$A$39,0),$C$5),INDEX(Trayectorias!$E$15:$G$39,MATCH($A12,Trayectorias!$A$15:$A$39,0),$C$5))+Parametros_PV!$C$17*(10/8)^Parametros_PV!$C$34*INDEX(Trayectorias!$K$15:$M$39,MATCH($A12,Trayectorias!$A$15:$A$39,0),$C$5)+Parametros_PV!$C$18*INDEX(Trayectorias!$K$15:$M$39,MATCH($A12,Trayectorias!$A$15:$A$39,0),$C$5))*Parametros_PV!$C$20 -> 720.10185 | E12: =(Parametros_PV!$C$16*(20/8)^Parametros_PV!$C$33*IF(20<$C$6,INDEX(Trayectorias!$H$15:$J$39,MATCH($A12,Trayectorias!$A$15:$A$39,0),$C$5),INDEX(Trayectorias!$E$15:$G$39,MATCH($A12,Trayectorias!$A$15:$A$39,0),$C$5))+Parametros_PV!$C$17*(20/8)^Parametros_PV!$C$34*INDEX(Trayectorias!$K$15:$M$39,MATCH($A12,Trayectorias!$A$15:$A$39,0),$C$5)+Parametros_PV!$C$18*INDEX(Trayectorias!$K$15:$M$39,MATCH($A12,Trayectorias!$A$15:$A$39,0),$C$5))*Parametros_PV!$C$20 -> 685.80958 | F12: =(Parametros_PV!$C$16*(50/8)^Parametros_PV!$C$33*IF(50<$C$6,INDEX(Trayectorias!$H$15:$J$39,MATCH($A12,Trayectorias!$A$15:$A$39,0),$C$5),INDEX(Trayectorias!$E$15:$G$39,MATCH($A12,Trayectorias!$A$15:$A$39,0),$C$5))+Parametros_PV!$C$17*(50/8)^Parametros_PV!$C$34*INDEX(Trayectorias!$K$15:$M$39,MATCH($A12,Trayectorias!$A$15:$A$39,0),$C$5)+Parametros_PV!$C$18*INDEX(Trayectorias!$K$15:$M$39,MATCH($A12,Trayectorias!$A$15:$A$39,0),$C$5))*Parametros_PV!$C$20 -> 643.29455 | G12: =(Parametros_PV!$C$16*(100/8)^Parametros_PV!$C$33*IF(100<$C$6,INDEX(Trayectorias!$H$15:$J$39,MATCH($A12,Trayectorias!$A$15:$A$39,0),$C$5),INDEX(Trayectorias!$E$15:$G$39,MATCH($A12,Trayectorias!$A$15:$A$39,0),$C$5))+Parametros_PV!$C$17*(100/8)^Parametros_PV!$C$34*INDEX(Trayectorias!$K$15:$M$39,MATCH($A12,Trayectorias!$A$15:$A$39,0),$C$5)+Parametros_PV!$C$18*INDEX(Trayectorias!$K$15:$M$39,MATCH($A12,Trayectorias!$A$15:$A$39,0),$C$5))*Parametros_PV!$C$20 -> 613.1334 | H12: =(Parametros_PV!$C$16*(200/8)^Parametros_PV!$C$33*IF(200<$C$6,INDEX(Trayectorias!$H$15:$J$39,MATCH($A12,Trayectorias!$A$15:$A$39,0),$C$5),INDEX(Trayectorias!$E$15:$G$39,MATCH($A12,Trayectorias!$A$15:$A$39,0),$C$5))+Parametros_PV!$C$17*(200/8)^Parametros_PV!$C$34*INDEX(Trayectorias!$K$15:$M$39,MATCH($A12,Trayectorias!$A$15:$A$39,0),$C$5)+Parametros_PV!$C$18*INDEX(Trayectorias!$K$15:$M$39,MATCH($A12,Trayectorias!$A$15:$A$39,0),$C$5))*Parametros_PV!$C$20 -> 584.58951
A13: 2029 | B13: =(Parametros_PV!$C$16*(1/8)^Parametros_PV!$C$33*IF(1<$C$6,INDEX(Trayectorias!$H$15:$J$39,MATCH($A13,Trayectorias!$A$15:$A$39,0),$C$5),INDEX(Trayectorias!$E$15:$G$39,MATCH($A13,Trayectorias!$A$15:$A$39,0),$C$5))+Parametros_PV!$C$17*(1/8)^Parametros_PV!$C$34*INDEX(Trayectorias!$K$15:$M$39,MATCH($A13,Trayectorias!$A$15:$A$39,0),$C$5)+Parametros_PV!$C$18*INDEX(Trayectorias!$K$15:$M$39,MATCH($A13,Trayectorias!$A$15:$A$39,0),$C$5))*Parametros_PV!$C$20 -> 841.02828 | C13: =(Parametros_PV!$C$16*(5/8)^Parametros_PV!$C$33*IF(5<$C$6,INDEX(Trayectorias!$H$15:$J$39,MATCH($A13,Trayectorias!$A$15:$A$39,0),$C$5),INDEX(Trayectorias!$E$15:$G$39,MATCH($A13,Trayectorias!$A$15:$A$39,0),$C$5))+Parametros_PV!$C$17*(5/8)^Parametros_PV!$C$34*INDEX(Trayectorias!$K$15:$M$39,MATCH($A13,Trayectorias!$A$15:$A$39,0),$C$5)+Parametros_PV!$C$18*INDEX(Trayectorias!$K$15:$M$39,MATCH($A13,Trayectorias!$A$15:$A$39,0),$C$5))*Parametros_PV!$C$20 -> 749.25733 | D13: =(Parametros_PV!$C$16*(10/8)^Parametros_PV!$C$33*IF(10<$C$6,INDEX(Trayectorias!$H$15:$J$39,MATCH($A13,Trayectorias!$A$15:$A$39,0),$C$5),INDEX(Trayectorias!$E$15:$G$39,MATCH($A13,Trayectorias!$A$15:$A$39,0),$C$5))+Parametros_PV!$C$17*(10/8)^Parametros_PV!$C$34*INDEX(Trayectorias!$K$15:$M$39,MATCH($A13,Trayectorias!$A$15:$A$39,0),$C$5)+Parametros_PV!$C$18*INDEX(Trayectorias!$K$15:$M$39,MATCH($A13,Trayectorias!$A$15:$A$39,0),$C$5))*Parametros_PV!$C$20 -> 684.15955 | E13: =(Parametros_PV!$C$16*(20/8)^Parametros_PV!$C$33*IF(20<$C$6,INDEX(Trayectorias!$H$15:$J$39,MATCH($A13,Trayectorias!$A$15:$A$39,0),$C$5),INDEX(Trayectorias!$E$15:$G$39,MATCH($A13,Trayectorias!$A$15:$A$39,0),$C$5))+Parametros_PV!$C$17*(20/8)^Parametros_PV!$C$34*INDEX(Trayectorias!$K$15:$M$39,MATCH($A13,Trayectorias!$A$15:$A$39,0),$C$5)+Parametros_PV!$C$18*INDEX(Trayectorias!$K$15:$M$39,MATCH($A13,Trayectorias!$A$15:$A$39,0),$C$5))*Parametros_PV!$C$20 -> 651.8652 | F13: =(Parametros_PV!$C$16*(50/8)^Parametros_PV!$C$33*IF(50<$C$6,INDEX(Trayectorias!$H$15:$J$39,MATCH($A13,Trayectorias!$A$15:$A$39,0),$C$5),INDEX(Trayectorias!$E$15:$G$39,MATCH($A13,Trayectorias!$A$15:$A$39,0),$C$5))+Parametros_PV!$C$17*(50/8)^Parametros_PV!$C$34*INDEX(Trayectorias!$K$15:$M$39,MATCH($A13,Trayectorias!$A$15:$A$39,0),$C$5)+Parametros_PV!$C$18*INDEX(Trayectorias!$K$15:$M$39,MATCH($A13,Trayectorias!$A$15:$A$39,0),$C$5))*Parametros_PV!$C$20 -> 611.81313 | G13: =(Parametros_PV!$C$16*(100/8)^Parametros_PV!$C$33*IF(100<$C$6,INDEX(Trayectorias!$H$15:$J$39,MATCH($A13,Trayectorias!$A$15:$A$39,0),$C$5),INDEX(Trayectorias!$E$15:$G$39,MATCH($A13,Trayectorias!$A$15:$A$39,0),$C$5))+Parametros_PV!$C$17*(100/8)^Parametros_PV!$C$34*INDEX(Trayectorias!$K$15:$M$39,MATCH($A13,Trayectorias!$A$15:$A$39,0),$C$5)+Parametros_PV!$C$18*INDEX(Trayectorias!$K$15:$M$39,MATCH($A13,Trayectorias!$A$15:$A$39,0),$C$5))*Parametros_PV!$C$20 -> 583.38918 | H13: =(Parametros_PV!$C$16*(200/8)^Parametros_PV!$C$33*IF(200<$C$6,INDEX(Trayectorias!$H$15:$J$39,MATCH($A13,Trayectorias!$A$15:$A$39,0),$C$5),INDEX(Trayectorias!$E$15:$G$39,MATCH($A13,Trayectorias!$A$15:$A$39,0),$C$5))+Parametros_PV!$C$17*(200/8)^Parametros_PV!$C$34*INDEX(Trayectorias!$K$15:$M$39,MATCH($A13,Trayectorias!$A$15:$A$39,0),$C$5)+Parametros_PV!$C$18*INDEX(Trayectorias!$K$15:$M$39,MATCH($A13,Trayectorias!$A$15:$A$39,0),$C$5))*Parametros_PV!$C$20 -> 556.48112
A14: 2030 | B14: =(Parametros_PV!$C$16*(1/8)^Parametros_PV!$C$33*IF(1<$C$6,INDEX(Trayectorias!$H$15:$J$39,MATCH($A14,Trayectorias!$A$15:$A$39,0),$C$5),INDEX(Trayectorias!$E$15:$G$39,MATCH($A14,Trayectorias!$A$15:$A$39,0),$C$5))+Parametros_PV!$C$17*(1/8)^Parametros_PV!$C$34*INDEX(Trayectorias!$K$15:$M$39,MATCH($A14,Trayectorias!$A$15:$A$39,0),$C$5)+Parametros_PV!$C$18*INDEX(Trayectorias!$K$15:$M$39,MATCH($A14,Trayectorias!$A$15:$A$39,0),$C$5))*Parametros_PV!$C$20 -> 809.27674 | C14: =(Parametros_PV!$C$16*(5/8)^Parametros_PV!$C$33*IF(5<$C$6,INDEX(Trayectorias!$H$15:$J$39,MATCH($A14,Trayectorias!$A$15:$A$39,0),$C$5),INDEX(Trayectorias!$E$15:$G$39,MATCH($A14,Trayectorias!$A$15:$A$39,0),$C$5))+Parametros_PV!$C$17*(5/8)^Parametros_PV!$C$34*INDEX(Trayectorias!$K$15:$M$39,MATCH($A14,Trayectorias!$A$15:$A$39,0),$C$5)+Parametros_PV!$C$18*INDEX(Trayectorias!$K$15:$M$39,MATCH($A14,Trayectorias!$A$15:$A$39,0),$C$5))*Parametros_PV!$C$20 -> 721.36931 | D14: =(Parametros_PV!$C$16*(10/8)^Parametros_PV!$C$33*IF(10<$C$6,INDEX(Trayectorias!$H$15:$J$39,MATCH($A14,Trayectorias!$A$15:$A$39,0),$C$5),INDEX(Trayectorias!$E$15:$G$39,MATCH($A14,Trayectorias!$A$15:$A$39,0),$C$5))+Parametros_PV!$C$17*(10/8)^Parametros_PV!$C$34*INDEX(Trayectorias!$K$15:$M$39,MATCH($A14,Trayectorias!$A$15:$A$39,0),$C$5)+Parametros_PV!$C$18*INDEX(Trayectorias!$K$15:$M$39,MATCH($A14,Trayectorias!$A$15:$A$39,0),$C$5))*Parametros_PV!$C$20 -> 650.63555 | E14: =(Parametros_PV!$C$16*(20/8)^Parametros_PV!$C$33*IF(20<$C$6,INDEX(Trayectorias!$H$15:$J$39,MATCH($A14,Trayectorias!$A$15:$A$39,0),$C$5),INDEX(Trayectorias!$E$15:$G$39,MATCH($A14,Trayectorias!$A$15:$A$39,0),$C$5))+Parametros_PV!$C$17*(20/8)^Parametros_PV!$C$34*INDEX(Trayectorias!$K$15:$M$39,MATCH($A14,Trayectorias!$A$15:$A$39,0),$C$5)+Parametros_PV!$C$18*INDEX(Trayectorias!$K$15:$M$39,MATCH($A14,Trayectorias!$A$15:$A$39,0),$C$5))*Parametros_PV!$C$20 -> 620.19569 | F14: =(Parametros_PV!$C$16*(50/8)^Parametros_PV!$C$33*IF(50<$C$6,INDEX(Trayectorias!$H$15:$J$39,MATCH($A14,Trayectorias!$A$15:$A$39,0),$C$5),INDEX(Trayectorias!$E$15:$G$39,MATCH($A14,Trayectorias!$A$15:$A$39,0),$C$5))+Parametros_PV!$C$17*(50/8)^Parametros_PV!$C$34*INDEX(Trayectorias!$K$15:$M$39,MATCH($A14,Trayectorias!$A$15:$A$39,0),$C$5)+Parametros_PV!$C$18*INDEX(Trayectorias!$K$15:$M$39,MATCH($A14,Trayectorias!$A$15:$A$39,0),$C$5))*Parametros_PV!$C$20 -> 582.43016 | G14: =(Parametros_PV!$C$16*(100/8)^Parametros_PV!$C$33*IF(100<$C$6,INDEX(Trayectorias!$H$15:$J$39,MATCH($A14,Trayectorias!$A$15:$A$39,0),$C$5),INDEX(Trayectorias!$E$15:$G$39,MATCH($A14,Trayectorias!$A$15:$A$39,0),$C$5))+Parametros_PV!$C$17*(100/8)^Parametros_PV!$C$34*INDEX(Trayectorias!$K$15:$M$39,MATCH($A14,Trayectorias!$A$15:$A$39,0),$C$5)+Parametros_PV!$C$18*INDEX(Trayectorias!$K$15:$M$39,MATCH($A14,Trayectorias!$A$15:$A$39,0),$C$5))*Parametros_PV!$C$20 -> 555.61926 | H14: =(Parametros_PV!$C$16*(200/8)^Parametros_PV!$C$33*IF(200<$C$6,INDEX(Trayectorias!$H$15:$J$39,MATCH($A14,Trayectorias!$A$15:$A$39,0),$C$5),INDEX(Trayectorias!$E$15:$G$39,MATCH($A14,Trayectorias!$A$15:$A$39,0),$C$5))+Parametros_PV!$C$17*(200/8)^Parametros_PV!$C$34*INDEX(Trayectorias!$K$15:$M$39,MATCH($A14,Trayectorias!$A$15:$A$39,0),$C$5)+Parametros_PV!$C$18*INDEX(Trayectorias!$K$15:$M$39,MATCH($A14,Trayectorias!$A$15:$A$39,0),$C$5))*Parametros_PV!$C$20 -> 530.23032
A15: 2031 | B15: =(Parametros_PV!$C$16*(1/8)^Parametros_PV!$C$33*IF(1<$C$6,INDEX(Trayectorias!$H$15:$J$39,MATCH($A15,Trayectorias!$A$15:$A$39,0),$C$5),INDEX(Trayectorias!$E$15:$G$39,MATCH($A15,Trayectorias!$A$15:$A$39,0),$C$5))+Parametros_PV!$C$17*(1/8)^Parametros_PV!$C$34*INDEX(Trayectorias!$K$15:$M$39,MATCH($A15,Trayectorias!$A$15:$A$39,0),$C$5)+Parametros_PV!$C$18*INDEX(Trayectorias!$K$15:$M$39,MATCH($A15,Trayectorias!$A$15:$A$39,0),$C$5))*Parametros_PV!$C$20 -> 778.95435 | C15: =(Parametros_PV!$C$16*(5/8)^Parametros_PV!$C$33*IF(5<$C$6,INDEX(Trayectorias!$H$15:$J$39,MATCH($A15,Trayectorias!$A$15:$A$39,0),$C$5),INDEX(Trayectorias!$E$15:$G$39,MATCH($A15,Trayectorias!$A$15:$A$39,0),$C$5))+Parametros_PV!$C$17*(5/8)^Parametros_PV!$C$34*INDEX(Trayectorias!$K$15:$M$39,MATCH($A15,Trayectorias!$A$15:$A$39,0),$C$5)+Parametros_PV!$C$18*INDEX(Trayectorias!$K$15:$M$39,MATCH($A15,Trayectorias!$A$15:$A$39,0),$C$5))*Parametros_PV!$C$20 -> 694.72538 | D15: =(Parametros_PV!$C$16*(10/8)^Parametros_PV!$C$33*IF(10<$C$6,INDEX(Trayectorias!$H$15:$J$39,MATCH($A15,Trayectorias!$A$15:$A$39,0),$C$5),INDEX(Trayectorias!$E$15:$G$39,MATCH($A15,Trayectorias!$A$15:$A$39,0),$C$5))+Parametros_PV!$C$17*(10/8)^Parametros_PV!$C$34*INDEX(Trayectorias!$K$15:$M$39,MATCH($A15,Trayectorias!$A$15:$A$39,0),$C$5)+Parametros_PV!$C$18*INDEX(Trayectorias!$K$15:$M$39,MATCH($A15,Trayectorias!$A$15:$A$39,0),$C$5))*Parametros_PV!$C$20 -> 619.34753 | E15: =(Parametros_PV!$C$16*(20/8)^Parametros_PV!$C$33*IF(20<$C$6,INDEX(Trayectorias!$H$15:$J$39,MATCH($A15,Trayectorias!$A$15:$A$39,0),$C$5),INDEX(Trayectorias!$E$15:$G$39,MATCH($A15,Trayectorias!$A$15:$A$39,0),$C$5))+Parametros_PV!$C$17*(20/8)^Parametros_PV!$C$34*INDEX(Trayectorias!$K$15:$M$39,MATCH($A15,Trayectorias!$A$15:$A$39,0),$C$5)+Parametros_PV!$C$18*INDEX(Trayectorias!$K$15:$M$39,MATCH($A15,Trayectorias!$A$15:$A$39,0),$C$5))*Parametros_PV!$C$20 -> 590.62976 | F15: =(Parametros_PV!$C$16*(50/8)^Parametros_PV!$C$33*IF(50<$C$6,INDEX(Trayectorias!$H$15:$J$39,MATCH($A15,Trayectorias!$A$15:$A$39,0),$C$5),INDEX(Trayectorias!$E$15:$G$39,MATCH($A15,Trayectorias!$A$15:$A$39,0),$C$5))+Parametros_PV!$C$17*(50/8)^Parametros_PV!$C$34*INDEX(Trayectorias!$K$15:$M$39,MATCH($A15,Trayectorias!$A$15:$A$39,0),$C$5)+Parametros_PV!$C$18*INDEX(Trayectorias!$K$15:$M$39,MATCH($A15,Trayectorias!$A$15:$A$39,0),$C$5))*Parametros_PV!$C$20 -> 554.98789 | G15: =(Parametros_PV!$C$16*(100/8)^Parametros_PV!$C$33*IF(100<$C$6,INDEX(Trayectorias!$H$15:$J$39,MATCH($A15,Trayectorias!$A$15:$A$39,0),$C$5),INDEX(Trayectorias!$E$15:$G$39,MATCH($A15,Trayectorias!$A$15:$A$39,0),$C$5))+Parametros_PV!$C$17*(100/8)^Parametros_PV!$C$34*INDEX(Trayectorias!$K$15:$M$39,MATCH($A15,Trayectorias!$A$15:$A$39,0),$C$5)+Parametros_PV!$C$18*INDEX(Trayectorias!$K$15:$M$39,MATCH($A15,Trayectorias!$A$15:$A$39,0),$C$5))*Parametros_PV!$C$20 -> 529.6754 | H15: =(Parametros_PV!$C$16*(200/8)^Parametros_PV!$C$33*IF(200<$C$6,INDEX(Trayectorias!$H$15:$J$39,MATCH($A15,Trayectorias!$A$15:$A$39,0),$C$5),INDEX(Trayectorias!$E$15:$G$39,MATCH($A15,Trayectorias!$A$15:$A$39,0),$C$5))+Parametros_PV!$C$17*(200/8)^Parametros_PV!$C$34*INDEX(Trayectorias!$K$15:$M$39,MATCH($A15,Trayectorias!$A$15:$A$39,0),$C$5)+Parametros_PV!$C$18*INDEX(Trayectorias!$K$15:$M$39,MATCH($A15,Trayectorias!$A$15:$A$39,0),$C$5))*Parametros_PV!$C$20 -> 505.69784
A16: 2032 | B16: =(Parametros_PV!$C$16*(1/8)^Parametros_PV!$C$33*IF(1<$C$6,INDEX(Trayectorias!$H$15:$J$39,MATCH($A16,Trayectorias!$A$15:$A$39,0),$C$5),INDEX(Trayectorias!$E$15:$G$39,MATCH($A16,Trayectorias!$A$15:$A$39,0),$C$5))+Parametros_PV!$C$17*(1/8)^Parametros_PV!$C$34*INDEX(Trayectorias!$K$15:$M$39,MATCH($A16,Trayectorias!$A$15:$A$39,0),$C$5)+Parametros_PV!$C$18*INDEX(Trayectorias!$K$15:$M$39,MATCH($A16,Trayectorias!$A$15:$A$39,0),$C$5))*Parametros_PV!$C$20 -> 749.99035 | C16: =(Parametros_PV!$C$16*(5/8)^Parametros_PV!$C$33*IF(5<$C$6,INDEX(Trayectorias!$H$15:$J$39,MATCH($A16,Trayectorias!$A$15:$A$39,0),$C$5),INDEX(Trayectorias!$E$15:$G$39,MATCH($A16,Trayectorias!$A$15:$A$39,0),$C$5))+Parametros_PV!$C$17*(5/8)^Parametros_PV!$C$34*INDEX(Trayectorias!$K$15:$M$39,MATCH($A16,Trayectorias!$A$15:$A$39,0),$C$5)+Parametros_PV!$C$18*INDEX(Trayectorias!$K$15:$M$39,MATCH($A16,Trayectorias!$A$15:$A$39,0),$C$5))*Parametros_PV!$C$20 -> 669.2642 | D16: =(Parametros_PV!$C$16*(10/8)^Parametros_PV!$C$33*IF(10<$C$6,INDEX(Trayectorias!$H$15:$J$39,MATCH($A16,Trayectorias!$A$15:$A$39,0),$C$5),INDEX(Trayectorias!$E$15:$G$39,MATCH($A16,Trayectorias!$A$15:$A$39,0),$C$5))+Parametros_PV!$C$17*(10/8)^Parametros_PV!$C$34*INDEX(Trayectorias!$K$15:$M$39,MATCH($A16,Trayectorias!$A$15:$A$39,0),$C$5)+Parametros_PV!$C$18*INDEX(Trayectorias!$K$15:$M$39,MATCH($A16,Trayectorias!$A$15:$A$39,0),$C$5))*Parametros_PV!$C$20 -> 590.12736 | E16: =(Parametros_PV!$C$16*(20/8)^Parametros_PV!$C$33*IF(20<$C$6,INDEX(Trayectorias!$H$15:$J$39,MATCH($A16,Trayectorias!$A$15:$A$39,0),$C$5),INDEX(Trayectorias!$E$15:$G$39,MATCH($A16,Trayectorias!$A$15:$A$39,0),$C$5))+Parametros_PV!$C$17*(20/8)^Parametros_PV!$C$34*INDEX(Trayectorias!$K$15:$M$39,MATCH($A16,Trayectorias!$A$15:$A$39,0),$C$5)+Parametros_PV!$C$18*INDEX(Trayectorias!$K$15:$M$39,MATCH($A16,Trayectorias!$A$15:$A$39,0),$C$5))*Parametros_PV!$C$20 -> 563.00945 | F16: =(Parametros_PV!$C$16*(50/8)^Parametros_PV!$C$33*IF(50<$C$6,INDEX(Trayectorias!$H$15:$J$39,MATCH($A16,Trayectorias!$A$15:$A$39,0),$C$5),INDEX(Trayectorias!$E$15:$G$39,MATCH($A16,Trayectorias!$A$15:$A$39,0),$C$5))+Parametros_PV!$C$17*(50/8)^Parametros_PV!$C$34*INDEX(Trayectorias!$K$15:$M$39,MATCH($A16,Trayectorias!$A$15:$A$39,0),$C$5)+Parametros_PV!$C$18*INDEX(Trayectorias!$K$15:$M$39,MATCH($A16,Trayectorias!$A$15:$A$39,0),$C$5))*Parametros_PV!$C$20 -> 529.34085 | G16: =(Parametros_PV!$C$16*(100/8)^Parametros_PV!$C$33*IF(100<$C$6,INDEX(Trayectorias!$H$15:$J$39,MATCH($A16,Trayectorias!$A$15:$A$39,0),$C$5),INDEX(Trayectorias!$E$15:$G$39,MATCH($A16,Trayectorias!$A$15:$A$39,0),$C$5))+Parametros_PV!$C$17*(100/8)^Parametros_PV!$C$34*INDEX(Trayectorias!$K$15:$M$39,MATCH($A16,Trayectorias!$A$15:$A$39,0),$C$5)+Parametros_PV!$C$18*INDEX(Trayectorias!$K$15:$M$39,MATCH($A16,Trayectorias!$A$15:$A$39,0),$C$5))*Parametros_PV!$C$20 -> 505.42092 | H16: =(Parametros_PV!$C$16*(200/8)^Parametros_PV!$C$33*IF(200<$C$6,INDEX(Trayectorias!$H$15:$J$39,MATCH($A16,Trayectorias!$A$15:$A$39,0),$C$5),INDEX(Trayectorias!$E$15:$G$39,MATCH($A16,Trayectorias!$A$15:$A$39,0),$C$5))+Parametros_PV!$C$17*(200/8)^Parametros_PV!$C$34*INDEX(Trayectorias!$K$15:$M$39,MATCH($A16,Trayectorias!$A$15:$A$39,0),$C$5)+Parametros_PV!$C$18*INDEX(Trayectorias!$K$15:$M$39,MATCH($A16,Trayectorias!$A$15:$A$39,0),$C$5))*Parametros_PV!$C$20 -> 482.75525
A17: 2033 | B17: =(Parametros_PV!$C$16*(1/8)^Parametros_PV!$C$33*IF(1<$C$6,INDEX(Trayectorias!$H$15:$J$39,MATCH($A17,Trayectorias!$A$15:$A$39,0),$C$5),INDEX(Trayectorias!$E$15:$G$39,MATCH($A17,Trayectorias!$A$15:$A$39,0),$C$5))+Parametros_PV!$C$17*(1/8)^Parametros_PV!$C$34*INDEX(Trayectorias!$K$15:$M$39,MATCH($A17,Trayectorias!$A$15:$A$39,0),$C$5)+Parametros_PV!$C$18*INDEX(Trayectorias!$K$15:$M$39,MATCH($A17,Trayectorias!$A$15:$A$39,0),$C$5))*Parametros_PV!$C$20 -> 722.3176 | C17: =(Parametros_PV!$C$16*(5/8)^Parametros_PV!$C$33*IF(5<$C$6,INDEX(Trayectorias!$H$15:$J$39,MATCH($A17,Trayectorias!$A$15:$A$39,0),$C$5),INDEX(Trayectorias!$E$15:$G$39,MATCH($A17,Trayectorias!$A$15:$A$39,0),$C$5))+Parametros_PV!$C$17*(5/8)^Parametros_PV!$C$34*INDEX(Trayectorias!$K$15:$M$39,MATCH($A17,Trayectorias!$A$15:$A$39,0),$C$5)+Parametros_PV!$C$18*INDEX(Trayectorias!$K$15:$M$39,MATCH($A17,Trayectorias!$A$15:$A$39,0),$C$5))*Parametros_PV!$C$20 -> 644.92758 | D17: =(Parametros_PV!$C$16*(10/8)^Parametros_PV!$C$33*IF(10<$C$6,INDEX(Trayectorias!$H$15:$J$39,MATCH($A17,Trayectorias!$A$15:$A$39,0),$C$5),INDEX(Trayectorias!$E$15:$G$39,MATCH($A17,Trayectorias!$A$15:$A$39,0),$C$5))+Parametros_PV!$C$17*(10/8)^Parametros_PV!$C$34*INDEX(Trayectorias!$K$15:$M$39,MATCH($A17,Trayectorias!$A$15:$A$39,0),$C$5)+Parametros_PV!$C$18*INDEX(Trayectorias!$K$15:$M$39,MATCH($A17,Trayectorias!$A$15:$A$39,0),$C$5))*Parametros_PV!$C$20 -> 562.82001 | E17: =(Parametros_PV!$C$16*(20/8)^Parametros_PV!$C$33*IF(20<$C$6,INDEX(Trayectorias!$H$15:$J$39,MATCH($A17,Trayectorias!$A$15:$A$39,0),$C$5),INDEX(Trayectorias!$E$15:$G$39,MATCH($A17,Trayectorias!$A$15:$A$39,0),$C$5))+Parametros_PV!$C$17*(20/8)^Parametros_PV!$C$34*INDEX(Trayectorias!$K$15:$M$39,MATCH($A17,Trayectorias!$A$15:$A$39,0),$C$5)+Parametros_PV!$C$18*INDEX(Trayectorias!$K$15:$M$39,MATCH($A17,Trayectorias!$A$15:$A$39,0),$C$5))*Parametros_PV!$C$20 -> 537.18908 | F17: =(Parametros_PV!$C$16*(50/8)^Parametros_PV!$C$33*IF(50<$C$6,INDEX(Trayectorias!$H$15:$J$39,MATCH($A17,Trayectorias!$A$15:$A$39,0),$C$5),INDEX(Trayectorias!$E$15:$G$39,MATCH($A17,Trayectorias!$A$15:$A$39,0),$C$5))+Parametros_PV!$C$17*(50/8)^Parametros_PV!$C$34*INDEX(Trayectorias!$K$15:$M$39,MATCH($A17,Trayectorias!$A$15:$A$39,0),$C$5)+Parametros_PV!$C$18*INDEX(Trayectorias!$K$15:$M$39,MATCH($A17,Trayectorias!$A$15:$A$39,0),$C$5))*Parametros_PV!$C$20 -> 505.35489 | G17: =(Parametros_PV!$C$16*(100/8)^Parametros_PV!$C$33*IF(100<$C$6,INDEX(Trayectorias!$H$15:$J$39,MATCH($A17,Trayectorias!$A$15:$A$39,0),$C$5),INDEX(Trayectorias!$E$15:$G$39,MATCH($A17,Trayectorias!$A$15:$A$39,0),$C$5))+Parametros_PV!$C$17*(100/8)^Parametros_PV!$C$34*INDEX(Trayectorias!$K$15:$M$39,MATCH($A17,Trayectorias!$A$15:$A$39,0),$C$5)+Parametros_PV!$C$18*INDEX(Trayectorias!$K$15:$M$39,MATCH($A17,Trayectorias!$A$15:$A$39,0),$C$5))*Parametros_PV!$C$20 -> 482.72976 | H17: =(Parametros_PV!$C$16*(200/8)^Parametros_PV!$C$33*IF(200<$C$6,INDEX(Trayectorias!$H$15:$J$39,MATCH($A17,Trayectorias!$A$15:$A$39,0),$C$5),INDEX(Trayectorias!$E$15:$G$39,MATCH($A17,Trayectorias!$A$15:$A$39,0),$C$5))+Parametros_PV!$C$17*(200/8)^Parametros_PV!$C$34*INDEX(Trayectorias!$K$15:$M$39,MATCH($A17,Trayectorias!$A$15:$A$39,0),$C$5)+Parametros_PV!$C$18*INDEX(Trayectorias!$K$15:$M$39,MATCH($A17,Trayectorias!$A$15:$A$39,0),$C$5))*Parametros_PV!$C$20 -> 461.28411
A18: 2034 | B18: =(Parametros_PV!$C$16*(1/8)^Parametros_PV!$C$33*IF(1<$C$6,INDEX(Trayectorias!$H$15:$J$39,MATCH($A18,Trayectorias!$A$15:$A$39,0),$C$5),INDEX(Trayectorias!$E$15:$G$39,MATCH($A18,Trayectorias!$A$15:$A$39,0),$C$5))+Parametros_PV!$C$17*(1/8)^Parametros_PV!$C$34*INDEX(Trayectorias!$K$15:$M$39,MATCH($A18,Trayectorias!$A$15:$A$39,0),$C$5)+Parametros_PV!$C$18*INDEX(Trayectorias!$K$15:$M$39,MATCH($A18,Trayectorias!$A$15:$A$39,0),$C$5))*Parametros_PV!$C$20 -> 695.87246 | C18: =(Parametros_PV!$C$16*(5/8)^Parametros_PV!$C$33*IF(5<$C$6,INDEX(Trayectorias!$H$15:$J$39,MATCH($A18,Trayectorias!$A$15:$A$39,0),$C$5),INDEX(Trayectorias!$E$15:$G$39,MATCH($A18,Trayectorias!$A$15:$A$39,0),$C$5))+Parametros_PV!$C$17*(5/8)^Parametros_PV!$C$34*INDEX(Trayectorias!$K$15:$M$39,MATCH($A18,Trayectorias!$A$15:$A$39,0),$C$5)+Parametros_PV!$C$18*INDEX(Trayectorias!$K$15:$M$39,MATCH($A18,Trayectorias!$A$15:$A$39,0),$C$5))*Parametros_PV!$C$20 -> 621.66032 | D18: =(Parametros_PV!$C$16*(10/8)^Parametros_PV!$C$33*IF(10<$C$6,INDEX(Trayectorias!$H$15:$J$39,MATCH($A18,Trayectorias!$A$15:$A$39,0),$C$5),INDEX(Trayectorias!$E$15:$G$39,MATCH($A18,Trayectorias!$A$15:$A$39,0),$C$5))+Parametros_PV!$C$17*(10/8)^Parametros_PV!$C$34*INDEX(Trayectorias!$K$15:$M$39,MATCH($A18,Trayectorias!$A$15:$A$39,0),$C$5)+Parametros_PV!$C$18*INDEX(Trayectorias!$K$15:$M$39,MATCH($A18,Trayectorias!$A$15:$A$39,0),$C$5))*Parametros_PV!$C$20 -> 537.2825 | E18: =(Parametros_PV!$C$16*(20/8)^Parametros_PV!$C$33*IF(20<$C$6,INDEX(Trayectorias!$H$15:$J$39,MATCH($A18,Trayectorias!$A$15:$A$39,0),$C$5),INDEX(Trayectorias!$E$15:$G$39,MATCH($A18,Trayectorias!$A$15:$A$39,0),$C$5))+Parametros_PV!$C$17*(20/8)^Parametros_PV!$C$34*INDEX(Trayectorias!$K$15:$M$39,MATCH($A18,Trayectorias!$A$15:$A$39,0),$C$5)+Parametros_PV!$C$18*INDEX(Trayectorias!$K$15:$M$39,MATCH($A18,Trayectorias!$A$15:$A$39,0),$C$5))*Parametros_PV!$C$20 -> 513.03432 | F18: =(Parametros_PV!$C$16*(50/8)^Parametros_PV!$C$33*IF(50<$C$6,INDEX(Trayectorias!$H$15:$J$39,MATCH($A18,Trayectorias!$A$15:$A$39,0),$C$5),INDEX(Trayectorias!$E$15:$G$39,MATCH($A18,Trayectorias!$A$15:$A$39,0),$C$5))+Parametros_PV!$C$17*(50/8)^Parametros_PV!$C$34*INDEX(Trayectorias!$K$15:$M$39,MATCH($A18,Trayectorias!$A$15:$A$39,0),$C$5)+Parametros_PV!$C$18*INDEX(Trayectorias!$K$15:$M$39,MATCH($A18,Trayectorias!$A$15:$A$39,0),$C$5))*Parametros_PV!$C$20 -> 482.90627 | G18: =(Parametros_PV!$C$16*(100/8)^Parametros_PV!$C$33*IF(100<$C$6,INDEX(Trayectorias!$H$15:$J$39,MATCH($A18,Trayectorias!$A$15:$A$39,0),$C$5),INDEX(Trayectorias!$E$15:$G$39,MATCH($A18,Trayectorias!$A$15:$A$39,0),$C$5))+Parametros_PV!$C$17*(100/8)^Parametros_PV!$C$34*INDEX(Trayectorias!$K$15:$M$39,MATCH($A18,Trayectorias!$A$15:$A$39,0),$C$5)+Parametros_PV!$C$18*INDEX(Trayectorias!$K$15:$M$39,MATCH($A18,Trayectorias!$A$15:$A$39,0),$C$5))*Parametros_PV!$C$20 -> 461.48567 | H18: =(Parametros_PV!$C$16*(200/8)^Parametros_PV!$C$33*IF(200<$C$6,INDEX(Trayectorias!$H$15:$J$39,MATCH($A18,Trayectorias!$A$15:$A$39,0),$C$5),INDEX(Trayectorias!$E$15:$G$39,MATCH($A18,Trayectorias!$A$15:$A$39,0),$C$5))+Parametros_PV!$C$17*(200/8)^Parametros_PV!$C$34*INDEX(Trayectorias!$K$15:$M$39,MATCH($A18,Trayectorias!$A$15:$A$39,0),$C$5)+Parametros_PV!$C$18*INDEX(Trayectorias!$K$15:$M$39,MATCH($A18,Trayectorias!$A$15:$A$39,0),$C$5))*Parametros_PV!$C$20 -> 441.17514
A19: 2035 | B19: =(Parametros_PV!$C$16*(1/8)^Parametros_PV!$C$33*IF(1<$C$6,INDEX(Trayectorias!$H$15:$J$39,MATCH($A19,Trayectorias!$A$15:$A$39,0),$C$5),INDEX(Trayectorias!$E$15:$G$39,MATCH($A19,Trayectorias!$A$15:$A$39,0),$C$5))+Parametros_PV!$C$17*(1/8)^Parametros_PV!$C$34*INDEX(Trayectorias!$K$15:$M$39,MATCH($A19,Trayectorias!$A$15:$A$39,0),$C$5)+Parametros_PV!$C$18*INDEX(Trayectorias!$K$15:$M$39,MATCH($A19,Trayectorias!$A$15:$A$39,0),$C$5))*Parametros_PV!$C$20 -> 670.59454 | C19: =(Parametros_PV!$C$16*(5/8)^Parametros_PV!$C$33*IF(5<$C$6,INDEX(Trayectorias!$H$15:$J$39,MATCH($A19,Trayectorias!$A$15:$A$39,0),$C$5),INDEX(Trayectorias!$E$15:$G$39,MATCH($A19,Trayectorias!$A$15:$A$39,0),$C$5))+Parametros_PV!$C$17*(5/8)^Parametros_PV!$C$34*INDEX(Trayectorias!$K$15:$M$39,MATCH($A19,Trayectorias!$A$15:$A$39,0),$C$5)+Parametros_PV!$C$18*INDEX(Trayectorias!$K$15:$M$39,MATCH($A19,Trayectorias!$A$15:$A$39,0),$C$5))*Parametros_PV!$C$20 -> 599.41009 | D19: =(Parametros_PV!$C$16*(10/8)^Parametros_PV!$C$33*IF(10<$C$6,INDEX(Trayectorias!$H$15:$J$39,MATCH($A19,Trayectorias!$A$15:$A$39,0),$C$5),INDEX(Trayectorias!$E$15:$G$39,MATCH($A19,Trayectorias!$A$15:$A$39,0),$C$5))+Parametros_PV!$C$17*(10/8)^Parametros_PV!$C$34*INDEX(Trayectorias!$K$15:$M$39,MATCH($A19,Trayectorias!$A$15:$A$39,0),$C$5)+Parametros_PV!$C$18*INDEX(Trayectorias!$K$15:$M$39,MATCH($A19,Trayectorias!$A$15:$A$39,0),$C$5))*Parametros_PV!$C$20 -> 513.38298 | E19: =(Parametros_PV!$C$16*(20/8)^Parametros_PV!$C$33*IF(20<$C$6,INDEX(Trayectorias!$H$15:$J$39,MATCH($A19,Trayectorias!$A$15:$A$39,0),$C$5),INDEX(Trayectorias!$E$15:$G$39,MATCH($A19,Trayectorias!$A$15:$A$39,0),$C$5))+Parametros_PV!$C$17*(20/8)^Parametros_PV!$C$34*INDEX(Trayectorias!$K$15:$M$39,MATCH($A19,Trayectorias!$A$15:$A$39,0),$C$5)+Parametros_PV!$C$18*INDEX(Trayectorias!$K$15:$M$39,MATCH($A19,Trayectorias!$A$15:$A$39,0),$C$5))*Parametros_PV!$C$20 -> 490.42125 | F19: =(Parametros_PV!$C$16*(50/8)^Parametros_PV!$C$33*IF(50<$C$6,INDEX(Trayectorias!$H$15:$J$39,MATCH($A19,Trayectorias!$A$15:$A$39,0),$C$5),INDEX(Trayectorias!$E$15:$G$39,MATCH($A19,Trayectorias!$A$15:$A$39,0),$C$5))+Parametros_PV!$C$17*(50/8)^Parametros_PV!$C$34*INDEX(Trayectorias!$K$15:$M$39,MATCH($A19,Trayectorias!$A$15:$A$39,0),$C$5)+Parametros_PV!$C$18*INDEX(Trayectorias!$K$15:$M$39,MATCH($A19,Trayectorias!$A$15:$A$39,0),$C$5))*Parametros_PV!$C$20 -> 461.88088 | G19: =(Parametros_PV!$C$16*(100/8)^Parametros_PV!$C$33*IF(100<$C$6,INDEX(Trayectorias!$H$15:$J$39,MATCH($A19,Trayectorias!$A$15:$A$39,0),$C$5),INDEX(Trayectorias!$E$15:$G$39,MATCH($A19,Trayectorias!$A$15:$A$39,0),$C$5))+Parametros_PV!$C$17*(100/8)^Parametros_PV!$C$34*INDEX(Trayectorias!$K$15:$M$39,MATCH($A19,Trayectorias!$A$15:$A$39,0),$C$5)+Parametros_PV!$C$18*INDEX(Trayectorias!$K$15:$M$39,MATCH($A19,Trayectorias!$A$15:$A$39,0),$C$5))*Parametros_PV!$C$20 -> 441.58138 | H19: =(Parametros_PV!$C$16*(200/8)^Parametros_PV!$C$33*IF(200<$C$6,INDEX(Trayectorias!$H$15:$J$39,MATCH($A19,Trayectorias!$A$15:$A$39,0),$C$5),INDEX(Trayectorias!$E$15:$G$39,MATCH($A19,Trayectorias!$A$15:$A$39,0),$C$5))+Parametros_PV!$C$17*(200/8)^Parametros_PV!$C$34*INDEX(Trayectorias!$K$15:$M$39,MATCH($A19,Trayectorias!$A$15:$A$39,0),$C$5)+Parametros_PV!$C$18*INDEX(Trayectorias!$K$15:$M$39,MATCH($A19,Trayectorias!$A$15:$A$39,0),$C$5))*Parametros_PV!$C$20 -> 422.32759
A20: 2036 | B20: =(Parametros_PV!$C$16*(1/8)^Parametros_PV!$C$33*IF(1<$C$6,INDEX(Trayectorias!$H$15:$J$39,MATCH($A20,Trayectorias!$A$15:$A$39,0),$C$5),INDEX(Trayectorias!$E$15:$G$39,MATCH($A20,Trayectorias!$A$15:$A$39,0),$C$5))+Parametros_PV!$C$17*(1/8)^Parametros_PV!$C$34*INDEX(Trayectorias!$K$15:$M$39,MATCH($A20,Trayectorias!$A$15:$A$39,0),$C$5)+Parametros_PV!$C$18*INDEX(Trayectorias!$K$15:$M$39,MATCH($A20,Trayectorias!$A$15:$A$39,0),$C$5))*Parametros_PV!$C$20 -> 658.36798 | C20: =(Parametros_PV!$C$16*(5/8)^Parametros_PV!$C$33*IF(5<$C$6,INDEX(Trayectorias!$H$15:$J$39,MATCH($A20,Trayectorias!$A$15:$A$39,0),$C$5),INDEX(Trayectorias!$E$15:$G$39,MATCH($A20,Trayectorias!$A$15:$A$39,0),$C$5))+Parametros_PV!$C$17*(5/8)^Parametros_PV!$C$34*INDEX(Trayectorias!$K$15:$M$39,MATCH($A20,Trayectorias!$A$15:$A$39,0),$C$5)+Parametros_PV!$C$18*INDEX(Trayectorias!$K$15:$M$39,MATCH($A20,Trayectorias!$A$15:$A$39,0),$C$5))*Parametros_PV!$C$20 -> 588.70185 | D20: =(Parametros_PV!$C$16*(10/8)^Parametros_PV!$C$33*IF(10<$C$6,INDEX(Trayectorias!$H$15:$J$39,MATCH($A20,Trayectorias!$A$15:$A$39,0),$C$5),INDEX(Trayectorias!$E$15:$G$39,MATCH($A20,Trayectorias!$A$15:$A$39,0),$C$5))+Parametros_PV!$C$17*(10/8)^Parametros_PV!$C$34*INDEX(Trayectorias!$K$15:$M$39,MATCH($A20,Trayectorias!$A$15:$A$39,0),$C$5)+Parametros_PV!$C$18*INDEX(Trayectorias!$K$15:$M$39,MATCH($A20,Trayectorias!$A$15:$A$39,0),$C$5))*Parametros_PV!$C$20 -> 505.2761 | E20: =(Parametros_PV!$C$16*(20/8)^Parametros_PV!$C$33*IF(20<$C$6,INDEX(Trayectorias!$H$15:$J$39,MATCH($A20,Trayectorias!$A$15:$A$39,0),$C$5),INDEX(Trayectorias!$E$15:$G$39,MATCH($A20,Trayectorias!$A$15:$A$39,0),$C$5))+Parametros_PV!$C$17*(20/8)^Parametros_PV!$C$34*INDEX(Trayectorias!$K$15:$M$39,MATCH($A20,Trayectorias!$A$15:$A$39,0),$C$5)+Parametros_PV!$C$18*INDEX(Trayectorias!$K$15:$M$39,MATCH($A20,Trayectorias!$A$15:$A$39,0),$C$5))*Parametros_PV!$C$20 -> 482.74898 | F20: =(Parametros_PV!$C$16*(50/8)^Parametros_PV!$C$33*IF(50<$C$6,INDEX(Trayectorias!$H$15:$J$39,MATCH($A20,Trayectorias!$A$15:$A$39,0),$C$5),INDEX(Trayectorias!$E$15:$G$39,MATCH($A20,Trayectorias!$A$15:$A$39,0),$C$5))+Parametros_PV!$C$17*(50/8)^Parametros_PV!$C$34*INDEX(Trayectorias!$K$15:$M$39,MATCH($A20,Trayectorias!$A$15:$A$39,0),$C$5)+Parametros_PV!$C$18*INDEX(Trayectorias!$K$15:$M$39,MATCH($A20,Trayectorias!$A$15:$A$39,0),$C$5))*Parametros_PV!$C$20 -> 454.74505 | G20: =(Parametros_PV!$C$16*(100/8)^Parametros_PV!$C$33*IF(100<$C$6,INDEX(Trayectorias!$H$15:$J$39,MATCH($A20,Trayectorias!$A$15:$A$39,0),$C$5),INDEX(Trayectorias!$E$15:$G$39,MATCH($A20,Trayectorias!$A$15:$A$39,0),$C$5))+Parametros_PV!$C$17*(100/8)^Parametros_PV!$C$34*INDEX(Trayectorias!$K$15:$M$39,MATCH($A20,Trayectorias!$A$15:$A$39,0),$C$5)+Parametros_PV!$C$18*INDEX(Trayectorias!$K$15:$M$39,MATCH($A20,Trayectorias!$A$15:$A$39,0),$C$5))*Parametros_PV!$C$20 -> 434.82442 | H20: =(Parametros_PV!$C$16*(200/8)^Parametros_PV!$C$33*IF(200<$C$6,INDEX(Trayectorias!$H$15:$J$39,MATCH($A20,Trayectorias!$A$15:$A$39,0),$C$5),INDEX(Trayectorias!$E$15:$G$39,MATCH($A20,Trayectorias!$A$15:$A$39,0),$C$5))+Parametros_PV!$C$17*(200/8)^Parametros_PV!$C$34*INDEX(Trayectorias!$K$15:$M$39,MATCH($A20,Trayectorias!$A$15:$A$39,0),$C$5)+Parametros_PV!$C$18*INDEX(Trayectorias!$K$15:$M$39,MATCH($A20,Trayectorias!$A$15:$A$39,0),$C$5))*Parametros_PV!$C$20 -> 415.92778
A21: 2037 | B21: =(Parametros_PV!$C$16*(1/8)^Parametros_PV!$C$33*IF(1<$C$6,INDEX(Trayectorias!$H$15:$J$39,MATCH($A21,Trayectorias!$A$15:$A$39,0),$C$5),INDEX(Trayectorias!$E$15:$G$39,MATCH($A21,Trayectorias!$A$15:$A$39,0),$C$5))+Parametros_PV!$C$17*(1/8)^Parametros_PV!$C$34*INDEX(Trayectorias!$K$15:$M$39,MATCH($A21,Trayectorias!$A$15:$A$39,0),$C$5)+Parametros_PV!$C$18*INDEX(Trayectorias!$K$15:$M$39,MATCH($A21,Trayectorias!$A$15:$A$39,0),$C$5))*Parametros_PV!$C$20 -> 646.45218 | C21: =(Parametros_PV!$C$16*(5/8)^Parametros_PV!$C$33*IF(5<$C$6,INDEX(Trayectorias!$H$15:$J$39,MATCH($A21,Trayectorias!$A$15:$A$39,0),$C$5),INDEX(Trayectorias!$E$15:$G$39,MATCH($A21,Trayectorias!$A$15:$A$39,0),$C$5))+Parametros_PV!$C$17*(5/8)^Parametros_PV!$C$34*INDEX(Trayectorias!$K$15:$M$39,MATCH($A21,Trayectorias!$A$15:$A$39,0),$C$5)+Parametros_PV!$C$18*INDEX(Trayectorias!$K$15:$M$39,MATCH($A21,Trayectorias!$A$15:$A$39,0),$C$5))*Parametros_PV!$C$20 -> 578.26321 | D21: =(Parametros_PV!$C$16*(10/8)^Parametros_PV!$C$33*IF(10<$C$6,INDEX(Trayectorias!$H$15:$J$39,MATCH($A21,Trayectorias!$A$15:$A$39,0),$C$5),INDEX(Trayectorias!$E$15:$G$39,MATCH($A21,Trayectorias!$A$15:$A$39,0),$C$5))+Parametros_PV!$C$17*(10/8)^Parametros_PV!$C$34*INDEX(Trayectorias!$K$15:$M$39,MATCH($A21,Trayectorias!$A$15:$A$39,0),$C$5)+Parametros_PV!$C$18*INDEX(Trayectorias!$K$15:$M$39,MATCH($A21,Trayectorias!$A$15:$A$39,0),$C$5))*Parametros_PV!$C$20 -> 497.35483 | E21: =(Parametros_PV!$C$16*(20/8)^Parametros_PV!$C$33*IF(20<$C$6,INDEX(Trayectorias!$H$15:$J$39,MATCH($A21,Trayectorias!$A$15:$A$39,0),$C$5),INDEX(Trayectorias!$E$15:$G$39,MATCH($A21,Trayectorias!$A$15:$A$39,0),$C$5))+Parametros_PV!$C$17*(20/8)^Parametros_PV!$C$34*INDEX(Trayectorias!$K$15:$M$39,MATCH($A21,Trayectorias!$A$15:$A$39,0),$C$5)+Parametros_PV!$C$18*INDEX(Trayectorias!$K$15:$M$39,MATCH($A21,Trayectorias!$A$15:$A$39,0),$C$5))*Parametros_PV!$C$20 -> 475.25144 | F21: =(Parametros_PV!$C$16*(50/8)^Parametros_PV!$C$33*IF(50<$C$6,INDEX(Trayectorias!$H$15:$J$39,MATCH($A21,Trayectorias!$A$15:$A$39,0),$C$5),INDEX(Trayectorias!$E$15:$G$39,MATCH($A21,Trayectorias!$A$15:$A$39,0),$C$5))+Parametros_PV!$C$17*(50/8)^Parametros_PV!$C$34*INDEX(Trayectorias!$K$15:$M$39,MATCH($A21,Trayectorias!$A$15:$A$39,0),$C$5)+Parametros_PV!$C$18*INDEX(Trayectorias!$K$15:$M$39,MATCH($A21,Trayectorias!$A$15:$A$39,0),$C$5))*Parametros_PV!$C$20 -> 447.77058 | G21: =(Parametros_PV!$C$16*(100/8)^Parametros_PV!$C$33*IF(100<$C$6,INDEX(Trayectorias!$H$15:$J$39,MATCH($A21,Trayectorias!$A$15:$A$39,0),$C$5),INDEX(Trayectorias!$E$15:$G$39,MATCH($A21,Trayectorias!$A$15:$A$39,0),$C$5))+Parametros_PV!$C$17*(100/8)^Parametros_PV!$C$34*INDEX(Trayectorias!$K$15:$M$39,MATCH($A21,Trayectorias!$A$15:$A$39,0),$C$5)+Parametros_PV!$C$18*INDEX(Trayectorias!$K$15:$M$39,MATCH($A21,Trayectorias!$A$15:$A$39,0),$C$5))*Parametros_PV!$C$20 -> 428.21938 | H21: =(Parametros_PV!$C$16*(200/8)^Parametros_PV!$C$33*IF(200<$C$6,INDEX(Trayectorias!$H$15:$J$39,MATCH($A21,Trayectorias!$A$15:$A$39,0),$C$5),INDEX(Trayectorias!$E$15:$G$39,MATCH($A21,Trayectorias!$A$15:$A$39,0),$C$5))+Parametros_PV!$C$17*(200/8)^Parametros_PV!$C$34*INDEX(Trayectorias!$K$15:$M$39,MATCH($A21,Trayectorias!$A$15:$A$39,0),$C$5)+Parametros_PV!$C$18*INDEX(Trayectorias!$K$15:$M$39,MATCH($A21,Trayectorias!$A$15:$A$39,0),$C$5))*Parametros_PV!$C$20 -> 409.67102
... A34: 2050 | B34: =(Parametros_PV!$C$16*(1/8)^Parametros_PV!$C$33*IF(1<$C$6,INDEX(Trayectorias!$H$15:$J$39,MATCH($A34,Trayectorias!$A$15:$A$39,0),$C$5),INDEX(Trayectorias!$E$15:$G$39,MATCH($A34,Trayectorias!$A$15:$A$39,0),$C$5))+Parametros_PV!$C$17*(1/8)^Parametros_PV!$C$34*INDEX(Trayectorias!$K$15:$M$39,MATCH($A34,Trayectorias!$A$15:$A$39,0),$C$5)+Parametros_PV!$C$18*INDEX(Trayectorias!$K$15:$M$39,MATCH($A34,Trayectorias!$A$15:$A$39,0),$C$5))*Parametros_PV!$C$20 -> 516.10479 | C34: =(Parametros_PV!$C$16*(5/8)^Parametros_PV!$C$33*IF(5<$C$6,INDEX(Trayectorias!$H$15:$J$39,MATCH($A34,Trayectorias!$A$15:$A$39,0),$C$5),INDEX(Trayectorias!$E$15:$G$39,MATCH($A34,Trayectorias!$A$15:$A$39,0),$C$5))+Parametros_PV!$C$17*(5/8)^Parametros_PV!$C$34*INDEX(Trayectorias!$K$15:$M$39,MATCH($A34,Trayectorias!$A$15:$A$39,0),$C$5)+Parametros_PV!$C$18*INDEX(Trayectorias!$K$15:$M$39,MATCH($A34,Trayectorias!$A$15:$A$39,0),$C$5))*Parametros_PV!$C$20 -> 463.87448 | D34: =(Parametros_PV!$C$16*(10/8)^Parametros_PV!$C$33*IF(10<$C$6,INDEX(Trayectorias!$H$15:$J$39,MATCH($A34,Trayectorias!$A$15:$A$39,0),$C$5),INDEX(Trayectorias!$E$15:$G$39,MATCH($A34,Trayectorias!$A$15:$A$39,0),$C$5))+Parametros_PV!$C$17*(10/8)^Parametros_PV!$C$34*INDEX(Trayectorias!$K$15:$M$39,MATCH($A34,Trayectorias!$A$15:$A$39,0),$C$5)+Parametros_PV!$C$18*INDEX(Trayectorias!$K$15:$M$39,MATCH($A34,Trayectorias!$A$15:$A$39,0),$C$5))*Parametros_PV!$C$20 -> 409.17823 | E34: =(Parametros_PV!$C$16*(20/8)^Parametros_PV!$C$33*IF(20<$C$6,INDEX(Trayectorias!$H$15:$J$39,MATCH($A34,Trayectorias!$A$15:$A$39,0),$C$5),INDEX(Trayectorias!$E$15:$G$39,MATCH($A34,Trayectorias!$A$15:$A$39,0),$C$5))+Parametros_PV!$C$17*(20/8)^Parametros_PV!$C$34*INDEX(Trayectorias!$K$15:$M$39,MATCH($A34,Trayectorias!$A$15:$A$39,0),$C$5)+Parametros_PV!$C$18*INDEX(Trayectorias!$K$15:$M$39,MATCH($A34,Trayectorias!$A$15:$A$39,0),$C$5))*Parametros_PV!$C$20 -> 391.71922 | F34: =(Parametros_PV!$C$16*(50/8)^Parametros_PV!$C$33*IF(50<$C$6,INDEX(Trayectorias!$H$15:$J$39,MATCH($A34,Trayectorias!$A$15:$A$39,0),$C$5),INDEX(Trayectorias!$E$15:$G$39,MATCH($A34,Trayectorias!$A$15:$A$39,0),$C$5))+Parametros_PV!$C$17*(50/8)^Parametros_PV!$C$34*INDEX(Trayectorias!$K$15:$M$39,MATCH($A34,Trayectorias!$A$15:$A$39,0),$C$5)+Parametros_PV!$C$18*INDEX(Trayectorias!$K$15:$M$39,MATCH($A34,Trayectorias!$A$15:$A$39,0),$C$5))*Parametros_PV!$C$20 -> 369.97458 | G34: =(Parametros_PV!$C$16*(100/8)^Parametros_PV!$C$33*IF(100<$C$6,INDEX(Trayectorias!$H$15:$J$39,MATCH($A34,Trayectorias!$A$15:$A$39,0),$C$5),INDEX(Trayectorias!$E$15:$G$39,MATCH($A34,Trayectorias!$A$15:$A$39,0),$C$5))+Parametros_PV!$C$17*(100/8)^Parametros_PV!$C$34*INDEX(Trayectorias!$K$15:$M$39,MATCH($A34,Trayectorias!$A$15:$A$39,0),$C$5)+Parametros_PV!$C$18*INDEX(Trayectorias!$K$15:$M$39,MATCH($A34,Trayectorias!$A$15:$A$39,0),$C$5))*Parametros_PV!$C$20 -> 354.47713 | H34: =(Parametros_PV!$C$16*(200/8)^Parametros_PV!$C$33*IF(200<$C$6,INDEX(Trayectorias!$H$15:$J$39,MATCH($A34,Trayectorias!$A$15:$A$39,0),$C$5),INDEX(Trayectorias!$E$15:$G$39,MATCH($A34,Trayectorias!$A$15:$A$39,0),$C$5))+Parametros_PV!$C$17*(200/8)^Parametros_PV!$C$34*INDEX(Trayectorias!$K$15:$M$39,MATCH($A34,Trayectorias!$A$15:$A$39,0),$C$5)+Parametros_PV!$C$18*INDEX(Trayectorias!$K$15:$M$39,MATCH($A34,Trayectorias!$A$15:$A$39,0),$C$5))*Parametros_PV!$C$20 -> 339.75234
A36: La curva es continua en escala: no hay saltos entre tramos. El único quiebre es de trayectoria, cuando por debajo de la escala de corte se usa la senda de commercial PV en lugar de la de utility.

Sheet Curva_Hibrido
A1: Configurador de planta híbrida
A2: Suma de las dos curvas menos el ahorro de infraestructura compartida
A4: Año | C4: 2030
A5: Escenario | C5: Medio
A6: Potencia solar (MWp DC) | C6: 20
A7: Energía nominal BESS (MWh) | C7: 40
A8: Duración BESS (h) | C8: 4
A9: Segmento BESS | C9: B3
A10: Factor de sobredimensionamiento | C10: 1.05
A11: Ahorro por infraestructura compartida | C11: 0.03
A13: Columna de escenario | C13: =MATCH($C$5,{"Bajo","Medio","Alto"},0) -> 2
A14: Potencia BESS (MW) | C14: =C7/C8 -> 10
A15: CAPEX solar (USD/kWp DC) | C15: =(Parametros_PV!$C$16*($C$6/8)^Parametros_PV!$C$33*IF($C$6<Curva_PV!$C$6,INDEX(Trayectorias!$H$15:$J$39,MATCH($C$4,Trayectorias!$A$15:$A$39,0),$C$13),INDEX(Trayectorias!$E$15:$G$39,MATCH($C$4,Trayectorias!$A$15:$A$39,0),$C$13))+Parametros_PV!$C$17*($C$6/8)^Parametros_PV!$C$34*INDEX(Trayectorias!$K$15:$M$39,MATCH($C$4,Trayectorias!$A$15:$A$39,0),$C$13)+Parametros_PV!$C$18*INDEX(Trayectorias!$K$15:$M$39,MATCH($C$4,Trayectorias!$A$15:$A$39,0),$C$13))*Parametros_PV!$C$20 -> 620.19569
A16: CAPEX solar (USD) | C16: =C15*C6*1000 -> 12403914
A17: CAPEX BESS (USD/kWh nominal) | C17: =(INDEX(Parametros_BESS!$D$5:$D$8,MATCH($C$9,Parametros_BESS!$A$5:$A$8,0))*(1+MAX(0,1/$C$8-Suministro_BESS!$A$13)*Suministro_BESS!$B$13)*$C$10*INDEX(Trayectorias!$B$15:$D$39,MATCH($C$4,Trayectorias!$A$15:$A$39,0),$C$13)+INDEX(Parametros_BESS!$E$5:$E$8,MATCH($C$9,Parametros_BESS!$A$5:$A$8,0))*INDEX(Trayectorias!$K$15:$M$39,MATCH($C$4,Trayectorias!$A$15:$A$39,0),$C$13)+INDEX(Parametros_BESS!$F$5:$F$8,MATCH($C$9,Parametros_BESS!$A$5:$A$8,0))*INDEX(Trayectorias!$K$15:$M$39,MATCH($C$4,Trayectorias!$A$15:$A$39,0),$C$13)/$C$8+INDEX(Parametros_BESS!$G$5:$G$8,MATCH($C$9,Parametros_BESS!$A$5:$A$8,0))*INDEX(Trayectorias!$K$15:$M$39,MATCH($C$4,Trayectorias!$A$15:$A$39,0),$C$13)/($C$7*1000))*(1+INDEX(Parametros_BESS!$H$5:$H$8,MATCH($C$9,Parametros_BESS!$A$5:$A$8,0)))*(1+INDEX(Parametros_BESS!$I$5:$I$8,MATCH($C$9,Parametros_BESS!$A$5:$A$8,0)))/(1-INDEX(Parametros_BESS!$J$5:$J$8,MATCH($C$9,Parametros_BESS!$A$5:$A$8,0))) -> 166.13281
A18: CAPEX BESS (USD) | C18: =C17*C7*1000 -> 6645312.6
A19: Suma simple (USD) | C19: =C16+C18 -> 19049226
A20: Ahorro por infraestructura compartida (USD) | C20: =-C19*C11 -> -571476.79
A21: CAPEX híbrido total (USD) | C21: =C19+C20 -> 18477750
A22: CAPEX híbrido (USD/kWp solar) | C22: =C21/(C6*1000) -> 923.88748

Sheet Validacion
A1: Contraste con referencias internacionales
A2: El modelo colombiano frente a los benchmarks publicados
A4: Referencia | B4: Año | C4: Publicado | D4: Modelo | E4: Dif. | F4: Comentario
A5: NREL, sistema de almacenamiento de 4 h, EE. UU. | B5: 2024 | C5: 334 | D5: =INDEX(Curva_BESS!$E$19:$E$43,MATCH(2026,Curva_BESS!$A$19:$A$43,0)) -> 178.6002 | E5: =D5/C5-1 -> -0.46526886 | F5: El modelo de NREL incluye el arancel de la Sección 301 sobre celdas chinas, un arancel general de 3,4 % y 5,8 % de impuesto a las ventas. Nada de eso aplica en Colombia, donde la Ley 1715 excluye el IVA sobre el equipo.
A6: IRENA, almacenamiento en baterías, promedio global | B6: 2024 | C6: 192 | D6: =INDEX(Curva_BESS!$E$19:$E$43,MATCH(2026,Curva_BESS!$A$19:$A$43,0)) -> 178.6002 | E6: =D6/C6-1 -> -0.069790628 | F6: Alineación cercana. Es la referencia más comparable con una cotización llave en mano colombiana.
A7: IRENA, solar utility-scale, costo total instalado global | B7: 2024 | C7: 691 | D7: =INDEX(Curva_PV!$G$10:$G$34,MATCH(2026,Curva_PV!$A$10:$A$34,0)) -> 679.20121 | E7: =D7/C7-1 -> -0.017074943 | F7: A 100 MWp el modelo queda cerca del promedio global. IRENA reporta 1.058 en EE. UU., 779 en Europa, 591 en China y 525 en India.
A8: NREL, componente de energía del almacenamiento | B8: 2024 | C8: 240.8 | D8: =Parametros_BESS!$D$7*(1+Parametros_BESS!$H$7)*(1+Parametros_BESS!$I$7)/(1-Parametros_BESS!$J$7) -> 124.90032 | E8: =D8/C8-1 -> -0.48131097 | F8: Es donde pega el arancel estadounidense sobre celdas chinas. El suministro colombiano medido en tres cotizaciones independientes está en unos 93 USD/kWh antes de indirectos y margen.
A9: Suministro de baterías medido, tres cotizaciones | B9: 2026 | C9: 88 | D9: =Parametros_BESS!$D$7 -> 93.4 | E9: =D9/C9-1 -> 0.061363636 | F9: S-1 a 87,4 CIF en octubre de 2025 y el contenedor de R3 a 88,2 DAP en junio de 2026. El parámetro del modelo se calibra como residuo del ancla de R3 y coincide con lo medido.
